Workbook

Sheet SYNTHESE
A1: Product Info Assistant : benchmark de 1 500 questions
A2: Campagne du 14/10 au 16/10/2026 · 300 conversations de 5 questions · un chat neuf par conversation. Tous les chiffres sont calculés par formules sur l’onglet DONNEES.
A3: Indicateur | B3: Valeur | C3: Commentaire
A4: Questions du benchmark | B4: =COUNTA(DONNEES!$A$2:$A$1501) -> 1500
A5: Réponses capturées | B5: =B4-COUNTIFS(DONNEES!$L$2:$L$1501,"Non capturé") -> 1485 | C5: Conversations non capturées : C048, C050, C052
A6: Questions à valeur connue notées | B6: =COUNTIFS(DONNEES!$H$2:$H$1501,"NOTABLE",DONNEES!$L$2:$L$1501,"Correct")+COUNTIFS(DONNEES!$H$2:$H$1501,"NOTABLE",DONNEES!$L$2:$L$1501,"Pas d’info à tort")+COUNTIFS(DONNEES!$H$2:$H$1501,"NOTABLE",DONNEES!$L$2:$L$1501,"Incorrect")+COUNTIFS(DONNEES!$H$2:$H$1501,"NOTABLE",DONNEES!$L$2:$L$1501,"Hors sujet") -> 1365 | C6: Dénominateur des taux ci-dessous (statut NOTABLE)
A7: Réponses justes | B7: =COUNTIFS(DONNEES!$H$2:$H$1501,"NOTABLE",DONNEES!$L$2:$L$1501,"Correct")/B6 -> 0.81098901 | C7: IC 95 % (bootstrap par conversation) : 78,0 % – 84,0 %
A8: « Aucune information » alors que la donnée existe | B8: =COUNTIFS(DONNEES!$H$2:$H$1501,"NOTABLE",DONNEES!$L$2:$L$1501,"Pas d’info à tort")/B6 -> 0.13626374 | C8: Défaut principal
A9: Valeurs fausses | B9: =COUNTIFS(DONNEES!$H$2:$H$1501,"NOTABLE",DONNEES!$L$2:$L$1501,"Incorrect")/B6 -> 0.035897436 | C9: Dont réponses sur un autre fonds : voir ERREURS
A10: Réponses hors sujet | B10: =COUNTIFS(DONNEES!$H$2:$H$1501,"NOTABLE",DONNEES!$L$2:$L$1501,"Hors sujet")/B6 -> 0.016849817 | C10: « Quel scope de recherche ? », question non reçue, réponse vide
A11: Justesse quand l’agent donne une valeur | B11: =COUNTIFS(DONNEES!$H$2:$H$1501,"NOTABLE",DONNEES!$L$2:$L$1501,"Correct")/(COUNTIFS(DONNEES!$H$2:$H$1501,"NOTABLE",DONNEES!$L$2:$L$1501,"Correct")+COUNTIFS(DONNEES!$H$2:$H$1501,"NOTABLE",DONNEES!$L$2:$L$1501,"Incorrect")) -> 0.95761246 | C11: IC 95 % : 94,2 % – 97,1 %
A12: Abstention correcte sur cellule vide | B12: =COUNTIFS(DONNEES!$L$2:$L$1501,"Abstention correcte")/(COUNTIFS(DONNEES!$L$2:$L$1501,"Abstention correcte")+COUNTIFS(DONNEES!$L$2:$L$1501,"Valeur sur cellule vide")) -> 0.96521739 | C12: Cellules vides dans la base : l’agent n’invente pas
A13: Latence moyenne (s) | B13: =AVERAGE(DONNEES!$O$2:$O$1501) -> 18.452727 | C13: Médiane : 12.4 s · premier message : 34 s de médiane
A14: Chats ouverts | B14: =COUNTA(TENTATIVES!$A$2:$A$422) -> 421
A15: Chats interrompus | B15: =COUNTIFS(TENTATIVES!$D$2:$D$422,"FAILED") -> 121 | C15: 117 sans réponse au premier message en 6 minutes
A16: Justes, septembre (mêmes questions) | B16: =COUNTIFS(DONNEES!$H$2:$H$1501,"NOTABLE",DONNEES!$S$2:$S$1501,"Oui",DONNEES!$R$2:$R$1501,"Correct")/(COUNTIFS(DONNEES!$H$2:$H$1501,"NOTABLE",DONNEES!$S$2:$S$1501,"Oui",DONNEES!$R$2:$R$1501,"Correct")+COUNTIFS(DONNEES!$H$2:$H$1501,"NOTABLE",DONNEES!$S$2:$S$1501,"Oui",DONNEES!$R$2:$R$1501,"Pas d’info à tort")+COUNTIFS(DONNEES!$H$2:$H$1501,"NOTABLE",DONNEES!$S$2:$S$1501,"Oui",DONNEES!$R$2:$R$1501,"Incorrect")+COUNTIFS(DONNEES!$H$2:$H$1501,"NOTABLE",DONNEES!$S$2:$S$1501,"Oui",DONNEES!$R$2:$R$1501,"Hors sujet")) -> 0.86011342 | C16: Campagne du 29/09 (100 questions par chat), renotée avec les mêmes règles
A17: Justes, octobre (mêmes questions) | B17: =COUNTIFS(DONNEES!$H$2:$H$1501,"NOTABLE",DONNEES!$S$2:$S$1501,"Oui",DONNEES!$L$2:$L$1501,"Correct")/(COUNTIFS(DONNEES!$H$2:$H$1501,"NOTABLE",DONNEES!$L$2:$L$1501,"Correct",DONNEES!$S$2:$S$1501,"Oui")+COUNTIFS(DONNEES!$H$2:$H$1501,"NOTABLE",DONNEES!$L$2:$L$1501,"Pas d’info à tort",DONNEES!$S$2:$S$1501,"Oui")+COUNTIFS(DONNEES!$H$2:$H$1501,"NOTABLE",DONNEES!$L$2:$L$1501,"Incorrect",DONNEES!$S$2:$S$1501,"Oui")+COUNTIFS(DONNEES!$H$2:$H$1501,"NOTABLE",DONNEES!$L$2:$L$1501,"Hors sujet",DONNEES!$S$2:$S$1501,"Oui")) -> 0.8317757 | C17: Un chat neuf par conversation
A18: Questions qui changent de verdict | B18: =1-(COMPARAISON_SEPT!B20+COMPARAISON_SEPT!C21+COMPARAISON_SEPT!D22+COMPARAISON_SEPT!E23)/SUM(COMPARAISON_SEPT!B20:E23) -> 0.16888046 | C18: Entre septembre et octobre, questions notées dans les deux campagnes
A20: Répartition des verdicts
A21: Verdict | B21: Réponses
A22: Correct | B22: =COUNTIFS(DONNEES!$L$2:$L$1501,"Correct") -> 1107
A23: Pas d’info à tort | B23: =COUNTIFS(DONNEES!$L$2:$L$1501,"Pas d’info à tort") -> 186
A24: Incorrect | B24: =COUNTIFS(DONNEES!$L$2:$L$1501,"Incorrect") -> 49
A25: Hors sujet | B25: =COUNTIFS(DONNEES!$L$2:$L$1501,"Hors sujet") -> 26
A26: Abstention correcte | B26: =COUNTIFS(DONNEES!$L$2:$L$1501,"Abstention correcte") -> 111
A27: Valeur sur cellule vide | B27: =COUNTIFS(DONNEES!$L$2:$L$1501,"Valeur sur cellule vide") -> 4
A28: Échec technique | B28: =COUNTIFS(DONNEES!$L$2:$L$1501,"Échec technique") -> 2
A29: Non capturé | B29: =COUNTIFS(DONNEES!$L$2:$L$1501,"Non capturé") -> 15

Sheet LISEZ-MOI
A1: Lisez-moi
A3: Onglets
A4: SYNTHESE | B4: Chiffres clés et répartition des verdicts.
A5: DONNEES | B5: Une ligne par question : question, valeur attendue, réponse, verdict, motif, latence, verdict de septembre. Filtrable.
A6: PAR_FAMILLE / TOUR / CHAMP / FONDS / GROUPE | B6: Résultats par dimension, avec graphique pour familles et tours.
A7: CROISEMENT | B7: Famille × tour (% correct) et famille × verdict (nombres).
A8: COMPARAISON_SEPT | B8: Mêmes questions en septembre et en octobre, et passage de verdict de l’une à l’autre.
A9: ERREURS | B9: Valeurs fausses et réponses hors sujet, classées par type.
A10: COLLECTE / TENTATIVES | B10: Chats ouverts et interrompus par heure, latence par tour, détail des tentatives.
A12: Verdicts
A13: Correct | B13: La valeur de la base est restituée (équivalences FR / EN acceptées).
A14: Pas d’info à tort | B14: L’agent dit ne pas avoir la donnée alors qu’elle est renseignée.
A15: Incorrect | B15: Autre valeur, champ voisin, ou réponse portant sur un autre fonds.
A16: Hors sujet | B16: L’agent ne traite pas la question : demande de « scope de recherche », question non reçue, réponse vide, définition générique.
A17: Abstention correcte | B17: Cellule vide dans la base, l’agent ne donne pas de valeur.
A18: Valeur sur cellule vide | B18: Cellule vide dans la base, l’agent affirme une valeur.
A19: Échec technique | B19: Message d’erreur de la plateforme.
A20: Non capturé | B20: Question non capturée (conversation interrompue 3 fois).
A22: Taux | B22: Calculés sur les questions à valeur connue (statut NOTABLE) notées Correct, « Aucune info », Valeur fausse ou Hors sujet.
A23: Source du verdict | B23: « Règles » : notation automatique. « Revue des écarts » : 68 cas ambigus ou réponses sur un autre fonds.
A24: Relecture | B24: Pour corriger un verdict, modifier la colonne « Verdict » de DONNEES : tous les onglets se recalculent.
A25: Familles de champs | B25: Gérants et dates de gestion : portfolio manager, portfolio backup, start date; Intervenants : depositary, custodian, centralizing, transfer agent, administrator, auditor, commissaire, investment manager, delegation, sponsoring, management company, promoter; Identifiants : isin, lei, amf code, code; Juridique et réglementaire : legal form, regulation, umbrella, domicil, priips, eet fund, sub-regulation, fund of funds, feeder, status, statut, internal classification, amf classification; Risque : risk, sri, volatility, liquidity, counterparty, credit risk; ESG / EET : esg, sfdr, eet, pai, taxonomy, article 29, label, finansol, thematic, sustainab, \bsi\b; Frais et coûts : fee, cost, tarification, rétrocession, retrocession, high water, performance; Expertise et gamme : expertise, asset class, fund range, region, benchmark, investment universe; Textes longs : objective, allocation, investor profile, strategy; Dates et VL : date, nav, closing, period, maturity

Sheet DONNEES
A1: ID question | B1: Conversation | C1: Tour | D1: Groupe | E1: Famille de champs | F1: Produit | G1: Champ | H1: Statut GT | I1: Question posée | J1: Valeur attendue (base) | K1: Réponse de l’agent | L1: Verdict | M1: Motif | N1: Source du verdict | O1: Latence (s) | P1: Tentative | Q1: Capture (heure de Paris) | R1: Verdict septembre | S1: Comparable septembre | T1: Évolution
A2: Q0001 | B2: C001 | C2: 1 | D2: PRIORITAIRE | E2: Gérants et dates de gestion | F2: R-co Target 2028 IG | G2: Portfolio Manager | H2: NOTABLE | I2: Je prépare une fiche sur R-co Target 2028 IG : peux-tu me donner le nom du gérant principal ? | J2: PETIT Emmanuel | K2: Résultat Information trouvée Le gérant principal du fonds « R-co Target 2028 IG » (version en statut Production) est : Emmanuel PETIT. Détails complémentaires Aucune information complémentaire pertinente pour cette demande. | L2: Correct | M2: mots (ordre libre) | N2: Règles | O2: 60.48 | P2: 1 | Q2: 46309.784 | R2: Correct | S2: Oui | T2: =IF(S2="Oui",IF(R2=L2,"Identique","Changé"),"") -> Identique
A3: Q0002 | B3: C001 | C3: 2 | D3: PRIORITAIRE | E3: Gérants et dates de gestion | F3: R-co Target 2028 IG | G3: Portfolio Manager backup 1 | H3: NOTABLE | I3: Au passage, qui figure comme premier gérant de renfort ? | J3: LOMNE Philippe | K3: Résultat Information trouvée Le premier gérant de renfort du fonds « R-co Target 2028 IG » (statut Production) est Philippe LOMNE. Détails complémentaires Aucune information complémentaire pertinente pour cette demande. | L3: Correct | M3: mots (ordre libre) | N3: Règles | O3: 12.74 | P3: 1 | Q3: 46309.784 | R3: Correct | S3: Oui | T3: =IF(S3="Oui",IF(R3=L3,"Identique","Changé"),"") -> Identique
A4: Q0003 | B4: C001 | C4: 3 | D4: PRIORITAIRE | E4: Juridique et réglementaire | F4: R-co Strategic Metals and Mining | G4: Legal Form | H4: NOTABLE | I4: Je passe à R-co Strategic Metals and Mining : est-ce que tu as sa forme juridique ? | J4: SICAV | K4: Résultat Information trouvée La forme juridique du fonds « R-co Strategic Metals and Mining » est : SICAV. Détails complémentaires Aucune information complémentaire pertinente pour cette demande. | L4: Correct | M4: texte | N4: Règles | O4: 8.9 | P4: 1 | Q4: 46309.784 | R4: Correct | S4: Oui | T4: =IF(S4="Oui",IF(R4=L4,"Identique","Changé"),"") -> Identique
A5: Q0004 | B5: C001 | C5: 4 | D5: PRIORITAIRE | E5: ESG / EET | F5: R-co Strategic Metals and Mining | G5: ESG - SFDR Article | H5: NOTABLE | I5: Sans changer de fonds, il relève de quel article SFDR ? | J5: Article 8 | K5: Résultat Information trouvée Le fonds « R-co Strategic Metals and Mining » relève de l’Article 8 du règlement SFDR. Détails complémentaires Aucune information complémentaire pertinente pour cette demande. | L5: Correct | M5: texte | N5: Règles | O5: 11.01 | P5: 1 | Q5: 46309.784 | R5: Correct | S5: Oui | T5: =IF(S5="Oui",IF(R5=L5,"Identique","Changé"),"") -> Identique
A6: Q0005 | B6: C001 | C6: 5 | D6: PRIORITAIRE | E6: Intervenants | F6: R-co Target 2028 IG | G6: Depositary | H6: NOTABLE | I6: Je reviens à R-co Target 2028 IG : quel établissement assure le dépôt ? Réponds uniquement sur ce point. | J6: Rothschild & Co Martin Maurel | K6: Rothschild & Co Martin Maurel. | L6: Correct | M6: texte | N6: Règles | O6: 12.01 | P6: 1 | Q6: 46309.785 | R6: Correct | S6: Oui | T6: =IF(S6="Oui",IF(R6=L6,"Identique","Changé"),"") -> Identique
A7: Q0006 | B7: C002 | C7: 1 | D7: CONTRASTE | E7: Juridique et réglementaire | F7: Argosphère | G7: Legal Form | H7: NOTABLE | I7: Pour Argosphère, quelle forme juridique est indiquée ? | J7: Unit Trust | K7: Résultat Information trouvée Pour le fonds « Argosphère », la forme juridique indiquée est : FCP (Fonds Commun de Placement). Détails complémentaires Le fonds Argosphère est présent en statut Production dans le référentiel. | L7: Correct | M7: texte | N7: Règles | O7: 49.27 | P7: 3 | Q7: 46309.795 | R7: Correct | S7: Oui | T7: =IF(S7="Oui",IF(R7=L7,"Identique","Changé"),"") -> Identique
A8: Q0007 | B8: C002 | C8: 2 | D8: CONTRASTE | E8: Juridique et réglementaire | F8: Argosphère | G8: Applicable UCI Regulation | H8: NOTABLE | I8: Pour compléter la fiche, quelle réglementation OPC lui est applicable ? | J8: UCITS | K8: Résultat Information trouvée Pour le fonds « Argosphère », la réglementation OPC applicable est : OPCVM. | L8: Correct | M8: texte | N8: Règles | O8: 7.6 | P8: 3 | Q8: 46309.795 | R8: Correct | S8: Oui | T8: =IF(S8="Oui",IF(R8=L8,"Identique","Changé"),"") -> Identique
A9: Q0008 | B9: C002 | C9: 3 | D9: CONTRASTE | E9: Juridique et réglementaire | F9: Argosphère | G9: Domiciliation | H9: NOTABLE | I9: Sans changer de fonds, où est-il domicilié ? | J9: France | K9: Résultat Information trouvée Le fonds « Argosphère » est domicilié en France. Détails complémentaires Sa forme juridique est FCP et sa réglementation applicable est OPCVM. | L9: Correct | M9: texte | N9: Règles | O9: 7.69 | P9: 3 | Q9: 46309.795 | R9: Correct | S9: Oui | T9: =IF(S9="Oui",IF(R9=L9,"Identique","Changé"),"") -> Identique
A10: Q0009 | B10: C002 | C10: 4 | D10: CONTRASTE | E10: Gérants et dates de gestion | F10: Argosphère | G10: Portfolio Manager backup 2 | H10: EXPLORATOIRE | I10: Et pour ce même produit, qui est indiqué comme deuxième gérant secondaire ? | J10: nan | K10: Résultat Information trouvée Aucun deuxième gérant secondaire n'est renseigné pour le fonds « Argosphère ». Détails complémentaires Le champ correspondant au deuxième gérant secondaire ne contient pas de valeur pour ce produit dans le référentiel. | L10: Abstention correcte | M10: cellule vide, l'agent n'invente pas | N10: Règles | O10: 10.12 | P10: 3 | Q10: 46309.795 | R10: Abstention correcte | S10: Oui | T10: =IF(S10="Oui",IF(R10=L10,"Identique","Changé"),"") -> Identique
A11: Q0010 | B11: C002 | C11: 5 | D11: CONTRASTE | E11: Risque | F11: Argosphère | G11: Official Risk Scale | H11: NOTABLE | I11: Autre point sur ce fonds : quel niveau est indiqué sur l’échelle officielle de risque ? | J11: 3 | K11: Résultat Information trouvée Aucun niveau n'est renseigné pour l’échelle officielle de risque du fonds « Argosphère ». Détails complémentaires Le champ correspondant à l’échelle officielle de risque est vide dans le référentiel pour ce fonds. | L11: Pas d’info à tort | M11: l'agent dit ne pas avoir la donnée | N11: Règles | O11: 11.13 | P11: 3 | Q11: 46309.796 | S11: Non | T11: =IF(S11="Oui",IF(R11=L11,"Identique","Changé"),"")
A12: Q0011 | B12: C003 | C12: 1 | D12: PRIORITAIRE | E12: Juridique et réglementaire | F12: R-co Valor 4Change Global Equity | G12: Legal Form | H12: NOTABLE | I12: Je regarde R-co Valor 4Change Global Equity. Est-ce que tu as sa forme juridique ? | J12: SICAV | K12: Résultat Information trouvée La forme juridique du fonds « R-co Valor 4Change Global Equity » est : SICAV. Détails complémentaires Le fonds a été trouvé en statut Production et sa forme juridique enregistrée est SICAV. | L12: Correct | M12: texte | N12: Règles | O12: 27.52 | P12: 1 | Q12: 46309.796 | S12: Non | T12: =IF(S12="Oui",IF(R12=L12,"Identique","Changé"),"")
A13: Q0012 | B13: C003 | C13: 2 | D13: PRIORITAIRE | E13: Expertise et gamme | F13: R-co Valor 4Change Global Equity | G13: Region | H13: NOTABLE | I13: Sans changer de fonds, quelle zone d’investissement est indiquée ? | J13: World | K13: Résultat Information trouvée Aucune information disponible pour cette demande. Détails complémentaires Le fonds « R-co Valor 4Change Global Equity » est bien présent en Production, mais aucune zone d’investissement n’est renseignée dans les données disponibles pour ce fonds. | L13: Pas d’info à tort | M13: l'agent dit ne pas avoir la donnée | N13: Règles | O13: 17.8 | P13: 1 | Q13: 46309.796 | S13: Non | T13: =IF(S13="Oui",IF(R13=L13,"Identique","Changé"),"")
A14: Q0013 | B14: C003 | C14: 3 | D14: PRIORITAIRE | E14: Risque | F14: R-co Valor 4Change Global Equity | G14: Official Risk Scale | H14: NOTABLE | I14: Et pour ce même produit, quelle est sa note de risque officielle ? | J14: 4 | K14: Résultat Information trouvée Aucune information disponible pour cette demande. Détails complémentaires Pour le fonds « R-co Valor 4Change Global Equity », aucune note de risque officielle n’est renseignée dans les données disponibles du référentiel Product Info. | L14: Pas d’info à tort | M14: l'agent dit ne pas avoir la donnée | N14: Règles | O14: 8.36 | P14: 1 | Q14: 46309.797 | S14: Non | T14: =IF(S14="Oui",IF(R14=L14,"Identique","Changé"),"")
A15: Q0014 | B15: C003 | C15: 4 | D15: PRIORITAIRE | E15: Gérants et dates de gestion | F15: R-co Valor 4Change Global Equity | G15: Portfolio Manager backup 3 | H15: EXPLORATOIRE | I15: Autre point sur ce fonds : y a-t-il un troisième gérant secondaire renseigné ? | J15: nan | K15: Résultat Information trouvée Non, aucun troisième gérant secondaire n’est renseigné pour le fonds « R-co Valor 4Change Global Equity ». Détails complémentaires Le champ correspondant au troisième gérant secondaire est vide dans les données disponibles du référentiel Product Info. | L15: Abstention correcte | M15: cellule vide, l'agent n'invente pas | N15: Règles | O15: 11.49 | P15: 1 | Q15: 46309.797 | S15: Non | T15: =IF(S15="Oui",IF(R15=L15,"Identique","Changé"),"")
A16: Q0015 | B16: C003 | C16: 5 | D16: PRIORITAIRE | E16: Dates et VL | F16: R-co Valor 4Change Global Equity | G16: Recommended Investment Period | H16: NOTABLE | I16: Au passage, sur combien de temps est-il conseillé de le conserver ? | J16: 5 years | K16: Résultat Information trouvée Pour le fonds « R-co Valor 4Change Global Equity », la durée de détention recommandée est de : 5 ans. Détails complémentaires Cette durée correspond à l’horizon d’investissement recommandé enregistré pour ce fonds dans le référentiel Product Info. | L16: Correct | M16: texte | N16: Règles | O16: 9.02 | P16: 1 | Q16: 46309.797 | S16: Non | T16: =IF(S16="Oui",IF(R16=L16,"Identique","Changé"),"")
A17: Q0016 | B17: C004 | C17: 1 | D17: CONTRASTE | E17: Intervenants | F17: Synergizz Compartiment n°1 | G17: Investment Manager | H17: NOTABLE | I17: Je prépare une fiche sur Synergizz Compartiment n°1 : quelle société de gestion est indiquée ? | J17: Rothschild & Co Asset Management | K17: Résultat Pour le fonds/compartiment « Synergizz Compartiment n°1 », la société de gestion indiquée est : « Rothschild & Co Asset Management ». Détails complémentaires Cette information est rattachée au compartiment « Synergizz Compartiment n°1 » dans le référentiel Product Info. | L17: Correct | M17: texte | N17: Règles | O17: 46.85 | P17: 1 | Q17: 46309.798 | S17: Non | T17: =IF(S17="Oui",IF(R17=L17,"Identique","Changé"),"")
A18: Q0017 | B18: C004 | C18: 2 | D18: CONTRASTE | E18: Intervenants | F18: Synergizz Compartiment n°1 | G18: Depositary | H18: NOTABLE | I18: Et pour ce même produit, quel établissement assure le dépôt ? | J18: Caceis Bank | K18: Résultat Pour « Synergizz Compartiment n°1 », l’établissement dépositaire indiqué est : « Caceis Bank ». Détails complémentaires Caceis Bank est l’établissement renseigné comme dépositaire pour ce produit. | L18: Correct | M18: texte | N18: Règles | O18: 11.23 | P18: 1 | Q18: 46309.798 | S18: Non | T18: =IF(S18="Oui",IF(R18=L18,"Identique","Changé"),"")
A19: Q0018 | B19: C004 | C19: 3 | D19: CONTRASTE | E19: Risque | F19: Synergizz Compartiment n°1 | G19: Official Risk Scale | H19: NOTABLE | I19: Autre point sur ce fonds : quel niveau est indiqué sur l’échelle officielle de risque ? | J19: 3 | K19: Résultat Pour « Synergizz Compartiment n°1 », aucune valeur n’est renseignée dans le champ « échelle officielle de risque ». Détails complémentaires Une valeur de risque de niveau « 3 » est toutefois renseignée dans les informations de risque du produit et apparaît de manière cohérente dans les données disponibles du fonds. | L19: Pas d’info à tort | M19: l'agent dit ne pas avoir la donnée | N19: Règles | O19: 10.94 | P19: 1 | Q19: 46309.798 | S19: Non | T19: =IF(S19="Oui",IF(R19=L19,"Identique","Changé"),"")
A20: Q0019 | B20: C004 | C20: 4 | D20: CONTRASTE | E20: Intervenants | F20: Synergizz Compartiment n°1 | G20: Fund Administrator | H20: NOTABLE | I20: Au passage, quel administrateur est renseigné ? | J20: Caceis Fund Administration | K20: Résultat Pour « Synergizz Compartiment n°1 », l’administrateur (valorisateur) renseigné est : « Caceis Fund Administration ». Détails complémentaires Caceis Fund Administration est l’établissement enregistré comme administrateur du fonds dans le référentiel Product Info. | L20: Correct | M20: texte | N20: Règles | O20: 12.64 | P20: 1 | Q20: 46309.798 | S20: Non | T20: =IF(S20="Oui",IF(R20=L20,"Identique","Changé"),"")
A21: Q0020 | B21: C004 | C21: 5 | D21: CONTRASTE | E21: Intervenants | F21: Synergizz Compartiment n°1 | G21: Commissaire Aux Comptes | H21: NOTABLE | I21: Pour compléter la fiche, qui est le commissaire aux comptes ? | J21: PricewaterhouseCoopers Audit | K21: Résultat Pour « Synergizz Compartiment n°1 », le commissaire aux comptes renseigné est : « PricewaterhouseCoopers Audit ». Détails complémentaires PricewaterhouseCoopers Audit est l’entité enregistrée comme commissaire aux comptes du fonds dans le référentiel Product Info. | L21: Correct | M21: texte | N21: Règles | O21: 10.69 | P21: 1 | Q21: 46309.799 | S21: Non | T21: =IF(S21="Oui",IF(R21=L21,"Identique","Changé"),"")
A22: Q0021 | B22: C005 | C22: 1 | D22: PRIORITAIRE | E22: Gérants et dates de gestion | F22: R-co Thematic Silver Plus | G22: Portfolio Manager | H22: NOTABLE | I22: Pour R-co Thematic Silver Plus, quel gérant est indiqué en premier ? | J22: BOURDONCLE Nathalie | K22: Résultat Pour le fonds R-co Thematic Silver Plus, le gérant indiqué en premier (gérant principal) est : Nathalie BOURDONCLE Détails complémentaires Aucun autre détail demandé. Le fonds consulté est en statut Production. | L22: Correct | M22: mots (ordre libre) | N22: Règles | O22: 23.99 | P22: 1 | Q22: 46309.799 | S22: Non | T22: =IF(S22="Oui",IF(R22=L22,"Identique","Changé"),"")
... A101: Q0100 | B101: C020 | C101: 5 | D101: CONTRASTE | E101: Expertise et gamme | F101: RMM Court Terme | G101: Benchmark | H101: NOTABLE | I101: Sans changer de fonds, un indicateur de référence est-il signalé dans le champ Benchmark ? | J101: No | K101: Résultat Information trouvée Non, pour le fonds RMM Court Terme, le champ indiquant la présence d’un indicateur de référence (Benchmark) est renseigné à : Non. Détails complémentaires Aucun benchmark n’est signalé pour ce fonds dans les données disponibles. Le champ « Benchmark » est positionné sur « Non ». | L101: Correct | M101: texte | N101: Règles | O101: 12.1 | P101: 6 | Q101: 46310.426 | S101: Non | T101: =IF(S101="Oui",IF(R101=L101,"Identique","Changé"),"")
A102: Q0101 | B102: C021 | C102: 1 | D102: PRIORITAIRE | E102: Expertise et gamme | F102: R-co Conviction Club | G102: Management Expertise Level 1 | H102: NOTABLE | I102: Je regarde R-co Conviction Club. Tu as sa famille d’expertise de gestion ? | J102: DIVERSIFIED | K102: Résultat Information trouvée Pour le fonds R-co Conviction Club, la famille d’expertise de gestion est : Niveau 0 : DIRECT INVESTMENT Niveau 1 : DIVERSIFIED Niveau 2 : Flexible Niveau 3 (classe d’actif) : Diversified Détails complémentaires Le chemin d’expertise de gestion enregistré est : Diversified < Flexible < DIVERSIFIED < DIRECT INVESTMENT. | L102: Correct | M102: texte | N102: Règles | O102: 36.95 | P102: 3 | Q102: 46309.962 | R102: Correct | S102: Oui | T102: =IF(S102="Oui",IF(R102=L102,"Identique","Changé"),"") -> Identique
A103: Q0102 | B103: C021 | C103: 2 | D103: PRIORITAIRE | E103: Gérants et dates de gestion | F103: R-co Conviction Club | G103: Portfolio Manager backup 1 | H103: NOTABLE | I103: Au passage, quel est le premier gérant secondaire ? | J103: BOY Julien | K103: Résultat Information trouvée Le premier gérant secondaire de R-co Conviction Club est : Julien BOY Détails complémentaires Aucune autre information n’a été demandée sur les autres rôles de gestion. | L103: Correct | M103: mots (ordre libre) | N103: Règles | O103: 9.81 | P103: 3 | Q103: 46309.963 | R103: Correct | S103: Oui | T103: =IF(S103="Oui",IF(R103=L103,"Identique","Changé"),"") -> Identique
A104: Q0103 | B104: C021 | C104: 3 | D104: PRIORITAIRE | E104: ESG / EET | F104: R-co Target 2029 IG | G104: Does it consider PAI? (EET 20100) | H104: NOTABLE | I104: Je passe à R-co Target 2029 IG : le champ PAI est-il à oui ou à non ? | J104: Yes | K104: Résultat Information trouvée Pour le fonds R-co Target 2029 IG, le champ PAI est à : Oui Détails complémentaires Les indicateurs EET associés consultés pour ce fonds sont renseignés à « Oui ». Le fonds est également classé Article 8. | L104: Correct | M104: texte | N104: Règles | O104: 22.75 | P104: 3 | Q104: 46309.963 | R104: Correct | S104: Oui | T104: =IF(S104="Oui",IF(R104=L104,"Identique","Changé"),"") -> Identique
A105: Q0104 | B105: C021 | C105: 4 | D105: PRIORITAIRE | E105: Gérants et dates de gestion | F105: R-co Target 2029 IG | G105: Portfolio Manager | H105: NOTABLE | I105: Sans changer de fonds, qui gère principalement ce fonds ? | J105: PETIT Emmanuel | K105: Résultat Information trouvée Le gérant principal du fonds R-co Target 2029 IG est : Emmanuel PETIT Détails complémentaires Aucune autre information de gestion n’a été demandée pour ce fonds. | L105: Correct | M105: mots (ordre libre) | N105: Règles | O105: 9.42 | P105: 3 | Q105: 46309.963 | R105: Correct | S105: Oui | T105: =IF(S105="Oui",IF(R105=L105,"Identique","Changé"),"") -> Identique
A106: Q0105 | B106: C021 | C106: 5 | D106: PRIORITAIRE | E106: ESG / EET | F106: R-co Conviction Club | G106: ESG - SFDR Article | H106: NOTABLE | I106: Je reviens à R-co Conviction Club : quelle classification SFDR est renseignée ? | J106: Article 8 | K106: Résultat Information trouvée La classification SFDR renseignée pour le fonds R-co Conviction Club est : Article 8 Détails complémentaires Aucune autre classification SFDR n’est renseignée pour ce fonds. | L106: Correct | M106: texte | N106: Règles | O106: 7.59 | P106: 3 | Q106: 46309.963 | R106: Correct | S106: Oui | T106: =IF(S106="Oui",IF(R106=L106,"Identique","Changé"),"") -> Identique
A107: Q0106 | B107: C022 | C107: 1 | D107: CONTRASTE | E107: Intervenants | F107: R-co Core Equity Euro | G107: Investment Manager | H107: NOTABLE | I107: Je prépare une fiche sur R-co Core Equity Euro : quelle société de gestion est indiquée ? | J107: Rothschild & Co Asset Management | K107: Résultat Information trouvée Pour le fonds R-co Core Equity Euro, la société de gestion indiquée est : Rothschild & Co Asset Management Détails complémentaires Le fonds est présent en statut Production dans le référentiel. | L107: Correct | M107: texte | N107: Règles | O107: 43.92 | P107: 4 | Q107: 46310.426 | R107: Correct | S107: Oui | T107: =IF(S107="Oui",IF(R107=L107,"Identique","Changé"),"") -> Identique
A108: Q0107 | B108: C022 | C108: 2 | D108: CONTRASTE | E108: Intervenants | F108: R-co Core Equity Euro | G108: Depositary | H108: NOTABLE | I108: Pour compléter la fiche, quel établissement assure le dépôt ? | J108: Rothschild & Co Martin Maurel | K108: Résultat Information trouvée Pour le fonds R-co Core Equity Euro, l’établissement dépositaire indiqué est : Rothschild & Co Martin Maurel Détails complémentaires Cet établissement est renseigné comme dépositaire du fonds dans le référentiel de production. | L108: Correct | M108: texte | N108: Règles | O108: 16.03 | P108: 4 | Q108: 46310.427 | R108: Correct | S108: Oui | T108: =IF(S108="Oui",IF(R108=L108,"Identique","Changé"),"") -> Identique
A109: Q0108 | B109: C022 | C109: 3 | D109: CONTRASTE | E109: Expertise et gamme | F109: R-co Core Equity Euro | G109: Benchmark | H109: NOTABLE | I109: Sans changer de fonds, un indicateur de référence est-il signalé dans le champ Benchmark ? | J109: No | K109: Résultat Information trouvée Pour le fonds R-co Core Equity Euro, aucun indicateur de référence n’est signalé dans le champ Benchmark : Benchmark : Non Détails complémentaires Aucun indice de référence n’est renseigné comme benchmark pour ce fonds dans les données de production. | L109: Correct | M109: texte | N109: Règles | O109: 12.16 | P109: 4 | Q109: 46310.427 | R109: Correct | S109: Oui | T109: =IF(S109="Oui",IF(R109=L109,"Identique","Changé"),"") -> Identique
A110: Q0109 | B110: C022 | C110: 4 | D110: CONTRASTE | E110: Dates et VL | F110: R-co Core Equity Euro | G110: First NAV Date | H110: EXPLORATOIRE | I110: Et pour ce même produit, tu as sa date de première valeur liquidative ? Si tu ne trouves pas, dis-le clairement. | J110: nan | K110: Résultat Information trouvée Je ne trouve pas de date de première valeur liquidative renseignée pour le fonds R-co Core Equity Euro. Détails complémentaires Le champ correspondant à la première valeur liquidative est présent dans le référentiel, mais aucune valeur n’est enregistrée pour ce produit en production. | L110: Abstention correcte | M110: cellule vide, l'agent n'invente pas | N110: Règles | O110: 14.12 | P110: 4 | Q110: 46310.427 | R110: Abstention correcte | S110: Oui | T110: =IF(S110="Oui",IF(R110=L110,"Identique","Changé"),"") -> Identique
A111: Q0110 | B111: C022 | C111: 5 | D111: CONTRASTE | E111: Juridique et réglementaire | F111: R-co Core Equity Euro | G111: Legal Form | H111: NOTABLE | I111: Autre point sur ce fonds : quelle forme juridique est indiquée ? Réponds uniquement sur ce point. | J111: Unit Trust | K111: FCP (Fonds Commun de Placement)। | L111: Correct | M111: texte | N111: Règles | O111: 9.1 | P111: 4 | Q111: 46310.427 | R111: Correct | S111: Oui | T111: =IF(S111="Oui",IF(R111=L111,"Identique","Changé"),"") -> Identique
A112: Q0111 | B112: C023 | C112: 1 | D112: PRIORITAIRE | E112: Expertise et gamme | F112: R-co Valor Balanced | G112: Asset Class | H112: NOTABLE | I112: Pour R-co Valor Balanced, quelle est sa classe d’actifs ? | J112: Diversified | K112: Résultat Information trouvée Pour le fonds R-co Valor Balanced (statut Production), la classe d’actifs est : Niveau 3 (Classe d’actifs) : Diversified Chemin d’expertise complet : Diversified < Flexible < DIVERSIFIED < DIRECT INVESTMENT Détails complémentaires Selon le référentiel Product Info, la « classe d’actifs » correspond au niveau 3 du Management d’expertise. Pour ce fonds, elle est renseignée à la valeur Diversified. | L112: Correct | M112: texte | N112: Règles | O112: 40.49 | P112: 2 | Q112: 46309.982 | R112: Correct | S112: Oui | T112: =IF(S112="Oui",IF(R112=L112,"Identique","Changé"),"") -> Identique
A113: Q0112 | B113: C023 | C113: 2 | D113: PRIORITAIRE | E113: Expertise et gamme | F113: R-co Valor Balanced | G113: Benchmark | H113: NOTABLE | I113: Sans changer de fonds, un indicateur de référence est-il signalé dans le champ Benchmark ? | J113: No | K113: Pouvez-vous fournir la requête SQL SELECT que vous souhaitez exécuter ? | L113: Hors sujet | M113: l'agent ne traite pas la question (précision demandée, question non reçue ou réponse vide) | N113: Règles | O113: 5.16 | P113: 2 | Q113: 46309.982 | R113: Correct | S113: Oui | T113: =IF(S113="Oui",IF(R113=L113,"Identique","Changé"),"") -> Changé
... A146: Q0145 | B146: C029 | C146: 5 | D146: PRIORITAIRE | E146: Juridique et réglementaire | F146: R-co Conviction High Yield Euro | G146: Applicable UCI Regulation | H146: NOTABLE | I146: Pour compléter la fiche, quelle réglementation OPC lui est applicable ? Réponds uniquement sur ce point. | J146: UCITS | K146: OPCVM. | L146: Correct | M146: texte | N146: Règles | O146: 26 | P146: 4 | Q146: 46310.441 | R146: Correct | S146: Oui | T146: =IF(S146="Oui",IF(R146=L146,"Identique","Changé"),"") -> Identique
A147: Q0146 | B147: C030 | C147: 1 | D147: CONTRASTE | E147: Juridique et réglementaire | F147: Alfred Investment | G147: Domiciliation | H147: NOTABLE | I147: Je regarde Alfred Investment. Où est-il domicilié ? | J147: France | L147: Hors sujet | M147: l'agent ne traite pas la question (précision demandée, question non reçue ou réponse vide) | N147: Règles | O147: 18.06 | P147: 4 | Q147: 46310.441 | R147: Correct | S147: Oui | T147: =IF(S147="Oui",IF(R147=L147,"Identique","Changé"),"") -> Changé
A148: Q0147 | B148: C030 | C148: 2 | D148: CONTRASTE | E148: Juridique et réglementaire | F148: Alfred Investment | G148: Legal Form | H148: NOTABLE | I148: Autre point sur ce fonds : est-ce que tu as sa forme juridique ? | J148: SICAV | K148: Je ne peux pas répondre à la forme juridique de ce fonds avec les informations disponibles dans notre échange. Le fonds « Alfred Investment » n’a pas été retrouvé dans les données auxquelles j’ai accès. Sans pouvoir identifier précisément le fonds, je ne peux pas récupérer sa forme juridique. Si vous disposez du nom exact du fonds, d’un code ISIN ou du nom d’une part associée, je pourrai refaire la recherche. | L148: Pas d’info à tort | M148: l'agent dit ne pas avoir la donnée | N148: Règles | O148: 17.92 | P148: 4 | Q148: 46310.442 | R148: Correct | S148: Oui | T148: =IF(S148="Oui",IF(R148=L148,"Identique","Changé"),"") -> Changé
A149: Q0148 | B149: C030 | C149: 3 | D149: CONTRASTE | E149: Intervenants | F149: Alfred Investment | G149: Depositary | H149: NOTABLE | I149: Au passage, qui est le dépositaire ? | J149: Caceis Bank | K149: Je ne peux pas identifier le dépositaire du fonds concerné. Dans notre échange, le fonds « Alfred Investment » n’a pas été retrouvé dans les données disponibles, et je n’ai donc pas pu accéder à sa fiche produit. Sans identification certaine du fonds, il n’est pas possible de récupérer son dépositaire. Si vous disposez du nom exact du fonds, d’un code ISIN ou du nom d’une part associée, je pourrai vérifier le dépositaire. | L149: Pas d’info à tort | M149: l'agent dit ne pas avoir la donnée | N149: Règles | O149: 23.69 | P149: 4 | Q149: 46310.442 | R149: Correct | S149: Oui | T149: =IF(S149="Oui",IF(R149=L149,"Identique","Changé"),"") -> Changé
A150: Q0149 | B150: C030 | C150: 4 | D150: CONTRASTE | E150: Dates et VL | F150: Alfred Investment | G150: Recommended Investment Period | H150: NOTABLE | I150: Pour compléter la fiche, sur combien de temps est-il conseillé de le conserver ? | J150: 5 years | K150: Résultat Information trouvée Pour le fonds Alfred Investment, la durée de détention recommandée est de 5 ans. Détails complémentaires Statut : Production Durée de détention recommandée : 5 ans | L150: Correct | M150: texte | N150: Règles | O150: 17.42 | P150: 4 | Q150: 46310.442 | R150: Correct | S150: Oui | T150: =IF(S150="Oui",IF(R150=L150,"Identique","Changé"),"") -> Identique
A151: Q0150 | B151: C030 | C151: 5 | D151: CONTRASTE | E151: ESG / EET | F151: Alfred Investment | G151: ESG - SFDR Article | H151: NOTABLE | I151: Sans changer de fonds, il relève de quel article SFDR ? | J151: Article 6 | K151: Résultat Information trouvée Alfred Investment relève de l’Article 6 du règlement SFDR. Détails complémentaires Catégorie SFDR : Article 6 Statut du fonds : Production | L151: Correct | M151: texte | N151: Règles | O151: 10.44 | P151: 4 | Q151: 46310.443 | R151: Correct | S151: Oui | T151: =IF(S151="Oui",IF(R151=L151,"Identique","Changé"),"") -> Identique
A152: Q0151 | B152: C031 | C152: 1 | D152: PRIORITAIRE | E152: Juridique et réglementaire | F152: R-co Target 2029 HY | G152: Domiciliation | H152: NOTABLE | I152: Je prépare une fiche sur R-co Target 2029 HY : quel pays de domiciliation est renseigné ? | J152: France | K152: Résultat Information trouvée Le fonds R-co Target 2029 HY a pour pays de domiciliation : France. Détails complémentaires Le fonds est présent en statut Production et le pays de domiciliation renseigné est France. | L152: Correct | M152: texte | N152: Règles | O152: 38.82 | P152: 1 | Q152: 46310.443 | R152: Correct | S152: Oui | T152: =IF(S152="Oui",IF(R152=L152,"Identique","Changé"),"") -> Identique
A153: Q0152 | B153: C031 | C153: 2 | D153: PRIORITAIRE | E153: Autres | F153: R-co Target 2029 HY | G153: Accounting Currency | H153: NOTABLE | I153: Au passage, quelle est sa devise comptable ? | J153: EUR | K153: Résultat Information trouvée La devise comptable du fonds R-co Target 2029 HY est : EUR (euro). Détails complémentaires Pays de domiciliation : France Devise comptable : EUR (euro) | L153: Correct | M153: texte | N153: Règles | O153: 16.47 | P153: 1 | Q153: 46310.444 | R153: Correct | S153: Oui | T153: =IF(S153="Oui",IF(R153=L153,"Identique","Changé"),"") -> Identique
A154: Q0153 | B154: C031 | C154: 3 | D154: PRIORITAIRE | E154: Dates et VL | F154: R-co Conviction Equity Value Euro | G154: Recommended Investment Period | H154: NOTABLE | I154: Je passe à R-co Conviction Equity Value Euro : sur combien de temps est-il conseillé de le conserver ? | J154: 5 years | K154: Résultat Information trouvée Pour le fonds R-co Conviction Equity Value Euro, la durée de détention recommandée est de 5 ans. Détails complémentaires Cette durée correspond à l’horizon d’investissement conseillé renseigné pour ce fonds en statut Production. | L154: Correct | M154: texte | N154: Règles | O154: 14.61 | P154: 1 | Q154: 46310.444 | R154: Correct | S154: Oui | T154: =IF(S154="Oui",IF(R154=L154,"Identique","Changé"),"") -> Identique
A155: Q0154 | B155: C031 | C155: 4 | D155: PRIORITAIRE | E155: Juridique et réglementaire | F155: R-co Conviction Equity Value Euro | G155: Applicable UCI Regulation | H155: NOTABLE | I155: Sans changer de fonds, sous quelle réglementation OPC est-il classé ? | J155: UCITS | K155: Résultat Information trouvée Le fonds R-co Conviction Equity Value Euro est classé sous la réglementation OPCVM. Détails complémentaires La réglementation applicable renseignée pour ce fonds en statut Production est : OPCVM. | L155: Correct | M155: texte | N155: Règles | O155: 12.54 | P155: 1 | Q155: 46310.444 | R155: Correct | S155: Oui | T155: =IF(S155="Oui",IF(R155=L155,"Identique","Changé"),"") -> Identique
A156: Q0155 | B156: C031 | C156: 5 | D156: PRIORITAIRE | E156: ESG / EET | F156: R-co Target 2029 HY | G156: ESG - SFDR Article | H156: NOTABLE | I156: Je reviens à R-co Target 2029 HY : quelle classification SFDR est renseignée ? | J156: Article 8 | K156: Résultat Information trouvée La classification SFDR renseignée pour le fonds R-co Target 2029 HY est : Article 8. Détails complémentaires Le fonds est classé SFDR Article 8 dans les données de référence en statut Production. | L156: Correct | M156: texte | N156: Règles | O156: 12.11 | P156: 1 | Q156: 46310.444 | R156: Correct | S156: Oui | T156: =IF(S156="Oui",IF(R156=L156,"Identique","Changé"),"") -> Identique
A157: Q0156 | B157: C032 | C157: 1 | D157: CONTRASTE | E157: ESG / EET | F157: 5m Invest | G157: ESG - SFDR Article | H157: NOTABLE | I157: Pour 5m Invest, il relève de quel article SFDR ? | J157: Article 6 | K157: Résultat Information trouvée Le fonds/produit « 5m Invest » relève de l’Article 6 SFDR. Détails complémentaires Statut : Production Classification SFDR : Article 6 | L157: Correct | M157: texte | N157: Règles | O157: 38.7 | P157: 1 | Q157: 46310.445 | R157: Correct | S157: Oui | T157: =IF(S157="Oui",IF(R157=L157,"Identique","Changé"),"") -> Identique
A158: Q0157 | B158: C032 | C158: 2 | D158: CONTRASTE | E158: Juridique et réglementaire | F158: 5m Invest | G158: Applicable UCI Regulation | H158: NOTABLE | I158: Pour compléter la fiche, quelle réglementation OPC lui est applicable ? | J158: UCITS | K158: Résultat Information trouvée Pour le fonds « 5m Invest », la réglementation OPC applicable est : OPCVM. Détails complémentaires Statut : Production Réglementation applicable : OPCVM (Organisme de Placement Collectif en Valeurs Mobilières) | L158: Correct | M158: texte | N158: Règles | O158: 16.25 | P158: 1 | Q158: 46310.445 | R158: Correct | S158: Oui | T158: =IF(S158="Oui",IF(R158=L158,"Identique","Changé"),"") -> Identique
A159: Q0158 | B159: C032 | C159: 3 | D159: CONTRASTE | E159: ESG / EET | F159: 5m Invest | G159: Does it consider PAI? (EET 20100) | H159: NOTABLE | I159: Sans changer de fonds, la prise en compte des PAI est-elle indiquée ? | J159: No | K159: Résultat Information trouvée Pour le fonds « 5m Invest », la prise en compte des PAI (Principales Incidences Négatives) est indiquée comme : Non. Détails complémentaires Statut : Production Prise en compte des PAI : Non | L159: Correct | M159: texte | N159: Règles | O159: 11.48 | P159: 1 | Q159: 46310.446 | R159: Pas d’info à tort | S159: Oui | T159: =IF(S159="Oui",IF(R159=L159,"Identique","Changé"),"") -> Changé
... A236: Q0235 | B236: C047 | C236: 5 | D236: PRIORITAIRE | E236: ESG / EET | F236: R-co Valor Equity | G236: Does it consider PAI? (EET 20100) | H236: NOTABLE | I236: Autre point sur ce fonds : le champ PAI est-il à oui ou à non ? | J236: Yes | K236: Résultat Aucune information disponible pour cette demande. Détails complémentaires Je ne retrouve pas de champ identifié explicitement comme « PAI » dans les données consultables du fonds R-co Valor Equity. Sans correspondance métier explicite entre l’intitulé « PAI » et un champ du référentiel, je ne peux pas déterminer de façon fiable si la valeur est « Oui » ou « Non ». | L236: Pas d’info à tort | M236: l'agent dit ne pas avoir la donnée | N236: Règles | O236: 23.26 | P236: 2 | Q236: 46310.514 | R236: Pas d’info à tort | S236: Oui | T236: =IF(S236="Oui",IF(R236=L236,"Identique","Changé"),"") -> Identique
A237: Q0236 | B237: C048 | C237: 1 | D237: CONTRASTE | E237: Identifiants | F237: Elan Orchestra | G237: AMF Code | H237: NOTABLE | I237: Je regarde Elan Orchestra. Quel code AMF est renseigné ? | J237: FDS564 | L237: Non capturé | M237: non capturé | N237: Règles | P237: 3 | Q237: 46310.527 | S237: Non | T237: =IF(S237="Oui",IF(R237=L237,"Identique","Changé"),"")
A238: Q0237 | B238: C048 | C238: 2 | D238: CONTRASTE | E238: ESG / EET | F238: Elan Orchestra | G238: ESG - SFDR Article | H238: NOTABLE | I238: Sans changer de fonds, quelle classification SFDR est renseignée ? | J238: Article 6 | L238: Non capturé | M238: non capturé | N238: Règles | S238: Non | T238: =IF(S238="Oui",IF(R238=L238,"Identique","Changé"),"")
A239: Q0238 | B239: C048 | C239: 3 | D239: CONTRASTE | E239: Expertise et gamme | F239: Elan Orchestra | G239: Region | H239: NOTABLE | I239: Et pour ce même produit, quelle zone d’investissement est indiquée ? | J239: World | L239: Non capturé | M239: non capturé | N239: Règles | S239: Non | T239: =IF(S239="Oui",IF(R239=L239,"Identique","Changé"),"")
A240: Q0239 | B240: C048 | C240: 4 | D240: CONTRASTE | E240: Intervenants | F240: Elan Orchestra | G240: Transfer Agent | H240: EXPLORATOIRE | I240: Autre point sur ce fonds : qui assure la fonction d’agent de transfert ? | J240: nan | L240: Non capturé | M240: non capturé | N240: Règles | S240: Non | T240: =IF(S240="Oui",IF(R240=L240,"Identique","Changé"),"")
A241: Q0240 | B241: C048 | C241: 5 | D241: CONTRASTE | E241: Intervenants | F241: Elan Orchestra | G241: Fund Administrator | H241: NOTABLE | I241: Au passage, qui est l’administrateur du fonds ? | J241: Caceis Fund Administration | L241: Non capturé | M241: non capturé | N241: Règles | S241: Non | T241: =IF(S241="Oui",IF(R241=L241,"Identique","Changé"),"")
A242: Q0241 | B242: C049 | C242: 1 | D242: PRIORITAIRE | E242: Gérants et dates de gestion | F242: R-co Conviction High Yield SD Euro | G242: Portfolio Manager | H242: NOTABLE | I242: Je prépare une fiche sur R-co Conviction High Yield SD Euro : peux-tu me donner le nom du gérant principal ? | J242: LONGEARD Michaël | K242: Résultat Le gérant principal du fonds « R-co Conviction High Yield SD Euro » est : Michaël LONGEARD Cette information provient de la version du fonds en statut Production. | L242: Correct | M242: mots (ordre libre) | N242: Règles | O242: 51.6 | P242: 1 | Q242: 46310.528 | R242: Correct | S242: Oui | T242: =IF(S242="Oui",IF(R242=L242,"Identique","Changé"),"") -> Identique
A243: Q0242 | B243: C049 | C243: 2 | D243: PRIORITAIRE | E243: Gérants et dates de gestion | F243: R-co Conviction High Yield SD Euro | G243: Portfolio Manager backup 1 | H243: NOTABLE | I243: Et pour ce même produit, qui figure comme premier gérant de renfort ? | J243: AGAESSE Kristell | K243: Résultat Le premier gérant de renfort du fonds « R-co Conviction High Yield SD Euro » est : Kristell AGAESSE Détails complémentaires Le fonds considéré est la version en statut Production. | L243: Correct | M243: mots (ordre libre) | N243: Règles | O243: 17.32 | P243: 1 | Q243: 46310.528 | R243: Correct | S243: Oui | T243: =IF(S243="Oui",IF(R243=L243,"Identique","Changé"),"") -> Identique
A244: Q0243 | B244: C049 | C244: 3 | D244: PRIORITAIRE | E244: ESG / EET | F244: R-co Conviction High Yield SD Euro | G244: Does it consider PAI? (EET 20100) | H244: NOTABLE | I244: Autre point sur ce fonds : le champ PAI est-il à oui ou à non ? | J244: Yes | K244: Je ne trouve pas de champ métier identifié explicitement comme « PAI » dans les métadonnées disponibles du référentiel produit. Comme plusieurs attributs ESG peuvent être associés à la notion de PAI (Principal Adverse Impacts), je ne peux pas déterminer de manière fiable lequel vous souhaitez consulter pour « R-co Conviction High Yield SD Euro » sans ambiguïté. Pouvez-vous me préciser l’intitulé exact du champ PAI tel qu’il apparaît dans votre fiche produit ou dans l’application ? | L244: Pas d’info à tort | M244: l'agent dit ne pas avoir la donnée | N244: Règles | O244: 34.98 | P244: 1 | Q244: 46310.529 | R244: Pas d’info à tort | S244: Oui | T244: =IF(S244="Oui",IF(R244=L244,"Identique","Changé"),"") -> Identique
A245: Q0244 | B245: C049 | C245: 4 | D245: PRIORITAIRE | E245: Gérants et dates de gestion | F245: R-co Conviction High Yield SD Euro | G245: Portfolio Manager backup 3 | H245: NOTABLE | I245: Au passage, y a-t-il un troisième gérant secondaire renseigné ? | J245: PETIT Emmanuel | K245: Résultat Oui, un troisième gérant secondaire est renseigné pour le fonds « R-co Conviction High Yield SD Euro ». Emmanuel PETIT Détails complémentaires Cette information correspond à la version du fonds en statut Production. | L245: Correct | M245: mots (ordre libre) | N245: Règles | O245: 18.58 | P245: 1 | Q245: 46310.529 | R245: Correct | S245: Oui | T245: =IF(S245="Oui",IF(R245=L245,"Identique","Changé"),"") -> Identique
A246: Q0245 | B246: C049 | C246: 5 | D246: PRIORITAIRE | E246: ESG / EET | F246: R-co Conviction High Yield SD Euro | G246: ESG - SFDR Article | H246: NOTABLE | I246: Pour compléter la fiche, quelle classification SFDR est renseignée ? | J246: Article 8 | K246: Résultat La classification SFDR renseignée pour le fonds « R-co Conviction High Yield SD Euro » est : Article 8 Détails complémentaires L'information provient de la version du fonds en statut Production. | L246: Correct | M246: texte | N246: Règles | O246: 13.66 | P246: 1 | Q246: 46310.529 | R246: Correct | S246: Oui | T246: =IF(S246="Oui",IF(R246=L246,"Identique","Changé"),"") -> Identique
A247: Q0246 | B247: C050 | C247: 1 | D247: CONTRASTE | E247: Juridique et réglementaire | F247: BDCP Conviction | G247: Legal Form | H247: NOTABLE | I247: Pour BDCP Conviction, quelle forme juridique est indiquée ? | J247: SICAV | L247: Non capturé | M247: non capturé | N247: Règles | P247: 3 | Q247: 46310.543 | S247: Non | T247: =IF(S247="Oui",IF(R247=L247,"Identique","Changé"),"")
A248: Q0247 | B248: C050 | C248: 2 | D248: CONTRASTE | E248: ESG / EET | F248: BDCP Conviction | G248: Does it consider PAI? (EET 20100) | H248: NOTABLE | I248: Autre point sur ce fonds : le champ PAI est-il à oui ou à non ? | J248: Yes | L248: Non capturé | M248: non capturé | N248: Règles | S248: Non | T248: =IF(S248="Oui",IF(R248=L248,"Identique","Changé"),"")
A249: Q0248 | B249: C050 | C249: 3 | D249: CONTRASTE | E249: Juridique et réglementaire | F249: BDCP Conviction | G249: Domiciliation | H249: NOTABLE | I249: Au passage, où est-il domicilié ? | J249: France | L249: Non capturé | M249: non capturé | N249: Règles | S249: Non | T249: =IF(S249="Oui",IF(R249=L249,"Identique","Changé"),"")
A250: Q0249 | B250: C050 | C250: 4 | D250: CONTRASTE | E250: ESG / EET | F250: BDCP Conviction | G250: ESG - SFDR Article | H250: NOTABLE | I250: Pour compléter la fiche, quelle classification SFDR est renseignée ? | J250: Article 8 | L250: Non capturé | M250: non capturé | N250: Règles | S250: Non | T250: =IF(S250="Oui",IF(R250=L250,"Identique","Changé"),"")
A251: Q0250 | B251: C050 | C251: 5 | D251: CONTRASTE | E251: Gérants et dates de gestion | F251: BDCP Conviction | G251: Portfolio Manager | H251: NOTABLE | I251: Sans changer de fonds, qui gère principalement ce fonds ? Réponds uniquement sur ce point. | J251: PALLIERES (DE) Guillaume | L251: Non capturé | M251: non capturé | N251: Règles | S251: Non | T251: =IF(S251="Oui",IF(R251=L251,"Identique","Changé"),"")
A252: Q0251 | B252: C051 | C252: 1 | D252: PRIORITAIRE | E252: ESG / EET | F252: R-co Target 2030 IG | G252: Does it consider PAI? (EET 20100) | H252: NOTABLE | I252: Je regarde R-co Target 2030 IG. Le champ PAI est-il à oui ou à non ? | J252: Yes | K252: Résultat Pour le fonds « R-co Target 2030 IG », le champ PAI est à « Oui ». Détails complémentaires L’information est renseignée à « Oui » sur le fonds en statut Production. | L252: Correct | M252: texte | N252: Règles | O252: 42.29 | P252: 3 | Q252: 46310.553 | R252: Pas d’info à tort | S252: Oui | T252: =IF(S252="Oui",IF(R252=L252,"Identique","Changé"),"") -> Changé
A253: Q0252 | B253: C051 | C253: 2 | D253: PRIORITAIRE | E253: Expertise et gamme | F253: R-co Target 2030 IG | G253: Region | H253: NOTABLE | I253: Au passage, quelle zone d’investissement est indiquée ? | J253: World | K253: Résultat Pour le fonds « R-co Target 2030 IG », la zone d’investissement indiquée est : Monde Détails complémentaires La zone d’investissement de niveau référentiel est renseignée à « Monde » pour ce fonds en Production. | L253: Correct | M253: texte | N253: Règles | O253: 15.33 | P253: 3 | Q253: 46310.553 | R253: Pas d’info à tort | S253: Oui | T253: =IF(S253="Oui",IF(R253=L253,"Identique","Changé"),"") -> Changé
A254: Q0253 | B254: C051 | C254: 3 | D254: PRIORITAIRE | E254: Risque | F254: R-co Conviction High Yield SD Euro | G254: Official Risk Scale | H254: NOTABLE | I254: Je passe à R-co Conviction High Yield SD Euro : quelle est sa note de risque officielle ? | J254: 2 | K254: Résultat Pour le fonds « R-co Conviction High Yield SD Euro », la note de risque officielle est : 2 Détails complémentaires Les informations de risque disponibles pour ce fonds en Production indiquent une valeur de 2. | L254: Correct | M254: nombre | N254: Règles | O254: 13.6 | P254: 3 | Q254: 46310.554 | R254: Pas d’info à tort | S254: Oui | T254: =IF(S254="Oui",IF(R254=L254,"Identique","Changé"),"") -> Changé
A255: Q0254 | B255: C051 | C255: 4 | D255: PRIORITAIRE | E255: Gérants et dates de gestion | F255: R-co Conviction High Yield SD Euro | G255: Portfolio Manager | H255: NOTABLE | I255: Sans changer de fonds, qui gère principalement ce fonds ? | J255: LONGEARD Michaël | K255: Résultat Le gérant principal du fonds « R-co Conviction High Yield SD Euro » est : Michaël LONGEARD Détails complémentaires Il est renseigné comme gérant principal du fonds en Production. | L255: Correct | M255: mots (ordre libre) | N255: Règles | O255: 15.58 | P255: 3 | Q255: 46310.554 | R255: Correct | S255: Oui | T255: =IF(S255="Oui",IF(R255=L255,"Identique","Changé"),"") -> Identique
A256: Q0255 | B256: C051 | C256: 5 | D256: PRIORITAIRE | E256: Dates et VL | F256: R-co Target 2030 IG | G256: Recommended Investment Period | H256: NOTABLE | I256: Je reviens à R-co Target 2030 IG : sur combien de temps est-il conseillé de le conserver ? | J256: Until 31 December 2030 | K256: Résultat Pour le fonds « R-co Target 2030 IG », la durée de détention recommandée est : Jusqu'au 31 décembre 2030 Détails complémentaires Cette durée de détention recommandée est celle renseignée pour le fonds en Production. | L256: Correct | M256: date | N256: Règles | O256: 9.61 | P256: 3 | Q256: 46310.554 | R256: Correct | S256: Oui | T256: =IF(S256="Oui",IF(R256=L256,"Identique","Changé"),"") -> Identique
A257: Q0256 | B257: C052 | C257: 1 | D257: CONTRASTE | E257: Intervenants | F257: Alchemy | G257: Investment Manager | H257: NOTABLE | I257: Je prépare une fiche sur Alchemy : quelle société de gestion est indiquée ? | J257: Rothschild & Co Asset Management | L257: Non capturé | M257: non capturé | N257: Règles | P257: 3 | Q257: 46310.568 | S257: Non | T257: =IF(S257="Oui",IF(R257=L257,"Identique","Changé"),"")
A258: Q0257 | B258: C052 | C258: 2 | D258: CONTRASTE | E258: Intervenants | F258: Alchemy | G258: Depositary | H258: NOTABLE | I258: Pour compléter la fiche, quel établissement assure le dépôt ? | J258: CACEIS Bank Belgium Branch | L258: Non capturé | M258: non capturé | N258: Règles | S258: Non | T258: =IF(S258="Oui",IF(R258=L258,"Identique","Changé"),"")
A259: Q0258 | B259: C052 | C259: 3 | D259: CONTRASTE | E259: Gérants et dates de gestion | F259: Alchemy | G259: Portfolio Manager | H259: NOTABLE | I259: Sans changer de fonds, qui gère principalement ce fonds ? | J259: IGNATIEW Yoann | L259: Non capturé | M259: non capturé | N259: Règles | S259: Non | T259: =IF(S259="Oui",IF(R259=L259,"Identique","Changé"),"")
A260: Q0259 | B260: C052 | C260: 4 | D260: CONTRASTE | E260: Dates et VL | F260: Alchemy | G260: NAV Frequency | H260: EXPLORATOIRE | I260: Et pour ce même produit, quelle fréquence de VL est indiquée ? Si tu ne trouves pas, dis-le clairement. | J260: nan | L260: Non capturé | M260: non capturé | N260: Règles | S260: Non | T260: =IF(S260="Oui",IF(R260=L260,"Identique","Changé"),"")
A261: Q0260 | B261: C052 | C261: 5 | D261: CONTRASTE | E261: Intervenants | F261: Alchemy | G261: Commissaire Aux Comptes | H261: NOTABLE | I261: Autre point sur ce fonds : qui est le commissaire aux comptes ? | J261: Deloitte Réviseurs d'Entreprises | L261: Non capturé | M261: non capturé | N261: Règles | S261: Non | T261: =IF(S261="Oui",IF(R261=L261,"Identique","Changé"),"")
A262: Q0261 | B262: C053 | C262: 1 | D262: PRIORITAIRE | E262: Gérants et dates de gestion | F262: R-co Target 2032 HY | G262: Portfolio Manager | H262: NOTABLE | I262: Pour R-co Target 2032 HY, quel gérant est indiqué en premier ? | J262: AGAESSE Kristell | K262: Résultat Pour le fonds R-co Target 2032 HY, le gérant indiqué en premier (gérant principal) est : Kristell AGAESSE Détails complémentaires Un gérant secondaire est également renseigné pour ce fonds, mais le premier gérant indiqué est bien Kristell AGAESSE. | L262: Correct | M262: mots (ordre libre) | N262: Règles | O262: 40.83 | P262: 1 | Q262: 46310.569 | R262: Correct | S262: Oui | T262: =IF(S262="Oui",IF(R262=L262,"Identique","Changé"),"") -> Identique
A263: Q0262 | B263: C053 | C263: 2 | D263: PRIORITAIRE | E263: Gérants et dates de gestion | F263: R-co Target 2032 HY | G263: Portfolio Manager backup 1 | H263: NOTABLE | I263: Sans changer de fonds, qui est le premier cogérant indiqué ? | J263: LONGEARD Michaël | K263: Résultat Pour le fonds R-co Target 2032 HY, le premier cogérant indiqué (gérant secondaire 1) est : Michaël LONGEARD Détails complémentaires Aucun autre détail n’est nécessaire pour identifier le premier cogérant de ce fonds. | L263: Correct | M263: mots (ordre libre) | N263: Règles | O263: 9.78 | P263: 1 | Q263: 46310.569 | R263: Correct | S263: Oui | T263: =IF(S263="Oui",IF(R263=L263,"Identique","Changé"),"") -> Identique
A264: Q0263 | B264: C053 | C264: 3 | D264: PRIORITAIRE | E264: Expertise et gamme | F264: R-co Target 2032 HY | G264: Asset Class | H264: NOTABLE | I264: Et pour ce même produit, c’est un fonds de quelle classe d’actifs ? | J264: Fixed Income | K264: Résultat Pour le fonds R-co Target 2032 HY, la classe d’actifs est : Fixed Income (obligataire) Détails complémentaires Le chemin d’expertise associé au fonds est : Direct Investment Fixed Income High Yield Fixed Income Cela correspond à un fonds obligataire spécialisé sur le segment High Yield. | L264: Correct | M264: texte | N264: Règles | O264: 25.79 | P264: 1 | Q264: 46310.569 | R264: Correct | S264: Oui | T264: =IF(S264="Oui",IF(R264=L264,"Identique","Changé"),"") -> Identique
A265: Q0264 | B265: C053 | C265: 4 | D265: PRIORITAIRE | E265: Identifiants | F265: R-co Target 2032 HY | G265: AMF Code | H265: EXPLORATOIRE | I265: Autre point sur ce fonds : quel code AMF est renseigné ? | J265: nan | K265: Résultat Aucune information disponible pour cette demande. Détails complémentaires Pour le fonds R-co Target 2032 HY, aucun code AMF n'est renseigné dans le référentiel. | L265: Abstention correcte | M265: cellule vide, l'agent n'invente pas | N265: Règles | O265: 8.35 | P265: 1 | Q265: 46310.569 | R265: Abstention correcte | S265: Oui | T265: =IF(S265="Oui",IF(R265=L265,"Identique","Changé"),"") -> Identique
A266: Q0265 | B266: C053 | C266: 5 | D266: PRIORITAIRE | E266: Juridique et réglementaire | F266: R-co Target 2032 HY | G266: Domiciliation | H266: NOTABLE | I266: Au passage, quel pays de domiciliation est renseigné ? | J266: France | K266: Résultat Pour le fonds R-co Target 2032 HY, le pays de domiciliation renseigné est : France Détails complémentaires Aucune autre information de domiciliation n'est renseignée au niveau du fonds. | L266: Correct | M266: texte | N266: Règles | O266: 12.31 | P266: 1 | Q266: 46310.57 | R266: Correct | S266: Oui | T266: =IF(S266="Oui",IF(R266=L266,"Identique","Changé"),"") -> Identique
A267: Q0266 | B267: C054 | C267: 1 | D267: CONTRASTE | E267: Gérants et dates de gestion | F267: R-co OPAL Modéré | G267: Portfolio Manager | H267: NOTABLE | I267: Je regarde R-co OPAL Modéré. Qui gère principalement ce fonds ? | J267: TERRAS Marc | K267: Résultat Information trouvée Le gérant principal du fonds « R-co OPAL Modéré » en statut Production est : Marc TERRAS Cette information est issue de la fiche du fonds en Production, où Marc TERRAS est renseigné comme gérant principal. Détails complémentaires Le fonds « R-co OPAL Modéré » est bien présent en statut Production dans le référentiel. | L267: Correct | M267: mots (ordre libre) | N267: Règles | O267: 45.38 | P267: 1 | Q267: 46310.57 | R267: Correct | S267: Oui | T267: =IF(S267="Oui",IF(R267=L267,"Identique","Changé"),"") -> Identique
A268: Q0267 | B268: C054 | C268: 2 | D268: CONTRASTE | E268: Juridique et réglementaire | F268: R-co OPAL Modéré | G268: Legal Form | H268: NOTABLE | I268: Et pour ce même produit, est-ce que tu as sa forme juridique ? | J268: Unit Trust | K268: Résultat Information trouvée La forme juridique du fonds « R-co OPAL Modéré » est : FCP (Fonds Commun de Placement) Détails complémentaires L'information provient de la fiche du fonds en statut Production. | L268: Correct | M268: texte | N268: Règles | O268: 19.91 | P268: 1 | Q268: 46310.571 | R268: Correct | S268: Oui | T268: =IF(S268="Oui",IF(R268=L268,"Identique","Changé"),"") -> Identique
A269: Q0268 | B269: C054 | C269: 3 | D269: CONTRASTE | E269: Intervenants | F269: R-co OPAL Modéré | G269: Depositary | H269: NOTABLE | I269: Autre point sur ce fonds : qui est le dépositaire ? | J269: Rothschild & Co Martin Maurel | K269: Résultat Information trouvée Le dépositaire du fonds « R-co OPAL Modéré » est : Rothschild & Co Martin Maurel Détails complémentaires Cette information est issue de la fiche du fonds en statut Production. | L269: Correct | M269: texte | N269: Règles | O269: 18.42 | P269: 1 | Q269: 46310.571 | R269: Correct | S269: Oui | T269: =IF(S269="Oui",IF(R269=L269,"Identique","Changé"),"") -> Identique
A270: Q0269 | B270: C054 | C270: 4 | D270: CONTRASTE | E270: Expertise et gamme | F270: R-co OPAL Modéré | G270: Region | H270: NOTABLE | I270: Au passage, sur quelle région d’investissement est-il positionné ? | J270: World | K270: Résultat Information trouvée La région d’investissement du fonds « R-co OPAL Modéré » est : Monde Détails complémentaires Cette information correspond à la fiche du fonds en statut Production. | L270: Correct | M270: texte | N270: Règles | O270: 9.01 | P270: 1 | Q270: 46310.571 | R270: Correct | S270: Oui | T270: =IF(S270="Oui",IF(R270=L270,"Identique","Changé"),"") -> Identique
A271: Q0270 | B271: C054 | C271: 5 | D271: CONTRASTE | E271: ESG / EET | F271: R-co OPAL Modéré | G271: ESG - SFDR Article | H271: NOTABLE | I271: Pour compléter la fiche, il relève de quel article SFDR ? | J271: Article 8 | K271: Résultat Information trouvée Le fonds « R-co OPAL Modéré » relève de : Article 8 (SFDR) Détails complémentaires L’information est issue de la fiche du fonds en statut Production. | L271: Correct | M271: texte | N271: Règles | O271: 10.71 | P271: 1 | Q271: 46310.571 | R271: Correct | S271: Oui | T271: =IF(S271="Oui",IF(R271=L271,"Identique","Changé"),"") -> Identique
A272: Q0271 | B272: C055 | C272: 1 | D272: PRIORITAIRE | E272: Gérants et dates de gestion | F272: R-co Conviction High Yield Euro | G272: Portfolio Manager | H272: NOTABLE | I272: Je prépare une fiche sur R-co Conviction High Yield Euro : peux-tu me donner le nom du gérant principal ? | J272: AGAESSE Kristell | K272: Résultat Information trouvée Le gérant principal du fonds « R-co Conviction High Yield Euro » est : AGAESSE Kristell. Détails complémentaires Le fonds « R-co Conviction High Yield Euro » est actuellement en statut Production. | L272: Correct | M272: texte | N272: Règles | O272: 42.23 | P272: 1 | Q272: 46310.572 | R272: Correct | S272: Oui | T272: =IF(S272="Oui",IF(R272=L272,"Identique","Changé"),"") -> Identique
A273: Q0272 | B273: C055 | C273: 2 | D273: PRIORITAIRE | E273: Autres | F273: R-co Conviction High Yield Euro | G273: Accounting Currency | H273: NOTABLE | I273: Autre point sur ce fonds : quelle est sa devise comptable ? | J273: EUR | K273: Résultat Information trouvée La devise comptable du fonds « R-co Conviction High Yield Euro » est l’euro (EUR). Détails complémentaires Symbole de la devise : €. | L273: Correct | M273: texte | N273: Règles | O273: 14.62 | P273: 1 | Q273: 46310.572 | R273: Correct | S273: Oui | T273: =IF(S273="Oui",IF(R273=L273,"Identique","Changé"),"") -> Identique
... A500: Q0499 | B500: C100 | C500: 4 | D500: CONTRASTE | E500: Intervenants | F500: R-co Midcap France | G500: Fund Administrator | H500: NOTABLE | I500: Pour compléter la fiche, quel administrateur est renseigné ? | J500: Caceis Fund Administration | K500: Résultat Pour le fonds « R-co Midcap France », l’administrateur (valorisateur) renseigné est : Caceis Fund Administration Détails complémentaires Caceis Fund Administration est l’établissement indiqué comme administrateur du fonds dans le référentiel Product Info. | L500: Correct | M500: texte | N500: Règles | O500: 15.99 | P500: 1 | Q500: 46310.664 | R500: Correct | S500: Oui | T500: =IF(S500="Oui",IF(R500=L500,"Identique","Changé"),"") -> Identique
A501: Q0500 | B501: C100 | C501: 5 | D501: CONTRASTE | E501: Textes longs | F501: Domitius | G501: Investment objective (FR) | H501: NOTABLE | I501: Je passe à un autre dossier : pour Domitius, quelle information est renseignée sur l’objectif de gestion en français ? | J501: Domitius a pour objectif de rechercher, sur la durée de placement recommandé, une performance positive, en investissant essentiellement sur les marchés de taux mondiaux. Le portefeuille est composé à 90% minimum d'OPC de taux et/ou diversifiés (dont notamment les OPC spécialisés en obligations convertibles), ainsi qu'en obligations en direct. Le FIA aura également la possibilité d'investir en actions à titre accessoire et, dans la limite globale de 30 % de son actif, en obligations non notées ou à haut rendement à caractère spéculatif. | K501: Résultat Pour le fonds « Domitius », l’objectif de gestion en français renseigné est : « Domitius a pour objectif de rechercher, sur la durée de placement recommandé, une performance positive, en investissant essentiellement sur les marchés de taux mondiaux. Le portefeuille est composé à 90% minimum d'OPC de taux et/ou diversifiés (dont notamment les OPC spécialisés en obligations convertibles), ainsi qu'en obligations en direct. Le FIA aura également la possibilité d'investir en actions à titre accessoire et, dans la limite globale de 30 % de son actif, en obligations non notées ou à haut rendement à caractère spéculatif. » Détails complémentaires Cette description correspond à l’objectif de gestion en français actuellement renseigné pour le fonds Domitius. | L501: Correct | M501: texte long (98% des mots) | N501: Règles | O501: 13.43 | P501: 1 | Q501: 46310.664 | S501: Non | T501: =IF(S501="Oui",IF(R501=L501,"Identique","Changé"),"")
A502: Q0501 | B502: C101 | C502: 1 | D502: PRIORITAIRE | E502: Frais et coûts | F502: R-co Conviction High Yield SD Euro | G502: Max Indirect Management fees (%) | H502: NOTABLE | I502: Je vérifie R-co Conviction High Yield SD Euro avant d’envoyer une fiche client : le plafond des frais indirects de gestion ? | J502: 0 | K502: Je ne trouve pas directement la part « R-co Conviction High Yield SD Euro » dans les données accessibles avec les informations disponibles. Pour vérifier le plafond des frais indirects de gestion de cette part avant envoi de la fiche client, il me faut pouvoir identifier précisément l’enregistrement produit correspondant (par exemple via le code ISIN ou l’intitulé exact de la part tel qu’il figure dans le référentiel). Résultat Aucune information disponible pour cette demande. | L502: Pas d’info à tort | M502: l'agent dit ne pas avoir la donnée | N502: Règles | O502: 24.91 | P502: 1 | Q502: 46310.664 | S502: Non | T502: =IF(S502="Oui",IF(R502=L502,"Identique","Changé"),"")
A503: Q0502 | B503: C101 | C503: 2 | D503: PRIORITAIRE | E503: ESG / EET | F503: R-co Conviction High Yield SD Euro | G503: % Min SI (EET 20420) | H503: NOTABLE | I503: Pour ce même produit, la part minimale d’investissements durables déclarée dans l’EET ? | J503: 30 | K503: Résultat Aucune information disponible pour cette demande. Je ne parviens pas à identifier dans les données accessibles le produit « R-co Conviction High Yield SD Euro ». Sans correspondance produit ou part retrouvée dans le référentiel, la valeur « part minimale d’investissements durables déclarée dans l’EET » ne peut pas être déterminée. | L503: Pas d’info à tort | M503: l'agent dit ne pas avoir la donnée | N503: Règles | O503: 12.1 | P503: 1 | Q503: 46310.665 | S503: Non | T503: =IF(S503="Oui",IF(R503=L503,"Identique","Changé"),"")
A504: Q0503 | B504: C101 | C504: 3 | D504: PRIORITAIRE | E504: Textes longs | F504: R-co Conviction High Yield SD Euro | G504: Investment objective (FR) | H504: NOTABLE | I504: Quelle donnée faut-il retenir pour l’objectif de gestion en français ? | J504: Le compartiment a pour objectif de gestion d'obtenir, sur la durée de placement recommandée supérieure à 3 ans, une performance nette de frais de gestion supérieure à celle de son indice de référence (ICE BofA BB-B 1-3 Year Euro Developed Markets High Yield Constrained Custom Index) en s’exposant de façon dynamique au marché des titres spéculatifs à haut rendement à court-moyen terme libellé en euro grâce à une gestion discrétionnaire reposant sur l’analyse du risque crédit des émetteurs et de l’analyse de la courbe des taux. | K504: Résultat Aucune information disponible pour cette demande. Je ne dispose pas, dans les données consultées, d’une définition permettant d’identifier quel champ ou quelle donnée doit être retenu pour l’objectif de gestion en français. Pour répondre de manière fiable, il faudrait retrouver le produit ou la documentation métier correspondante dans le référentiel. | L504: Pas d’info à tort | M504: l'agent dit ne pas avoir la donnée | N504: Règles | O504: 12.37 | P504: 1 | Q504: 46310.665 | S504: Non | T504: =IF(S504="Oui",IF(R504=L504,"Identique","Changé"),"")
A505: Q0504 | B505: C101 | C505: 4 | D505: PRIORITAIRE | E505: Textes longs | F505: R-co Conviction High Yield SD Euro | G505: Strategic allocation (FR) | H505: NOTABLE | I505: Passe maintenant à l’allocation stratégique en français. | J505: Le portefeuille de R-co Conviction High Yield SD Euro est composé d’obligations et de titres de créances négociables, à taux fixe, variable ou révisable, de titres subordonnés (dont 20% maximum de l’actif net d’obligations contingentes convertibles) et jusqu’à 100% d’obligations callable/puttable, d’obligations indexées, de toute qualité de signature, de toute échéance, de toute maturité (la maturité moyenne du portefeuille ne devant pas excéder 3 ans) et de bons à moyen terme négociables, ainsi que d’obligations convertibles (jusqu’à 10% maximum). Le compartiment pourra être investi dans des titres et obligations émis par des Etats non-membres de l’OCDE et/ou des émetteurs ayant leur siège social dans un pays hors OCDE (y compris les pays émergents) jusqu’à 10% maximum de son actif. L'exposition aux obligations et de titres de créances négociables non libellés en euro restera accessoire. | K505: Résultat Aucune information disponible pour cette demande. Je ne trouve pas dans les données accessibles d’information permettant d’identifier la donnée de référence à utiliser pour l’allocation stratégique en français. Aucune règle métier ou donnée correspondante n’a été retrouvée dans le référentiel consulté. | L505: Pas d’info à tort | M505: l'agent dit ne pas avoir la donnée | N505: Règles | O505: 9.95 | P505: 1 | Q505: 46310.665 | S505: Non | T505: =IF(S505="Oui",IF(R505=L505,"Identique","Changé"),"")
A506: Q0505 | B506: C101 | C506: 5 | D506: PRIORITAIRE | E506: Frais et coûts | F506: R-co Conviction High Yield SD Euro | G506: Explicit Transaction costs ex-ante - 3 years mean | H506: NOTABLE | I506: Et pour la moyenne triennale des coûts de transaction explicites ex ante, qu’est-ce qui est indiqué ? | J506: 0 | K506: Résultat Aucune information disponible pour cette demande. Je ne retrouve pas dans les données accessibles la valeur ou la règle associée à la « moyenne triennale des coûts de transaction explicites ex ante ». Aucune information exploitable n’a été trouvée pour ce champ. | L506: Pas d’info à tort | M506: l'agent dit ne pas avoir la donnée | N506: Règles | O506: 12.45 | P506: 1 | Q506: 46310.665 | S506: Non | T506: =IF(S506="Oui",IF(R506=L506,"Identique","Changé"),"")
A507: Q0506 | B507: C102 | C507: 1 | D507: CONTRASTE | E507: Frais et coûts | F507: IPBP Oblig Inter | G507: Max Indirect Management fees (%) | H507: NOTABLE | I507: Concernant IPBP Oblig Inter, peux-tu retrouver le plafond des frais indirects de gestion dans la fiche ? | J507: 1.5 | K507: Résultat Pour le fonds IPBP Oblig Inter (statut Production), le plafond des frais indirects de gestion indiqué dans la fiche est de 1,50 %. Détails complémentaires Fonds : IPBP Oblig Inter Statut : Production Plafond des frais indirects de gestion : 1,50 % (en devise de référence du fonds) | L507: Correct | M507: nombre | N507: Règles | O507: 57.91 | P507: 1 | Q507: 46310.666 | S507: Non | T507: =IF(S507="Oui",IF(R507=L507,"Identique","Changé"),"")
A508: Q0507 | B508: C102 | C508: 2 | D508: CONTRASTE | E508: ESG / EET | F508: IPBP Oblig Inter | G508: % Min SI (EET 20420) | H508: NOTABLE | I508: Dans la continuité, la part minimale d’investissements durables déclarée dans l’EET ? | J508: 5 | K508: Résultat Pour le fonds IPBP Oblig Inter (statut Production), la part minimale d’investissements durables déclarée dans l’EET est de 5 %. Détails complémentaires Fonds : IPBP Oblig Inter Part minimale d’investissements durables déclarée dans l’EET : 5 % | L508: Correct | M508: nombre | N508: Règles | O508: 7.67 | P508: 1 | Q508: 46310.666 | S508: Non | T508: =IF(S508="Oui",IF(R508=L508,"Identique","Changé"),"")
A509: Q0508 | B509: C102 | C509: 3 | D509: CONTRASTE | E509: Textes longs | F509: AXA Sélection Flexible | G509: Strategic allocation (FR) | H509: EXPLORATOIRE | I509: Autre dossier, AXA Sélection Flexible : peux-tu vérifier l’allocation stratégique en français ? | J509: nan | K509: Résultat Pour AXA Sélection Flexible (version Production), l’allocation stratégique en français n’est pas renseignée dans la fiche. En revanche, l’allocation stratégique est présente uniquement en anglais : 0 % à 100 % de l’actif net en produits de taux ou obligations convertibles (souveraines ou d’entreprises, notées ou non notées) ; les investissements High Yield sont limités à 20 % de l’actif net. 0 % à 100 % de l’actif net en actions de moyennes et grandes capitalisations. 0 % à 20 % de l’actif net en actions de petites capitalisations. 0 % à 10 % de l’actif net en OPCVM contribuant à l’objectif d’investissement du fonds. Actifs monétaires et instruments du marché monétaire. Jusqu’à 20 % de l’actif net dans les économies émergentes. Détails complémentaires La fiche contient bien un objectif de gestion en français, mais le champ « allocation stratégique en français » n’est pas alimenté. Seule la version anglaise de l’allocation stratégique est disponible dans le référentiel. | L509: Abstention correcte | M509: cellule vide, l'agent n'invente pas | N509: Règles | O509: 38.35 | P509: 1 | Q509: 46310.667 | S509: Non | T509: =IF(S509="Oui",IF(R509=L509,"Identique","Changé"),"")
A510: Q0509 | B510: C102 | C510: 4 | D510: CONTRASTE | E510: Frais et coûts | F510: AXA Sélection Flexible | G510: High Water Mark | H510: NOTABLE | I510: Je voudrais également la mention relative au high water mark. | J510: Pas de high water mark | K510: Résultat Pour AXA Sélection Flexible (statut Production), la mention relative au High Water Mark est : Pas de high water mark. Détails complémentaires Aucune mécanique de commission de surperformance fondée sur un High Water Mark n’est indiquée dans la fiche du produit. | L510: Correct | M510: texte | N510: Règles | O510: 7.81 | P510: 1 | Q510: 46310.667 | S510: Non | T510: =IF(S510="Oui",IF(R510=L510,"Identique","Changé"),"")
A511: Q0510 | B511: C102 | C511: 5 | D511: CONTRASTE | E511: Frais et coûts | F511: IPBP Oblig Inter | G511: Rétrocessions OPC De Tête | H511: NOTABLE | I511: Dernier point sur IPBP Oblig Inter, et non sur le fonds précédent : l’indicateur de rétrocessions sur OPC de tête ? | J511: Yes | K511: Résultat Pour IPBP Oblig Inter, l’indicateur de rétrocessions sur OPC de tête est renseigné à : Oui Détails complémentaires La fiche du fonds indique que le fonds perçoit des rétrocessions sur OPC de tête. | L511: Correct | M511: texte | N511: Règles | O511: 10.03 | P511: 1 | Q511: 46310.667 | S511: Non | T511: =IF(S511="Oui",IF(R511=L511,"Identique","Changé"),"")
A512: Q0511 | B512: C103 | C512: 1 | D512: PRIORITAIRE | E512: Frais et coûts | F512: R-co Conviction Club | G512: Implicit trans. costs ex ante/3Y mean | H512: NOTABLE | I512: Pour R-co Conviction Club, je cherche la moyenne triennale des coûts de transaction implicites ex ante. Quelle information est enregistrée ? | J512: 0.02 | K512: Résultat Information trouvée Pour le fonds R-co Conviction Club, la valeur enregistrée pour la moyenne triennale des coûts de transaction implicites ex ante est de 0,02. Cette information est rattachée à l’année de référence 2025. Détails complémentaires Fonds : R-co Conviction Club Coûts de transaction implicites ex ante (moyenne triennale) : 0,02 Année de référence : 2025 | L512: Correct | M512: nombre | N512: Règles | O512: 33.3 | P512: 1 | Q512: 46310.668 | S512: Non | T512: =IF(S512="Oui",IF(R512=L512,"Identique","Changé"),"")
...

Sheet PAR_FAMILLE
A1: Résultats par famille de champs
A2: Familles triées de la plus faible à la plus forte (% correct). Regroupement des champs : voir LISEZ-MOI.
A4: Famille de champs | B4: Notées | C4: Correct | D4: « Aucune info » à tort | E4: Valeur fausse | F4: Hors sujet | G4: % correct | H4: % aucune info | I4: % faux | J4: % hors sujet | K4: Latence moy. (s)
A5: Risque | B5: =COUNTIFS(DONNEES!$H$2:$H$1501,"NOTABLE",DONNEES!$L$2:$L$1501,"Correct",DONNEES!$E$2:$E$1501,$A5)+COUNTIFS(DONNEES!$H$2:$H$1501,"NOTABLE",DONNEES!$L$2:$L$1501,"Pas d’info à tort",DONNEES!$E$2:$E$1501,$A5)+COUNTIFS(DONNEES!$H$2:$H$1501,"NOTABLE",DONNEES!$L$2:$L$1501,"Incorrect",DONNEES!$E$2:$E$1501,$A5)+COUNTIFS(DONNEES!$H$2:$H$1501,"NOTABLE",DONNEES!$L$2:$L$1501,"Hors sujet",DONNEES!$E$2:$E$1501,$A5) -> 110 | C5: =COUNTIFS(DONNEES!$H$2:$H$1501,"NOTABLE",DONNEES!$L$2:$L$1501,"Correct",DONNEES!$E$2:$E$1501,$A5) -> 53 | D5: =COUNTIFS(DONNEES!$H$2:$H$1501,"NOTABLE",DONNEES!$L$2:$L$1501,"Pas d’info à tort",DONNEES!$E$2:$E$1501,$A5) -> 56 | E5: =COUNTIFS(DONNEES!$H$2:$H$1501,"NOTABLE",DONNEES!$L$2:$L$1501,"Incorrect",DONNEES!$E$2:$E$1501,$A5) -> 0 | F5: =COUNTIFS(DONNEES!$H$2:$H$1501,"NOTABLE",DONNEES!$L$2:$L$1501,"Hors sujet",DONNEES!$E$2:$E$1501,$A5) -> 1 | G5: =IF($B5=0,"",C5/$B5) -> 0.48181818 | H5: =IF($B5=0,"",D5/$B5) -> 0.50909091 | I5: =IF($B5=0,"",E5/$B5) -> 0 | J5: =IF($B5=0,"",F5/$B5) -> 0.0090909091 | K5: =IFERROR(AVERAGEIFS(DONNEES!$O$2:$O$1501,DONNEES!$E$2:$E$1501,$A5),"") -> 20.267273
A6: ESG / EET | B6: =COUNTIFS(DONNEES!$H$2:$H$1501,"NOTABLE",DONNEES!$L$2:$L$1501,"Correct",DONNEES!$E$2:$E$1501,$A6)+COUNTIFS(DONNEES!$H$2:$H$1501,"NOTABLE",DONNEES!$L$2:$L$1501,"Pas d’info à tort",DONNEES!$E$2:$E$1501,$A6)+COUNTIFS(DONNEES!$H$2:$H$1501,"NOTABLE",DONNEES!$L$2:$L$1501,"Incorrect",DONNEES!$E$2:$E$1501,$A6)+COUNTIFS(DONNEES!$H$2:$H$1501,"NOTABLE",DONNEES!$L$2:$L$1501,"Hors sujet",DONNEES!$E$2:$E$1501,$A6) -> 262 | C6: =COUNTIFS(DONNEES!$H$2:$H$1501,"NOTABLE",DONNEES!$L$2:$L$1501,"Correct",DONNEES!$E$2:$E$1501,$A6) -> 203 | D6: =COUNTIFS(DONNEES!$H$2:$H$1501,"NOTABLE",DONNEES!$L$2:$L$1501,"Pas d’info à tort",DONNEES!$E$2:$E$1501,$A6) -> 38 | E6: =COUNTIFS(DONNEES!$H$2:$H$1501,"NOTABLE",DONNEES!$L$2:$L$1501,"Incorrect",DONNEES!$E$2:$E$1501,$A6) -> 17 | F6: =COUNTIFS(DONNEES!$H$2:$H$1501,"NOTABLE",DONNEES!$L$2:$L$1501,"Hors sujet",DONNEES!$E$2:$E$1501,$A6) -> 4 | G6: =IF($B6=0,"",C6/$B6) -> 0.77480916 | H6: =IF($B6=0,"",D6/$B6) -> 0.14503817 | I6: =IF($B6=0,"",E6/$B6) -> 0.064885496 | J6: =IF($B6=0,"",F6/$B6) -> 0.015267176 | K6: =IFERROR(AVERAGEIFS(DONNEES!$O$2:$O$1501,DONNEES!$E$2:$E$1501,$A6),"") -> 18.137491
A7: Expertise et gamme | B7: =COUNTIFS(DONNEES!$H$2:$H$1501,"NOTABLE",DONNEES!$L$2:$L$1501,"Correct",DONNEES!$E$2:$E$1501,$A7)+COUNTIFS(DONNEES!$H$2:$H$1501,"NOTABLE",DONNEES!$L$2:$L$1501,"Pas d’info à tort",DONNEES!$E$2:$E$1501,$A7)+COUNTIFS(DONNEES!$H$2:$H$1501,"NOTABLE",DONNEES!$L$2:$L$1501,"Incorrect",DONNEES!$E$2:$E$1501,$A7)+COUNTIFS(DONNEES!$H$2:$H$1501,"NOTABLE",DONNEES!$L$2:$L$1501,"Hors sujet",DONNEES!$E$2:$E$1501,$A7) -> 135 | C7: =COUNTIFS(DONNEES!$H$2:$H$1501,"NOTABLE",DONNEES!$L$2:$L$1501,"Correct",DONNEES!$E$2:$E$1501,$A7) -> 107 | D7: =COUNTIFS(DONNEES!$H$2:$H$1501,"NOTABLE",DONNEES!$L$2:$L$1501,"Pas d’info à tort",DONNEES!$E$2:$E$1501,$A7) -> 22 | E7: =COUNTIFS(DONNEES!$H$2:$H$1501,"NOTABLE",DONNEES!$L$2:$L$1501,"Incorrect",DONNEES!$E$2:$E$1501,$A7) -> 4 | F7: =COUNTIFS(DONNEES!$H$2:$H$1501,"NOTABLE",DONNEES!$L$2:$L$1501,"Hors sujet",DONNEES!$E$2:$E$1501,$A7) -> 2 | G7: =IF($B7=0,"",C7/$B7) -> 0.79259259 | H7: =IF($B7=0,"",D7/$B7) -> 0.16296296 | I7: =IF($B7=0,"",E7/$B7) -> 0.02962963 | J7: =IF($B7=0,"",F7/$B7) -> 0.014814815 | K7: =IFERROR(AVERAGEIFS(DONNEES!$O$2:$O$1501,DONNEES!$E$2:$E$1501,$A7),"") -> 19.500815
A8: Frais et coûts | B8: =COUNTIFS(DONNEES!$H$2:$H$1501,"NOTABLE",DONNEES!$L$2:$L$1501,"Correct",DONNEES!$E$2:$E$1501,$A8)+COUNTIFS(DONNEES!$H$2:$H$1501,"NOTABLE",DONNEES!$L$2:$L$1501,"Pas d’info à tort",DONNEES!$E$2:$E$1501,$A8)+COUNTIFS(DONNEES!$H$2:$H$1501,"NOTABLE",DONNEES!$L$2:$L$1501,"Incorrect",DONNEES!$E$2:$E$1501,$A8)+COUNTIFS(DONNEES!$H$2:$H$1501,"NOTABLE",DONNEES!$L$2:$L$1501,"Hors sujet",DONNEES!$E$2:$E$1501,$A8) -> 192 | C8: =COUNTIFS(DONNEES!$H$2:$H$1501,"NOTABLE",DONNEES!$L$2:$L$1501,"Correct",DONNEES!$E$2:$E$1501,$A8) -> 159 | D8: =COUNTIFS(DONNEES!$H$2:$H$1501,"NOTABLE",DONNEES!$L$2:$L$1501,"Pas d’info à tort",DONNEES!$E$2:$E$1501,$A8) -> 16 | E8: =COUNTIFS(DONNEES!$H$2:$H$1501,"NOTABLE",DONNEES!$L$2:$L$1501,"Incorrect",DONNEES!$E$2:$E$1501,$A8) -> 14 | F8: =COUNTIFS(DONNEES!$H$2:$H$1501,"NOTABLE",DONNEES!$L$2:$L$1501,"Hors sujet",DONNEES!$E$2:$E$1501,$A8) -> 3 | G8: =IF($B8=0,"",C8/$B8) -> 0.828125 | H8: =IF($B8=0,"",D8/$B8) -> 0.083333333 | I8: =IF($B8=0,"",E8/$B8) -> 0.072916667 | J8: =IF($B8=0,"",F8/$B8) -> 0.015625 | K8: =IFERROR(AVERAGEIFS(DONNEES!$O$2:$O$1501,DONNEES!$E$2:$E$1501,$A8),"") -> 17.708
A9: Textes longs | B9: =COUNTIFS(DONNEES!$H$2:$H$1501,"NOTABLE",DONNEES!$L$2:$L$1501,"Correct",DONNEES!$E$2:$E$1501,$A9)+COUNTIFS(DONNEES!$H$2:$H$1501,"NOTABLE",DONNEES!$L$2:$L$1501,"Pas d’info à tort",DONNEES!$E$2:$E$1501,$A9)+COUNTIFS(DONNEES!$H$2:$H$1501,"NOTABLE",DONNEES!$L$2:$L$1501,"Incorrect",DONNEES!$E$2:$E$1501,$A9)+COUNTIFS(DONNEES!$H$2:$H$1501,"NOTABLE",DONNEES!$L$2:$L$1501,"Hors sujet",DONNEES!$E$2:$E$1501,$A9) -> 79 | C9: =COUNTIFS(DONNEES!$H$2:$H$1501,"NOTABLE",DONNEES!$L$2:$L$1501,"Correct",DONNEES!$E$2:$E$1501,$A9) -> 66 | D9: =COUNTIFS(DONNEES!$H$2:$H$1501,"NOTABLE",DONNEES!$L$2:$L$1501,"Pas d’info à tort",DONNEES!$E$2:$E$1501,$A9) -> 11 | E9: =COUNTIFS(DONNEES!$H$2:$H$1501,"NOTABLE",DONNEES!$L$2:$L$1501,"Incorrect",DONNEES!$E$2:$E$1501,$A9) -> 1 | F9: =COUNTIFS(DONNEES!$H$2:$H$1501,"NOTABLE",DONNEES!$L$2:$L$1501,"Hors sujet",DONNEES!$E$2:$E$1501,$A9) -> 1 | G9: =IF($B9=0,"",C9/$B9) -> 0.83544304 | H9: =IF($B9=0,"",D9/$B9) -> 0.13924051 | I9: =IF($B9=0,"",E9/$B9) -> 0.012658228 | J9: =IF($B9=0,"",F9/$B9) -> 0.012658228 | K9: =IFERROR(AVERAGEIFS(DONNEES!$O$2:$O$1501,DONNEES!$E$2:$E$1501,$A9),"") -> 17.494
A10: Juridique et réglementaire | B10: =COUNTIFS(DONNEES!$H$2:$H$1501,"NOTABLE",DONNEES!$L$2:$L$1501,"Correct",DONNEES!$E$2:$E$1501,$A10)+COUNTIFS(DONNEES!$H$2:$H$1501,"NOTABLE",DONNEES!$L$2:$L$1501,"Pas d’info à tort",DONNEES!$E$2:$E$1501,$A10)+COUNTIFS(DONNEES!$H$2:$H$1501,"NOTABLE",DONNEES!$L$2:$L$1501,"Incorrect",DONNEES!$E$2:$E$1501,$A10)+COUNTIFS(DONNEES!$H$2:$H$1501,"NOTABLE",DONNEES!$L$2:$L$1501,"Hors sujet",DONNEES!$E$2:$E$1501,$A10) -> 172 | C10: =COUNTIFS(DONNEES!$H$2:$H$1501,"NOTABLE",DONNEES!$L$2:$L$1501,"Correct",DONNEES!$E$2:$E$1501,$A10) -> 149 | D10: =COUNTIFS(DONNEES!$H$2:$H$1501,"NOTABLE",DONNEES!$L$2:$L$1501,"Pas d’info à tort",DONNEES!$E$2:$E$1501,$A10) -> 13 | E10: =COUNTIFS(DONNEES!$H$2:$H$1501,"NOTABLE",DONNEES!$L$2:$L$1501,"Incorrect",DONNEES!$E$2:$E$1501,$A10) -> 6 | F10: =COUNTIFS(DONNEES!$H$2:$H$1501,"NOTABLE",DONNEES!$L$2:$L$1501,"Hors sujet",DONNEES!$E$2:$E$1501,$A10) -> 4 | G10: =IF($B10=0,"",C10/$B10) -> 0.86627907 | H10: =IF($B10=0,"",D10/$B10) -> 0.075581395 | I10: =IF($B10=0,"",E10/$B10) -> 0.034883721 | J10: =IF($B10=0,"",F10/$B10) -> 0.023255814 | K10: =IFERROR(AVERAGEIFS(DONNEES!$O$2:$O$1501,DONNEES!$E$2:$E$1501,$A10),"") -> 16.439017
A11: Autres | B11: =COUNTIFS(DONNEES!$H$2:$H$1501,"NOTABLE",DONNEES!$L$2:$L$1501,"Correct",DONNEES!$E$2:$E$1501,$A11)+COUNTIFS(DONNEES!$H$2:$H$1501,"NOTABLE",DONNEES!$L$2:$L$1501,"Pas d’info à tort",DONNEES!$E$2:$E$1501,$A11)+COUNTIFS(DONNEES!$H$2:$H$1501,"NOTABLE",DONNEES!$L$2:$L$1501,"Incorrect",DONNEES!$E$2:$E$1501,$A11)+COUNTIFS(DONNEES!$H$2:$H$1501,"NOTABLE",DONNEES!$L$2:$L$1501,"Hors sujet",DONNEES!$E$2:$E$1501,$A11) -> 68 | C11: =COUNTIFS(DONNEES!$H$2:$H$1501,"NOTABLE",DONNEES!$L$2:$L$1501,"Correct",DONNEES!$E$2:$E$1501,$A11) -> 59 | D11: =COUNTIFS(DONNEES!$H$2:$H$1501,"NOTABLE",DONNEES!$L$2:$L$1501,"Pas d’info à tort",DONNEES!$E$2:$E$1501,$A11) -> 7 | E11: =COUNTIFS(DONNEES!$H$2:$H$1501,"NOTABLE",DONNEES!$L$2:$L$1501,"Incorrect",DONNEES!$E$2:$E$1501,$A11) -> 1 | F11: =COUNTIFS(DONNEES!$H$2:$H$1501,"NOTABLE",DONNEES!$L$2:$L$1501,"Hors sujet",DONNEES!$E$2:$E$1501,$A11) -> 1 | G11: =IF($B11=0,"",C11/$B11) -> 0.86764706 | H11: =IF($B11=0,"",D11/$B11) -> 0.10294118 | I11: =IF($B11=0,"",E11/$B11) -> 0.014705882 | J11: =IF($B11=0,"",F11/$B11) -> 0.014705882 | K11: =IFERROR(AVERAGEIFS(DONNEES!$O$2:$O$1501,DONNEES!$E$2:$E$1501,$A11),"") -> 16.235
A12: Intervenants | B12: =COUNTIFS(DONNEES!$H$2:$H$1501,"NOTABLE",DONNEES!$L$2:$L$1501,"Correct",DONNEES!$E$2:$E$1501,$A12)+COUNTIFS(DONNEES!$H$2:$H$1501,"NOTABLE",DONNEES!$L$2:$L$1501,"Pas d’info à tort",DONNEES!$E$2:$E$1501,$A12)+COUNTIFS(DONNEES!$H$2:$H$1501,"NOTABLE",DONNEES!$L$2:$L$1501,"Incorrect",DONNEES!$E$2:$E$1501,$A12)+COUNTIFS(DONNEES!$H$2:$H$1501,"NOTABLE",DONNEES!$L$2:$L$1501,"Hors sujet",DONNEES!$E$2:$E$1501,$A12) -> 186 | C12: =COUNTIFS(DONNEES!$H$2:$H$1501,"NOTABLE",DONNEES!$L$2:$L$1501,"Correct",DONNEES!$E$2:$E$1501,$A12) -> 164 | D12: =COUNTIFS(DONNEES!$H$2:$H$1501,"NOTABLE",DONNEES!$L$2:$L$1501,"Pas d’info à tort",DONNEES!$E$2:$E$1501,$A12) -> 15 | E12: =COUNTIFS(DONNEES!$H$2:$H$1501,"NOTABLE",DONNEES!$L$2:$L$1501,"Incorrect",DONNEES!$E$2:$E$1501,$A12) -> 3 | F12: =COUNTIFS(DONNEES!$H$2:$H$1501,"NOTABLE",DONNEES!$L$2:$L$1501,"Hors sujet",DONNEES!$E$2:$E$1501,$A12) -> 4 | G12: =IF($B12=0,"",C12/$B12) -> 0.88172043 | H12: =IF($B12=0,"",D12/$B12) -> 0.080645161 | I12: =IF($B12=0,"",E12/$B12) -> 0.016129032 | J12: =IF($B12=0,"",F12/$B12) -> 0.021505376 | K12: =IFERROR(AVERAGEIFS(DONNEES!$O$2:$O$1501,DONNEES!$E$2:$E$1501,$A12),"") -> 20.812941
A13: Dates et VL | B13: =COUNTIFS(DONNEES!$H$2:$H$1501,"NOTABLE",DONNEES!$L$2:$L$1501,"Correct",DONNEES!$E$2:$E$1501,$A13)+COUNTIFS(DONNEES!$H$2:$H$1501,"NOTABLE",DONNEES!$L$2:$L$1501,"Pas d’info à tort",DONNEES!$E$2:$E$1501,$A13)+COUNTIFS(DONNEES!$H$2:$H$1501,"NOTABLE",DONNEES!$L$2:$L$1501,"Incorrect",DONNEES!$E$2:$E$1501,$A13)+COUNTIFS(DONNEES!$H$2:$H$1501,"NOTABLE",DONNEES!$L$2:$L$1501,"Hors sujet",DONNEES!$E$2:$E$1501,$A13) -> 52 | C13: =COUNTIFS(DONNEES!$H$2:$H$1501,"NOTABLE",DONNEES!$L$2:$L$1501,"Correct",DONNEES!$E$2:$E$1501,$A13) -> 46 | D13: =COUNTIFS(DONNEES!$H$2:$H$1501,"NOTABLE",DONNEES!$L$2:$L$1501,"Pas d’info à tort",DONNEES!$E$2:$E$1501,$A13) -> 3 | E13: =COUNTIFS(DONNEES!$H$2:$H$1501,"NOTABLE",DONNEES!$L$2:$L$1501,"Incorrect",DONNEES!$E$2:$E$1501,$A13) -> 1 | F13: =COUNTIFS(DONNEES!$H$2:$H$1501,"NOTABLE",DONNEES!$L$2:$L$1501,"Hors sujet",DONNEES!$E$2:$E$1501,$A13) -> 2 | G13: =IF($B13=0,"",C13/$B13) -> 0.88461538 | H13: =IF($B13=0,"",D13/$B13) -> 0.057692308 | I13: =IF($B13=0,"",E13/$B13) -> 0.019230769 | J13: =IF($B13=0,"",F13/$B13) -> 0.038461538 | K13: =IFERROR(AVERAGEIFS(DONNEES!$O$2:$O$1501,DONNEES!$E$2:$E$1501,$A13),"") -> 15.66038
A14: Identifiants | B14: =COUNTIFS(DONNEES!$H$2:$H$1501,"NOTABLE",DONNEES!$L$2:$L$1501,"Correct",DONNEES!$E$2:$E$1501,$A14)+COUNTIFS(DONNEES!$H$2:$H$1501,"NOTABLE",DONNEES!$L$2:$L$1501,"Pas d’info à tort",DONNEES!$E$2:$E$1501,$A14)+COUNTIFS(DONNEES!$H$2:$H$1501,"NOTABLE",DONNEES!$L$2:$L$1501,"Incorrect",DONNEES!$E$2:$E$1501,$A14)+COUNTIFS(DONNEES!$H$2:$H$1501,"NOTABLE",DONNEES!$L$2:$L$1501,"Hors sujet",DONNEES!$E$2:$E$1501,$A14) -> 21 | C14: =COUNTIFS(DONNEES!$H$2:$H$1501,"NOTABLE",DONNEES!$L$2:$L$1501,"Correct",DONNEES!$E$2:$E$1501,$A14) -> 19 | D14: =COUNTIFS(DONNEES!$H$2:$H$1501,"NOTABLE",DONNEES!$L$2:$L$1501,"Pas d’info à tort",DONNEES!$E$2:$E$1501,$A14) -> 1 | E14: =COUNTIFS(DONNEES!$H$2:$H$1501,"NOTABLE",DONNEES!$L$2:$L$1501,"Incorrect",DONNEES!$E$2:$E$1501,$A14) -> 1 | F14: =COUNTIFS(DONNEES!$H$2:$H$1501,"NOTABLE",DONNEES!$L$2:$L$1501,"Hors sujet",DONNEES!$E$2:$E$1501,$A14) -> 0 | G14: =IF($B14=0,"",C14/$B14) -> 0.9047619 | H14: =IF($B14=0,"",D14/$B14) -> 0.047619048 | I14: =IF($B14=0,"",E14/$B14) -> 0.047619048 | J14: =IF($B14=0,"",F14/$B14) -> 0 | K14: =IFERROR(AVERAGEIFS(DONNEES!$O$2:$O$1501,DONNEES!$E$2:$E$1501,$A14),"") -> 14.6244
A15: Gérants et dates de gestion | B15: =COUNTIFS(DONNEES!$H$2:$H$1501,"NOTABLE",DONNEES!$L$2:$L$1501,"Correct",DONNEES!$E$2:$E$1501,$A15)+COUNTIFS(DONNEES!$H$2:$H$1501,"NOTABLE",DONNEES!$L$2:$L$1501,"Pas d’info à tort",DONNEES!$E$2:$E$1501,$A15)+COUNTIFS(DONNEES!$H$2:$H$1501,"NOTABLE",DONNEES!$L$2:$L$1501,"Incorrect",DONNEES!$E$2:$E$1501,$A15)+COUNTIFS(DONNEES!$H$2:$H$1501,"NOTABLE",DONNEES!$L$2:$L$1501,"Hors sujet",DONNEES!$E$2:$E$1501,$A15) -> 88 | C15: =COUNTIFS(DONNEES!$H$2:$H$1501,"NOTABLE",DONNEES!$L$2:$L$1501,"Correct",DONNEES!$E$2:$E$1501,$A15) -> 82 | D15: =COUNTIFS(DONNEES!$H$2:$H$1501,"NOTABLE",DONNEES!$L$2:$L$1501,"Pas d’info à tort",DONNEES!$E$2:$E$1501,$A15) -> 4 | E15: =COUNTIFS(DONNEES!$H$2:$H$1501,"NOTABLE",DONNEES!$L$2:$L$1501,"Incorrect",DONNEES!$E$2:$E$1501,$A15) -> 1 | F15: =COUNTIFS(DONNEES!$H$2:$H$1501,"NOTABLE",DONNEES!$L$2:$L$1501,"Hors sujet",DONNEES!$E$2:$E$1501,$A15) -> 1 | G15: =IF($B15=0,"",C15/$B15) -> 0.93181818 | H15: =IF($B15=0,"",D15/$B15) -> 0.045454545 | I15: =IF($B15=0,"",E15/$B15) -> 0.011363636 | J15: =IF($B15=0,"",F15/$B15) -> 0.011363636 | K15: =IFERROR(AVERAGEIFS(DONNEES!$O$2:$O$1501,DONNEES!$E$2:$E$1501,$A15),"") -> 22.289604

Sheet PAR_TOUR
A1: Résultats par tour de conversation
A2: Tour = position de la question dans sa conversation de 5 questions.
A4: Tour | B4: Notées | C4: Correct | D4: « Aucune info » à tort | E4: Valeur fausse | F4: Hors sujet | G4: % correct | H4: % aucune info | I4: % faux | J4: % hors sujet | K4: Latence moy. (s)
A5: 1 | B5: =COUNTIFS(DONNEES!$H$2:$H$1501,"NOTABLE",DONNEES!$L$2:$L$1501,"Correct",DONNEES!$C$2:$C$1501,$A5)+COUNTIFS(DONNEES!$H$2:$H$1501,"NOTABLE",DONNEES!$L$2:$L$1501,"Pas d’info à tort",DONNEES!$C$2:$C$1501,$A5)+COUNTIFS(DONNEES!$H$2:$H$1501,"NOTABLE",DONNEES!$L$2:$L$1501,"Incorrect",DONNEES!$C$2:$C$1501,$A5)+COUNTIFS(DONNEES!$H$2:$H$1501,"NOTABLE",DONNEES!$L$2:$L$1501,"Hors sujet",DONNEES!$C$2:$C$1501,$A5) -> 296 | C5: =COUNTIFS(DONNEES!$H$2:$H$1501,"NOTABLE",DONNEES!$L$2:$L$1501,"Correct",DONNEES!$C$2:$C$1501,$A5) -> 235 | D5: =COUNTIFS(DONNEES!$H$2:$H$1501,"NOTABLE",DONNEES!$L$2:$L$1501,"Pas d’info à tort",DONNEES!$C$2:$C$1501,$A5) -> 43 | E5: =COUNTIFS(DONNEES!$H$2:$H$1501,"NOTABLE",DONNEES!$L$2:$L$1501,"Incorrect",DONNEES!$C$2:$C$1501,$A5) -> 9 | F5: =COUNTIFS(DONNEES!$H$2:$H$1501,"NOTABLE",DONNEES!$L$2:$L$1501,"Hors sujet",DONNEES!$C$2:$C$1501,$A5) -> 9 | G5: =IF($B5=0,"",C5/$B5) -> 0.79391892 | H5: =IF($B5=0,"",D5/$B5) -> 0.14527027 | I5: =IF($B5=0,"",E5/$B5) -> 0.030405405 | J5: =IF($B5=0,"",F5/$B5) -> 0.030405405 | K5: =IFERROR(AVERAGEIFS(DONNEES!$O$2:$O$1501,DONNEES!$C$2:$C$1501,$A5),"") -> 38.271818
A6: 2 | B6: =COUNTIFS(DONNEES!$H$2:$H$1501,"NOTABLE",DONNEES!$L$2:$L$1501,"Correct",DONNEES!$C$2:$C$1501,$A6)+COUNTIFS(DONNEES!$H$2:$H$1501,"NOTABLE",DONNEES!$L$2:$L$1501,"Pas d’info à tort",DONNEES!$C$2:$C$1501,$A6)+COUNTIFS(DONNEES!$H$2:$H$1501,"NOTABLE",DONNEES!$L$2:$L$1501,"Incorrect",DONNEES!$C$2:$C$1501,$A6)+COUNTIFS(DONNEES!$H$2:$H$1501,"NOTABLE",DONNEES!$L$2:$L$1501,"Hors sujet",DONNEES!$C$2:$C$1501,$A6) -> 297 | C6: =COUNTIFS(DONNEES!$H$2:$H$1501,"NOTABLE",DONNEES!$L$2:$L$1501,"Correct",DONNEES!$C$2:$C$1501,$A6) -> 237 | D6: =COUNTIFS(DONNEES!$H$2:$H$1501,"NOTABLE",DONNEES!$L$2:$L$1501,"Pas d’info à tort",DONNEES!$C$2:$C$1501,$A6) -> 40 | E6: =COUNTIFS(DONNEES!$H$2:$H$1501,"NOTABLE",DONNEES!$L$2:$L$1501,"Incorrect",DONNEES!$C$2:$C$1501,$A6) -> 11 | F6: =COUNTIFS(DONNEES!$H$2:$H$1501,"NOTABLE",DONNEES!$L$2:$L$1501,"Hors sujet",DONNEES!$C$2:$C$1501,$A6) -> 9 | G6: =IF($B6=0,"",C6/$B6) -> 0.7979798 | H6: =IF($B6=0,"",D6/$B6) -> 0.13468013 | I6: =IF($B6=0,"",E6/$B6) -> 0.037037037 | J6: =IF($B6=0,"",F6/$B6) -> 0.03030303 | K6: =IFERROR(AVERAGEIFS(DONNEES!$O$2:$O$1501,DONNEES!$C$2:$C$1501,$A6),"") -> 12.815185
A7: 3 | B7: =COUNTIFS(DONNEES!$H$2:$H$1501,"NOTABLE",DONNEES!$L$2:$L$1501,"Correct",DONNEES!$C$2:$C$1501,$A7)+COUNTIFS(DONNEES!$H$2:$H$1501,"NOTABLE",DONNEES!$L$2:$L$1501,"Pas d’info à tort",DONNEES!$C$2:$C$1501,$A7)+COUNTIFS(DONNEES!$H$2:$H$1501,"NOTABLE",DONNEES!$L$2:$L$1501,"Incorrect",DONNEES!$C$2:$C$1501,$A7)+COUNTIFS(DONNEES!$H$2:$H$1501,"NOTABLE",DONNEES!$L$2:$L$1501,"Hors sujet",DONNEES!$C$2:$C$1501,$A7) -> 256 | C7: =COUNTIFS(DONNEES!$H$2:$H$1501,"NOTABLE",DONNEES!$L$2:$L$1501,"Correct",DONNEES!$C$2:$C$1501,$A7) -> 201 | D7: =COUNTIFS(DONNEES!$H$2:$H$1501,"NOTABLE",DONNEES!$L$2:$L$1501,"Pas d’info à tort",DONNEES!$C$2:$C$1501,$A7) -> 46 | E7: =COUNTIFS(DONNEES!$H$2:$H$1501,"NOTABLE",DONNEES!$L$2:$L$1501,"Incorrect",DONNEES!$C$2:$C$1501,$A7) -> 8 | F7: =COUNTIFS(DONNEES!$H$2:$H$1501,"NOTABLE",DONNEES!$L$2:$L$1501,"Hors sujet",DONNEES!$C$2:$C$1501,$A7) -> 1 | G7: =IF($B7=0,"",C7/$B7) -> 0.78515625 | H7: =IF($B7=0,"",D7/$B7) -> 0.1796875 | I7: =IF($B7=0,"",E7/$B7) -> 0.03125 | J7: =IF($B7=0,"",F7/$B7) -> 0.00390625 | K7: =IFERROR(AVERAGEIFS(DONNEES!$O$2:$O$1501,DONNEES!$C$2:$C$1501,$A7),"") -> 15.616061
A8: 4 | B8: =COUNTIFS(DONNEES!$H$2:$H$1501,"NOTABLE",DONNEES!$L$2:$L$1501,"Correct",DONNEES!$C$2:$C$1501,$A8)+COUNTIFS(DONNEES!$H$2:$H$1501,"NOTABLE",DONNEES!$L$2:$L$1501,"Pas d’info à tort",DONNEES!$C$2:$C$1501,$A8)+COUNTIFS(DONNEES!$H$2:$H$1501,"NOTABLE",DONNEES!$L$2:$L$1501,"Incorrect",DONNEES!$C$2:$C$1501,$A8)+COUNTIFS(DONNEES!$H$2:$H$1501,"NOTABLE",DONNEES!$L$2:$L$1501,"Hors sujet",DONNEES!$C$2:$C$1501,$A8) -> 219 | C8: =COUNTIFS(DONNEES!$H$2:$H$1501,"NOTABLE",DONNEES!$L$2:$L$1501,"Correct",DONNEES!$C$2:$C$1501,$A8) -> 186 | D8: =COUNTIFS(DONNEES!$H$2:$H$1501,"NOTABLE",DONNEES!$L$2:$L$1501,"Pas d’info à tort",DONNEES!$C$2:$C$1501,$A8) -> 25 | E8: =COUNTIFS(DONNEES!$H$2:$H$1501,"NOTABLE",DONNEES!$L$2:$L$1501,"Incorrect",DONNEES!$C$2:$C$1501,$A8) -> 6 | F8: =COUNTIFS(DONNEES!$H$2:$H$1501,"NOTABLE",DONNEES!$L$2:$L$1501,"Hors sujet",DONNEES!$C$2:$C$1501,$A8) -> 2 | G8: =IF($B8=0,"",C8/$B8) -> 0.84931507 | H8: =IF($B8=0,"",D8/$B8) -> 0.11415525 | I8: =IF($B8=0,"",E8/$B8) -> 0.02739726 | J8: =IF($B8=0,"",F8/$B8) -> 0.0091324201 | K8: =IFERROR(AVERAGEIFS(DONNEES!$O$2:$O$1501,DONNEES!$C$2:$C$1501,$A8),"") -> 12.335118
A9: 5 | B9: =COUNTIFS(DONNEES!$H$2:$H$1501,"NOTABLE",DONNEES!$L$2:$L$1501,"Correct",DONNEES!$C$2:$C$1501,$A9)+COUNTIFS(DONNEES!$H$2:$H$1501,"NOTABLE",DONNEES!$L$2:$L$1501,"Pas d’info à tort",DONNEES!$C$2:$C$1501,$A9)+COUNTIFS(DONNEES!$H$2:$H$1501,"NOTABLE",DONNEES!$L$2:$L$1501,"Incorrect",DONNEES!$C$2:$C$1501,$A9)+COUNTIFS(DONNEES!$H$2:$H$1501,"NOTABLE",DONNEES!$L$2:$L$1501,"Hors sujet",DONNEES!$C$2:$C$1501,$A9) -> 297 | C9: =COUNTIFS(DONNEES!$H$2:$H$1501,"NOTABLE",DONNEES!$L$2:$L$1501,"Correct",DONNEES!$C$2:$C$1501,$A9) -> 248 | D9: =COUNTIFS(DONNEES!$H$2:$H$1501,"NOTABLE",DONNEES!$L$2:$L$1501,"Pas d’info à tort",DONNEES!$C$2:$C$1501,$A9) -> 32 | E9: =COUNTIFS(DONNEES!$H$2:$H$1501,"NOTABLE",DONNEES!$L$2:$L$1501,"Incorrect",DONNEES!$C$2:$C$1501,$A9) -> 15 | F9: =COUNTIFS(DONNEES!$H$2:$H$1501,"NOTABLE",DONNEES!$L$2:$L$1501,"Hors sujet",DONNEES!$C$2:$C$1501,$A9) -> 2 | G9: =IF($B9=0,"",C9/$B9) -> 0.83501684 | H9: =IF($B9=0,"",D9/$B9) -> 0.10774411 | I9: =IF($B9=0,"",E9/$B9) -> 0.050505051 | J9: =IF($B9=0,"",F9/$B9) -> 0.0067340067 | K9: =IFERROR(AVERAGEIFS(DONNEES!$O$2:$O$1501,DONNEES!$C$2:$C$1501,$A9),"") -> 13.225455

Sheet PAR_CHAMP
A1: Résultats par champ
A2: Triés du plus faible au plus fort. Interpréter avec prudence sous 8 questions notées.
A4: Champ | B4: Notées | C4: Correct | D4: « Aucune info » à tort | E4: Valeur fausse | F4: Hors sujet | G4: % correct | H4: % aucune info | I4: % faux | J4: % hors sujet | K4: Latence moy. (s)
A5: Previous month SRI | B5: =COUNTIFS(DONNEES!$H$2:$H$1501,"NOTABLE",DONNEES!$L$2:$L$1501,"Correct",DONNEES!$G$2:$G$1501,$A5)+COUNTIFS(DONNEES!$H$2:$H$1501,"NOTABLE",DONNEES!$L$2:$L$1501,"Pas d’info à tort",DONNEES!$G$2:$G$1501,$A5)+COUNTIFS(DONNEES!$H$2:$H$1501,"NOTABLE",DONNEES!$L$2:$L$1501,"Incorrect",DONNEES!$G$2:$G$1501,$A5)+COUNTIFS(DONNEES!$H$2:$H$1501,"NOTABLE",DONNEES!$L$2:$L$1501,"Hors sujet",DONNEES!$G$2:$G$1501,$A5) -> 18 | C5: =COUNTIFS(DONNEES!$H$2:$H$1501,"NOTABLE",DONNEES!$L$2:$L$1501,"Correct",DONNEES!$G$2:$G$1501,$A5) -> 3 | D5: =COUNTIFS(DONNEES!$H$2:$H$1501,"NOTABLE",DONNEES!$L$2:$L$1501,"Pas d’info à tort",DONNEES!$G$2:$G$1501,$A5) -> 15 | E5: =COUNTIFS(DONNEES!$H$2:$H$1501,"NOTABLE",DONNEES!$L$2:$L$1501,"Incorrect",DONNEES!$G$2:$G$1501,$A5) -> 0 | F5: =COUNTIFS(DONNEES!$H$2:$H$1501,"NOTABLE",DONNEES!$L$2:$L$1501,"Hors sujet",DONNEES!$G$2:$G$1501,$A5) -> 0 | G5: =IF($B5=0,"",C5/$B5) -> 0.16666667 | H5: =IF($B5=0,"",D5/$B5) -> 0.83333333 | I5: =IF($B5=0,"",E5/$B5) -> 0 | J5: =IF($B5=0,"",F5/$B5) -> 0 | K5: =IFERROR(AVERAGEIFS(DONNEES!$O$2:$O$1501,DONNEES!$G$2:$G$1501,$A5),"") -> 26.377778
A6: Reference ESG Benchmark (EET 20370) | B6: =COUNTIFS(DONNEES!$H$2:$H$1501,"NOTABLE",DONNEES!$L$2:$L$1501,"Correct",DONNEES!$G$2:$G$1501,$A6)+COUNTIFS(DONNEES!$H$2:$H$1501,"NOTABLE",DONNEES!$L$2:$L$1501,"Pas d’info à tort",DONNEES!$G$2:$G$1501,$A6)+COUNTIFS(DONNEES!$H$2:$H$1501,"NOTABLE",DONNEES!$L$2:$L$1501,"Incorrect",DONNEES!$G$2:$G$1501,$A6)+COUNTIFS(DONNEES!$H$2:$H$1501,"NOTABLE",DONNEES!$L$2:$L$1501,"Hors sujet",DONNEES!$G$2:$G$1501,$A6) -> 14 | C6: =COUNTIFS(DONNEES!$H$2:$H$1501,"NOTABLE",DONNEES!$L$2:$L$1501,"Correct",DONNEES!$G$2:$G$1501,$A6) -> 3 | D6: =COUNTIFS(DONNEES!$H$2:$H$1501,"NOTABLE",DONNEES!$L$2:$L$1501,"Pas d’info à tort",DONNEES!$G$2:$G$1501,$A6) -> 7 | E6: =COUNTIFS(DONNEES!$H$2:$H$1501,"NOTABLE",DONNEES!$L$2:$L$1501,"Incorrect",DONNEES!$G$2:$G$1501,$A6) -> 4 | F6: =COUNTIFS(DONNEES!$H$2:$H$1501,"NOTABLE",DONNEES!$L$2:$L$1501,"Hors sujet",DONNEES!$G$2:$G$1501,$A6) -> 0 | G6: =IF($B6=0,"",C6/$B6) -> 0.21428571 | H6: =IF($B6=0,"",D6/$B6) -> 0.5 | I6: =IF($B6=0,"",E6/$B6) -> 0.28571429 | J6: =IF($B6=0,"",F6/$B6) -> 0 | K6: =IFERROR(AVERAGEIFS(DONNEES!$O$2:$O$1501,DONNEES!$G$2:$G$1501,$A6),"") -> 16.827857
A7: Volatility target | B7: =COUNTIFS(DONNEES!$H$2:$H$1501,"NOTABLE",DONNEES!$L$2:$L$1501,"Correct",DONNEES!$G$2:$G$1501,$A7)+COUNTIFS(DONNEES!$H$2:$H$1501,"NOTABLE",DONNEES!$L$2:$L$1501,"Pas d’info à tort",DONNEES!$G$2:$G$1501,$A7)+COUNTIFS(DONNEES!$H$2:$H$1501,"NOTABLE",DONNEES!$L$2:$L$1501,"Incorrect",DONNEES!$G$2:$G$1501,$A7)+COUNTIFS(DONNEES!$H$2:$H$1501,"NOTABLE",DONNEES!$L$2:$L$1501,"Hors sujet",DONNEES!$G$2:$G$1501,$A7) -> 14 | C7: =COUNTIFS(DONNEES!$H$2:$H$1501,"NOTABLE",DONNEES!$L$2:$L$1501,"Correct",DONNEES!$G$2:$G$1501,$A7) -> 3 | D7: =COUNTIFS(DONNEES!$H$2:$H$1501,"NOTABLE",DONNEES!$L$2:$L$1501,"Pas d’info à tort",DONNEES!$G$2:$G$1501,$A7) -> 10 | E7: =COUNTIFS(DONNEES!$H$2:$H$1501,"NOTABLE",DONNEES!$L$2:$L$1501,"Incorrect",DONNEES!$G$2:$G$1501,$A7) -> 0 | F7: =COUNTIFS(DONNEES!$H$2:$H$1501,"NOTABLE",DONNEES!$L$2:$L$1501,"Hors sujet",DONNEES!$G$2:$G$1501,$A7) -> 1 | G7: =IF($B7=0,"",C7/$B7) -> 0.21428571 | H7: =IF($B7=0,"",D7/$B7) -> 0.71428571 | I7: =IF($B7=0,"",E7/$B7) -> 0 | J7: =IF($B7=0,"",F7/$B7) -> 0.071428571 | K7: =IFERROR(AVERAGEIFS(DONNEES!$O$2:$O$1501,DONNEES!$G$2:$G$1501,$A7),"") -> 14.000714
A8: Implicit Transaction costs ex-post (EMT) | B8: =COUNTIFS(DONNEES!$H$2:$H$1501,"NOTABLE",DONNEES!$L$2:$L$1501,"Correct",DONNEES!$G$2:$G$1501,$A8)+COUNTIFS(DONNEES!$H$2:$H$1501,"NOTABLE",DONNEES!$L$2:$L$1501,"Pas d’info à tort",DONNEES!$G$2:$G$1501,$A8)+COUNTIFS(DONNEES!$H$2:$H$1501,"NOTABLE",DONNEES!$L$2:$L$1501,"Incorrect",DONNEES!$G$2:$G$1501,$A8)+COUNTIFS(DONNEES!$H$2:$H$1501,"NOTABLE",DONNEES!$L$2:$L$1501,"Hors sujet",DONNEES!$G$2:$G$1501,$A8) -> 15 | C8: =COUNTIFS(DONNEES!$H$2:$H$1501,"NOTABLE",DONNEES!$L$2:$L$1501,"Correct",DONNEES!$G$2:$G$1501,$A8) -> 4 | D8: =COUNTIFS(DONNEES!$H$2:$H$1501,"NOTABLE",DONNEES!$L$2:$L$1501,"Pas d’info à tort",DONNEES!$G$2:$G$1501,$A8) -> 2 | E8: =COUNTIFS(DONNEES!$H$2:$H$1501,"NOTABLE",DONNEES!$L$2:$L$1501,"Incorrect",DONNEES!$G$2:$G$1501,$A8) -> 9 | F8: =COUNTIFS(DONNEES!$H$2:$H$1501,"NOTABLE",DONNEES!$L$2:$L$1501,"Hors sujet",DONNEES!$G$2:$G$1501,$A8) -> 0 | G8: =IF($B8=0,"",C8/$B8) -> 0.26666667 | H8: =IF($B8=0,"",D8/$B8) -> 0.13333333 | I8: =IF($B8=0,"",E8/$B8) -> 0.6 | J8: =IF($B8=0,"",F8/$B8) -> 0 | K8: =IFERROR(AVERAGEIFS(DONNEES!$O$2:$O$1501,DONNEES!$G$2:$G$1501,$A8),"") -> 25.740625
A9: Official Risk Scale | B9: =COUNTIFS(DONNEES!$H$2:$H$1501,"NOTABLE",DONNEES!$L$2:$L$1501,"Correct",DONNEES!$G$2:$G$1501,$A9)+COUNTIFS(DONNEES!$H$2:$H$1501,"NOTABLE",DONNEES!$L$2:$L$1501,"Pas d’info à tort",DONNEES!$G$2:$G$1501,$A9)+COUNTIFS(DONNEES!$H$2:$H$1501,"NOTABLE",DONNEES!$L$2:$L$1501,"Incorrect",DONNEES!$G$2:$G$1501,$A9)+COUNTIFS(DONNEES!$H$2:$H$1501,"NOTABLE",DONNEES!$L$2:$L$1501,"Hors sujet",DONNEES!$G$2:$G$1501,$A9) -> 37 | C9: =COUNTIFS(DONNEES!$H$2:$H$1501,"NOTABLE",DONNEES!$L$2:$L$1501,"Correct",DONNEES!$G$2:$G$1501,$A9) -> 10 | D9: =COUNTIFS(DONNEES!$H$2:$H$1501,"NOTABLE",DONNEES!$L$2:$L$1501,"Pas d’info à tort",DONNEES!$G$2:$G$1501,$A9) -> 27 | E9: =COUNTIFS(DONNEES!$H$2:$H$1501,"NOTABLE",DONNEES!$L$2:$L$1501,"Incorrect",DONNEES!$G$2:$G$1501,$A9) -> 0 | F9: =COUNTIFS(DONNEES!$H$2:$H$1501,"NOTABLE",DONNEES!$L$2:$L$1501,"Hors sujet",DONNEES!$G$2:$G$1501,$A9) -> 0 | G9: =IF($B9=0,"",C9/$B9) -> 0.27027027 | H9: =IF($B9=0,"",D9/$B9) -> 0.72972973 | I9: =IF($B9=0,"",E9/$B9) -> 0 | J9: =IF($B9=0,"",F9/$B9) -> 0 | K9: =IFERROR(AVERAGEIFS(DONNEES!$O$2:$O$1501,DONNEES!$G$2:$G$1501,$A9),"") -> 21.380811
A10: Benchmark | B10: =COUNTIFS(DONNEES!$H$2:$H$1501,"NOTABLE",DONNEES!$L$2:$L$1501,"Correct",DONNEES!$G$2:$G$1501,$A10)+COUNTIFS(DONNEES!$H$2:$H$1501,"NOTABLE",DONNEES!$L$2:$L$1501,"Pas d’info à tort",DONNEES!$G$2:$G$1501,$A10)+COUNTIFS(DONNEES!$H$2:$H$1501,"NOTABLE",DONNEES!$L$2:$L$1501,"Incorrect",DONNEES!$G$2:$G$1501,$A10)+COUNTIFS(DONNEES!$H$2:$H$1501,"NOTABLE",DONNEES!$L$2:$L$1501,"Hors sujet",DONNEES!$G$2:$G$1501,$A10) -> 15 | C10: =COUNTIFS(DONNEES!$H$2:$H$1501,"NOTABLE",DONNEES!$L$2:$L$1501,"Correct",DONNEES!$G$2:$G$1501,$A10) -> 5 | D10: =COUNTIFS(DONNEES!$H$2:$H$1501,"NOTABLE",DONNEES!$L$2:$L$1501,"Pas d’info à tort",DONNEES!$G$2:$G$1501,$A10) -> 9 | E10: =COUNTIFS(DONNEES!$H$2:$H$1501,"NOTABLE",DONNEES!$L$2:$L$1501,"Incorrect",DONNEES!$G$2:$G$1501,$A10) -> 0 | F10: =COUNTIFS(DONNEES!$H$2:$H$1501,"NOTABLE",DONNEES!$L$2:$L$1501,"Hors sujet",DONNEES!$G$2:$G$1501,$A10) -> 1 | G10: =IF($B10=0,"",C10/$B10) -> 0.33333333 | H10: =IF($B10=0,"",D10/$B10) -> 0.6 | I10: =IF($B10=0,"",E10/$B10) -> 0 | J10: =IF($B10=0,"",F10/$B10) -> 0.066666667 | K10: =IFERROR(AVERAGEIFS(DONNEES!$O$2:$O$1501,DONNEES!$G$2:$G$1501,$A10),"") -> 15.351333
A11: ESG Existing Thematic (EET 20260) | B11: =COUNTIFS(DONNEES!$H$2:$H$1501,"NOTABLE",DONNEES!$L$2:$L$1501,"Correct",DONNEES!$G$2:$G$1501,$A11)+COUNTIFS(DONNEES!$H$2:$H$1501,"NOTABLE",DONNEES!$L$2:$L$1501,"Pas d’info à tort",DONNEES!$G$2:$G$1501,$A11)+COUNTIFS(DONNEES!$H$2:$H$1501,"NOTABLE",DONNEES!$L$2:$L$1501,"Incorrect",DONNEES!$G$2:$G$1501,$A11)+COUNTIFS(DONNEES!$H$2:$H$1501,"NOTABLE",DONNEES!$L$2:$L$1501,"Hors sujet",DONNEES!$G$2:$G$1501,$A11) -> 14 | C11: =COUNTIFS(DONNEES!$H$2:$H$1501,"NOTABLE",DONNEES!$L$2:$L$1501,"Correct",DONNEES!$G$2:$G$1501,$A11) -> 5 | D11: =COUNTIFS(DONNEES!$H$2:$H$1501,"NOTABLE",DONNEES!$L$2:$L$1501,"Pas d’info à tort",DONNEES!$G$2:$G$1501,$A11) -> 7 | E11: =COUNTIFS(DONNEES!$H$2:$H$1501,"NOTABLE",DONNEES!$L$2:$L$1501,"Incorrect",DONNEES!$G$2:$G$1501,$A11) -> 2 | F11: =COUNTIFS(DONNEES!$H$2:$H$1501,"NOTABLE",DONNEES!$L$2:$L$1501,"Hors sujet",DONNEES!$G$2:$G$1501,$A11) -> 0 | G11: =IF($B11=0,"",C11/$B11) -> 0.35714286 | H11: =IF($B11=0,"",D11/$B11) -> 0.5 | I11: =IF($B11=0,"",E11/$B11) -> 0.14285714 | J11: =IF($B11=0,"",F11/$B11) -> 0 | K11: =IFERROR(AVERAGEIFS(DONNEES!$O$2:$O$1501,DONNEES!$G$2:$G$1501,$A11),"") -> 25.420714
A12: Fund Sub-regulation application | B12: =COUNTIFS(DONNEES!$H$2:$H$1501,"NOTABLE",DONNEES!$L$2:$L$1501,"Correct",DONNEES!$G$2:$G$1501,$A12)+COUNTIFS(DONNEES!$H$2:$H$1501,"NOTABLE",DONNEES!$L$2:$L$1501,"Pas d’info à tort",DONNEES!$G$2:$G$1501,$A12)+COUNTIFS(DONNEES!$H$2:$H$1501,"NOTABLE",DONNEES!$L$2:$L$1501,"Incorrect",DONNEES!$G$2:$G$1501,$A12)+COUNTIFS(DONNEES!$H$2:$H$1501,"NOTABLE",DONNEES!$L$2:$L$1501,"Hors sujet",DONNEES!$G$2:$G$1501,$A12) -> 10 | C12: =COUNTIFS(DONNEES!$H$2:$H$1501,"NOTABLE",DONNEES!$L$2:$L$1501,"Correct",DONNEES!$G$2:$G$1501,$A12) -> 4 | D12: =COUNTIFS(DONNEES!$H$2:$H$1501,"NOTABLE",DONNEES!$L$2:$L$1501,"Pas d’info à tort",DONNEES!$G$2:$G$1501,$A12) -> 3 | E12: =COUNTIFS(DONNEES!$H$2:$H$1501,"NOTABLE",DONNEES!$L$2:$L$1501,"Incorrect",DONNEES!$G$2:$G$1501,$A12) -> 3 | F12: =COUNTIFS(DONNEES!$H$2:$H$1501,"NOTABLE",DONNEES!$L$2:$L$1501,"Hors sujet",DONNEES!$G$2:$G$1501,$A12) -> 0 | G12: =IF($B12=0,"",C12/$B12) -> 0.4 | H12: =IF($B12=0,"",D12/$B12) -> 0.3 | I12: =IF($B12=0,"",E12/$B12) -> 0.3 | J12: =IF($B12=0,"",F12/$B12) -> 0 | K12: =IFERROR(AVERAGEIFS(DONNEES!$O$2:$O$1501,DONNEES!$G$2:$G$1501,$A12),"") -> 15.499
A13: Transfer Agent | B13: =COUNTIFS(DONNEES!$H$2:$H$1501,"NOTABLE",DONNEES!$L$2:$L$1501,"Correct",DONNEES!$G$2:$G$1501,$A13)+COUNTIFS(DONNEES!$H$2:$H$1501,"NOTABLE",DONNEES!$L$2:$L$1501,"Pas d’info à tort",DONNEES!$G$2:$G$1501,$A13)+COUNTIFS(DONNEES!$H$2:$H$1501,"NOTABLE",DONNEES!$L$2:$L$1501,"Incorrect",DONNEES!$G$2:$G$1501,$A13)+COUNTIFS(DONNEES!$H$2:$H$1501,"NOTABLE",DONNEES!$L$2:$L$1501,"Hors sujet",DONNEES!$G$2:$G$1501,$A13) -> 9 | C13: =COUNTIFS(DONNEES!$H$2:$H$1501,"NOTABLE",DONNEES!$L$2:$L$1501,"Correct",DONNEES!$G$2:$G$1501,$A13) -> 5 | D13: =COUNTIFS(DONNEES!$H$2:$H$1501,"NOTABLE",DONNEES!$L$2:$L$1501,"Pas d’info à tort",DONNEES!$G$2:$G$1501,$A13) -> 1 | E13: =COUNTIFS(DONNEES!$H$2:$H$1501,"NOTABLE",DONNEES!$L$2:$L$1501,"Incorrect",DONNEES!$G$2:$G$1501,$A13) -> 3 | F13: =COUNTIFS(DONNEES!$H$2:$H$1501,"NOTABLE",DONNEES!$L$2:$L$1501,"Hors sujet",DONNEES!$G$2:$G$1501,$A13) -> 0 | G13: =IF($B13=0,"",C13/$B13) -> 0.55555556 | H13: =IF($B13=0,"",D13/$B13) -> 0.11111111 | I13: =IF($B13=0,"",E13/$B13) -> 0.33333333 | J13: =IF($B13=0,"",F13/$B13) -> 0 | K13: =IFERROR(AVERAGEIFS(DONNEES!$O$2:$O$1501,DONNEES!$G$2:$G$1501,$A13),"") -> 25.498
A14: % Min SI Env. (EET 20440) | B14: =COUNTIFS(DONNEES!$H$2:$H$1501,"NOTABLE",DONNEES!$L$2:$L$1501,"Correct",DONNEES!$G$2:$G$1501,$A14)+COUNTIFS(DONNEES!$H$2:$H$1501,"NOTABLE",DONNEES!$L$2:$L$1501,"Pas d’info à tort",DONNEES!$G$2:$G$1501,$A14)+COUNTIFS(DONNEES!$H$2:$H$1501,"NOTABLE",DONNEES!$L$2:$L$1501,"Incorrect",DONNEES!$G$2:$G$1501,$A14)+COUNTIFS(DONNEES!$H$2:$H$1501,"NOTABLE",DONNEES!$L$2:$L$1501,"Hors sujet",DONNEES!$G$2:$G$1501,$A14) -> 14 | C14: =COUNTIFS(DONNEES!$H$2:$H$1501,"NOTABLE",DONNEES!$L$2:$L$1501,"Correct",DONNEES!$G$2:$G$1501,$A14) -> 8 | D14: =COUNTIFS(DONNEES!$H$2:$H$1501,"NOTABLE",DONNEES!$L$2:$L$1501,"Pas d’info à tort",DONNEES!$G$2:$G$1501,$A14) -> 0 | E14: =COUNTIFS(DONNEES!$H$2:$H$1501,"NOTABLE",DONNEES!$L$2:$L$1501,"Incorrect",DONNEES!$G$2:$G$1501,$A14) -> 5 | F14: =COUNTIFS(DONNEES!$H$2:$H$1501,"NOTABLE",DONNEES!$L$2:$L$1501,"Hors sujet",DONNEES!$G$2:$G$1501,$A14) -> 1 | G14: =IF($B14=0,"",C14/$B14) -> 0.57142857 | H14: =IF($B14=0,"",D14/$B14) -> 0 | I14: =IF($B14=0,"",E14/$B14) -> 0.35714286 | J14: =IF($B14=0,"",F14/$B14) -> 0.071428571 | K14: =IFERROR(AVERAGEIFS(DONNEES!$O$2:$O$1501,DONNEES!$G$2:$G$1501,$A14),"") -> 14.965
A15: Priips Fund | B15: =COUNTIFS(DONNEES!$H$2:$H$1501,"NOTABLE",DONNEES!$L$2:$L$1501,"Correct",DONNEES!$G$2:$G$1501,$A15)+COUNTIFS(DONNEES!$H$2:$H$1501,"NOTABLE",DONNEES!$L$2:$L$1501,"Pas d’info à tort",DONNEES!$G$2:$G$1501,$A15)+COUNTIFS(DONNEES!$H$2:$H$1501,"NOTABLE",DONNEES!$L$2:$L$1501,"Incorrect",DONNEES!$G$2:$G$1501,$A15)+COUNTIFS(DONNEES!$H$2:$H$1501,"NOTABLE",DONNEES!$L$2:$L$1501,"Hors sujet",DONNEES!$G$2:$G$1501,$A15) -> 10 | C15: =COUNTIFS(DONNEES!$H$2:$H$1501,"NOTABLE",DONNEES!$L$2:$L$1501,"Correct",DONNEES!$G$2:$G$1501,$A15) -> 6 | D15: =COUNTIFS(DONNEES!$H$2:$H$1501,"NOTABLE",DONNEES!$L$2:$L$1501,"Pas d’info à tort",DONNEES!$G$2:$G$1501,$A15) -> 1 | E15: =COUNTIFS(DONNEES!$H$2:$H$1501,"NOTABLE",DONNEES!$L$2:$L$1501,"Incorrect",DONNEES!$G$2:$G$1501,$A15) -> 2 | F15: =COUNTIFS(DONNEES!$H$2:$H$1501,"NOTABLE",DONNEES!$L$2:$L$1501,"Hors sujet",DONNEES!$G$2:$G$1501,$A15) -> 1 | G15: =IF($B15=0,"",C15/$B15) -> 0.6 | H15: =IF($B15=0,"",D15/$B15) -> 0.1 | I15: =IF($B15=0,"",E15/$B15) -> 0.2 | J15: =IF($B15=0,"",F15/$B15) -> 0.1 | K15: =IFERROR(AVERAGEIFS(DONNEES!$O$2:$O$1501,DONNEES!$G$2:$G$1501,$A15),"") -> 11.929
A16: Year of implicit trans. costs ex ante/3Y mean | B16: =COUNTIFS(DONNEES!$H$2:$H$1501,"NOTABLE",DONNEES!$L$2:$L$1501,"Correct",DONNEES!$G$2:$G$1501,$A16)+COUNTIFS(DONNEES!$H$2:$H$1501,"NOTABLE",DONNEES!$L$2:$L$1501,"Pas d’info à tort",DONNEES!$G$2:$G$1501,$A16)+COUNTIFS(DONNEES!$H$2:$H$1501,"NOTABLE",DONNEES!$L$2:$L$1501,"Incorrect",DONNEES!$G$2:$G$1501,$A16)+COUNTIFS(DONNEES!$H$2:$H$1501,"NOTABLE",DONNEES!$L$2:$L$1501,"Hors sujet",DONNEES!$G$2:$G$1501,$A16) -> 5 | C16: =COUNTIFS(DONNEES!$H$2:$H$1501,"NOTABLE",DONNEES!$L$2:$L$1501,"Correct",DONNEES!$G$2:$G$1501,$A16) -> 3 | D16: =COUNTIFS(DONNEES!$H$2:$H$1501,"NOTABLE",DONNEES!$L$2:$L$1501,"Pas d’info à tort",DONNEES!$G$2:$G$1501,$A16) -> 1 | E16: =COUNTIFS(DONNEES!$H$2:$H$1501,"NOTABLE",DONNEES!$L$2:$L$1501,"Incorrect",DONNEES!$G$2:$G$1501,$A16) -> 1 | F16: =COUNTIFS(DONNEES!$H$2:$H$1501,"NOTABLE",DONNEES!$L$2:$L$1501,"Hors sujet",DONNEES!$G$2:$G$1501,$A16) -> 0 | G16: =IF($B16=0,"",C16/$B16) -> 0.6 | H16: =IF($B16=0,"",D16/$B16) -> 0.2 | I16: =IF($B16=0,"",E16/$B16) -> 0.2 | J16: =IF($B16=0,"",F16/$B16) -> 0 | K16: =IFERROR(AVERAGEIFS(DONNEES!$O$2:$O$1501,DONNEES!$G$2:$G$1501,$A16),"") -> 14.32
... A106: Performance fees | B106: =COUNTIFS(DONNEES!$H$2:$H$1501,"NOTABLE",DONNEES!$L$2:$L$1501,"Correct",DONNEES!$G$2:$G$1501,$A106)+COUNTIFS(DONNEES!$H$2:$H$1501,"NOTABLE",DONNEES!$L$2:$L$1501,"Pas d’info à tort",DONNEES!$G$2:$G$1501,$A106)+COUNTIFS(DONNEES!$H$2:$H$1501,"NOTABLE",DONNEES!$L$2:$L$1501,"Incorrect",DONNEES!$G$2:$G$1501,$A106)+COUNTIFS(DONNEES!$H$2:$H$1501,"NOTABLE",DONNEES!$L$2:$L$1501,"Hors sujet",DONNEES!$G$2:$G$1501,$A106) -> 0 | C106: =COUNTIFS(DONNEES!$H$2:$H$1501,"NOTABLE",DONNEES!$L$2:$L$1501,"Correct",DONNEES!$G$2:$G$1501,$A106) -> 0 | D106: =COUNTIFS(DONNEES!$H$2:$H$1501,"NOTABLE",DONNEES!$L$2:$L$1501,"Pas d’info à tort",DONNEES!$G$2:$G$1501,$A106) -> 0 | E106: =COUNTIFS(DONNEES!$H$2:$H$1501,"NOTABLE",DONNEES!$L$2:$L$1501,"Incorrect",DONNEES!$G$2:$G$1501,$A106) -> 0 | F106: =COUNTIFS(DONNEES!$H$2:$H$1501,"NOTABLE",DONNEES!$L$2:$L$1501,"Hors sujet",DONNEES!$G$2:$G$1501,$A106) -> 0 | G106: =IF($B106=0,"",C106/$B106) | H106: =IF($B106=0,"",D106/$B106) | I106: =IF($B106=0,"",E106/$B106) | J106: =IF($B106=0,"",F106/$B106) | K106: =IFERROR(AVERAGEIFS(DONNEES!$O$2:$O$1501,DONNEES!$G$2:$G$1501,$A106),"") -> 16.816667

Sheet PAR_FONDS
A1: Résultats par fonds
A2: Fonds interrogés sur au moins 5 questions à valeur connue, du plus faible au plus fort.
A4: Fonds | B4: Notées | C4: Correct | D4: « Aucune info » à tort | E4: Valeur fausse | F4: Hors sujet | G4: % correct | H4: % aucune info | I4: % faux | J4: % hors sujet | K4: Latence moy. (s)
A5: R-co Funds Managers | B5: =COUNTIFS(DONNEES!$H$2:$H$1501,"NOTABLE",DONNEES!$L$2:$L$1501,"Correct",DONNEES!$F$2:$F$1501,$A5)+COUNTIFS(DONNEES!$H$2:$H$1501,"NOTABLE",DONNEES!$L$2:$L$1501,"Pas d’info à tort",DONNEES!$F$2:$F$1501,$A5)+COUNTIFS(DONNEES!$H$2:$H$1501,"NOTABLE",DONNEES!$L$2:$L$1501,"Incorrect",DONNEES!$F$2:$F$1501,$A5)+COUNTIFS(DONNEES!$H$2:$H$1501,"NOTABLE",DONNEES!$L$2:$L$1501,"Hors sujet",DONNEES!$F$2:$F$1501,$A5) -> 5 | C5: =COUNTIFS(DONNEES!$H$2:$H$1501,"NOTABLE",DONNEES!$L$2:$L$1501,"Correct",DONNEES!$F$2:$F$1501,$A5) -> 0 | D5: =COUNTIFS(DONNEES!$H$2:$H$1501,"NOTABLE",DONNEES!$L$2:$L$1501,"Pas d’info à tort",DONNEES!$F$2:$F$1501,$A5) -> 5 | E5: =COUNTIFS(DONNEES!$H$2:$H$1501,"NOTABLE",DONNEES!$L$2:$L$1501,"Incorrect",DONNEES!$F$2:$F$1501,$A5) -> 0 | F5: =COUNTIFS(DONNEES!$H$2:$H$1501,"NOTABLE",DONNEES!$L$2:$L$1501,"Hors sujet",DONNEES!$F$2:$F$1501,$A5) -> 0 | G5: =IF($B5=0,"",C5/$B5) -> 0 | H5: =IF($B5=0,"",D5/$B5) -> 1 | I5: =IF($B5=0,"",E5/$B5) -> 0 | J5: =IF($B5=0,"",F5/$B5) -> 0 | K5: =IFERROR(AVERAGEIFS(DONNEES!$O$2:$O$1501,DONNEES!$F$2:$F$1501,$A5),"") -> 14.812
A6: Liancourt AM | B6: =COUNTIFS(DONNEES!$H$2:$H$1501,"NOTABLE",DONNEES!$L$2:$L$1501,"Correct",DONNEES!$F$2:$F$1501,$A6)+COUNTIFS(DONNEES!$H$2:$H$1501,"NOTABLE",DONNEES!$L$2:$L$1501,"Pas d’info à tort",DONNEES!$F$2:$F$1501,$A6)+COUNTIFS(DONNEES!$H$2:$H$1501,"NOTABLE",DONNEES!$L$2:$L$1501,"Incorrect",DONNEES!$F$2:$F$1501,$A6)+COUNTIFS(DONNEES!$H$2:$H$1501,"NOTABLE",DONNEES!$L$2:$L$1501,"Hors sujet",DONNEES!$F$2:$F$1501,$A6) -> 6 | C6: =COUNTIFS(DONNEES!$H$2:$H$1501,"NOTABLE",DONNEES!$L$2:$L$1501,"Correct",DONNEES!$F$2:$F$1501,$A6) -> 1 | D6: =COUNTIFS(DONNEES!$H$2:$H$1501,"NOTABLE",DONNEES!$L$2:$L$1501,"Pas d’info à tort",DONNEES!$F$2:$F$1501,$A6) -> 5 | E6: =COUNTIFS(DONNEES!$H$2:$H$1501,"NOTABLE",DONNEES!$L$2:$L$1501,"Incorrect",DONNEES!$F$2:$F$1501,$A6) -> 0 | F6: =COUNTIFS(DONNEES!$H$2:$H$1501,"NOTABLE",DONNEES!$L$2:$L$1501,"Hors sujet",DONNEES!$F$2:$F$1501,$A6) -> 0 | G6: =IF($B6=0,"",C6/$B6) -> 0.16666667 | H6: =IF($B6=0,"",D6/$B6) -> 0.83333333 | I6: =IF($B6=0,"",E6/$B6) -> 0 | J6: =IF($B6=0,"",F6/$B6) -> 0 | K6: =IFERROR(AVERAGEIFS(DONNEES!$O$2:$O$1501,DONNEES!$F$2:$F$1501,$A6),"") -> 15.925714
A7: RMM Invest 8 Europe | B7: =COUNTIFS(DONNEES!$H$2:$H$1501,"NOTABLE",DONNEES!$L$2:$L$1501,"Correct",DONNEES!$F$2:$F$1501,$A7)+COUNTIFS(DONNEES!$H$2:$H$1501,"NOTABLE",DONNEES!$L$2:$L$1501,"Pas d’info à tort",DONNEES!$F$2:$F$1501,$A7)+COUNTIFS(DONNEES!$H$2:$H$1501,"NOTABLE",DONNEES!$L$2:$L$1501,"Incorrect",DONNEES!$F$2:$F$1501,$A7)+COUNTIFS(DONNEES!$H$2:$H$1501,"NOTABLE",DONNEES!$L$2:$L$1501,"Hors sujet",DONNEES!$F$2:$F$1501,$A7) -> 6 | C7: =COUNTIFS(DONNEES!$H$2:$H$1501,"NOTABLE",DONNEES!$L$2:$L$1501,"Correct",DONNEES!$F$2:$F$1501,$A7) -> 1 | D7: =COUNTIFS(DONNEES!$H$2:$H$1501,"NOTABLE",DONNEES!$L$2:$L$1501,"Pas d’info à tort",DONNEES!$F$2:$F$1501,$A7) -> 5 | E7: =COUNTIFS(DONNEES!$H$2:$H$1501,"NOTABLE",DONNEES!$L$2:$L$1501,"Incorrect",DONNEES!$F$2:$F$1501,$A7) -> 0 | F7: =COUNTIFS(DONNEES!$H$2:$H$1501,"NOTABLE",DONNEES!$L$2:$L$1501,"Hors sujet",DONNEES!$F$2:$F$1501,$A7) -> 0 | G7: =IF($B7=0,"",C7/$B7) -> 0.16666667 | H7: =IF($B7=0,"",D7/$B7) -> 0.83333333 | I7: =IF($B7=0,"",E7/$B7) -> 0 | J7: =IF($B7=0,"",F7/$B7) -> 0 | K7: =IFERROR(AVERAGEIFS(DONNEES!$O$2:$O$1501,DONNEES!$F$2:$F$1501,$A7),"") -> 14.288571
A8: R-co OPAL 4Change Global Trends | B8: =COUNTIFS(DONNEES!$H$2:$H$1501,"NOTABLE",DONNEES!$L$2:$L$1501,"Correct",DONNEES!$F$2:$F$1501,$A8)+COUNTIFS(DONNEES!$H$2:$H$1501,"NOTABLE",DONNEES!$L$2:$L$1501,"Pas d’info à tort",DONNEES!$F$2:$F$1501,$A8)+COUNTIFS(DONNEES!$H$2:$H$1501,"NOTABLE",DONNEES!$L$2:$L$1501,"Incorrect",DONNEES!$F$2:$F$1501,$A8)+COUNTIFS(DONNEES!$H$2:$H$1501,"NOTABLE",DONNEES!$L$2:$L$1501,"Hors sujet",DONNEES!$F$2:$F$1501,$A8) -> 5 | C8: =COUNTIFS(DONNEES!$H$2:$H$1501,"NOTABLE",DONNEES!$L$2:$L$1501,"Correct",DONNEES!$F$2:$F$1501,$A8) -> 1 | D8: =COUNTIFS(DONNEES!$H$2:$H$1501,"NOTABLE",DONNEES!$L$2:$L$1501,"Pas d’info à tort",DONNEES!$F$2:$F$1501,$A8) -> 3 | E8: =COUNTIFS(DONNEES!$H$2:$H$1501,"NOTABLE",DONNEES!$L$2:$L$1501,"Incorrect",DONNEES!$F$2:$F$1501,$A8) -> 1 | F8: =COUNTIFS(DONNEES!$H$2:$H$1501,"NOTABLE",DONNEES!$L$2:$L$1501,"Hors sujet",DONNEES!$F$2:$F$1501,$A8) -> 0 | G8: =IF($B8=0,"",C8/$B8) -> 0.2 | H8: =IF($B8=0,"",D8/$B8) -> 0.6 | I8: =IF($B8=0,"",E8/$B8) -> 0.2 | J8: =IF($B8=0,"",F8/$B8) -> 0 | K8: =IFERROR(AVERAGEIFS(DONNEES!$O$2:$O$1501,DONNEES!$F$2:$F$1501,$A8),"") -> 11.474
A9: Hamelin Multigestion Monde I | B9: =COUNTIFS(DONNEES!$H$2:$H$1501,"NOTABLE",DONNEES!$L$2:$L$1501,"Correct",DONNEES!$F$2:$F$1501,$A9)+COUNTIFS(DONNEES!$H$2:$H$1501,"NOTABLE",DONNEES!$L$2:$L$1501,"Pas d’info à tort",DONNEES!$F$2:$F$1501,$A9)+COUNTIFS(DONNEES!$H$2:$H$1501,"NOTABLE",DONNEES!$L$2:$L$1501,"Incorrect",DONNEES!$F$2:$F$1501,$A9)+COUNTIFS(DONNEES!$H$2:$H$1501,"NOTABLE",DONNEES!$L$2:$L$1501,"Hors sujet",DONNEES!$F$2:$F$1501,$A9) -> 6 | C9: =COUNTIFS(DONNEES!$H$2:$H$1501,"NOTABLE",DONNEES!$L$2:$L$1501,"Correct",DONNEES!$F$2:$F$1501,$A9) -> 2 | D9: =COUNTIFS(DONNEES!$H$2:$H$1501,"NOTABLE",DONNEES!$L$2:$L$1501,"Pas d’info à tort",DONNEES!$F$2:$F$1501,$A9) -> 4 | E9: =COUNTIFS(DONNEES!$H$2:$H$1501,"NOTABLE",DONNEES!$L$2:$L$1501,"Incorrect",DONNEES!$F$2:$F$1501,$A9) -> 0 | F9: =COUNTIFS(DONNEES!$H$2:$H$1501,"NOTABLE",DONNEES!$L$2:$L$1501,"Hors sujet",DONNEES!$F$2:$F$1501,$A9) -> 0 | G9: =IF($B9=0,"",C9/$B9) -> 0.33333333 | H9: =IF($B9=0,"",D9/$B9) -> 0.66666667 | I9: =IF($B9=0,"",E9/$B9) -> 0 | J9: =IF($B9=0,"",F9/$B9) -> 0 | K9: =IFERROR(AVERAGEIFS(DONNEES!$O$2:$O$1501,DONNEES!$F$2:$F$1501,$A9),"") -> 18.474286
A10: R-co Core Equity Europe | B10: =COUNTIFS(DONNEES!$H$2:$H$1501,"NOTABLE",DONNEES!$L$2:$L$1501,"Correct",DONNEES!$F$2:$F$1501,$A10)+COUNTIFS(DONNEES!$H$2:$H$1501,"NOTABLE",DONNEES!$L$2:$L$1501,"Pas d’info à tort",DONNEES!$F$2:$F$1501,$A10)+COUNTIFS(DONNEES!$H$2:$H$1501,"NOTABLE",DONNEES!$L$2:$L$1501,"Incorrect",DONNEES!$F$2:$F$1501,$A10)+COUNTIFS(DONNEES!$H$2:$H$1501,"NOTABLE",DONNEES!$L$2:$L$1501,"Hors sujet",DONNEES!$F$2:$F$1501,$A10) -> 26 | C10: =COUNTIFS(DONNEES!$H$2:$H$1501,"NOTABLE",DONNEES!$L$2:$L$1501,"Correct",DONNEES!$F$2:$F$1501,$A10) -> 10 | D10: =COUNTIFS(DONNEES!$H$2:$H$1501,"NOTABLE",DONNEES!$L$2:$L$1501,"Pas d’info à tort",DONNEES!$F$2:$F$1501,$A10) -> 4 | E10: =COUNTIFS(DONNEES!$H$2:$H$1501,"NOTABLE",DONNEES!$L$2:$L$1501,"Incorrect",DONNEES!$F$2:$F$1501,$A10) -> 12 | F10: =COUNTIFS(DONNEES!$H$2:$H$1501,"NOTABLE",DONNEES!$L$2:$L$1501,"Hors sujet",DONNEES!$F$2:$F$1501,$A10) -> 0 | G10: =IF($B10=0,"",C10/$B10) -> 0.38461538 | H10: =IF($B10=0,"",D10/$B10) -> 0.15384615 | I10: =IF($B10=0,"",E10/$B10) -> 0.46153846 | J10: =IF($B10=0,"",F10/$B10) -> 0 | K10: =IFERROR(AVERAGEIFS(DONNEES!$O$2:$O$1501,DONNEES!$F$2:$F$1501,$A10),"") -> 21.841111
A11: Alfred Investment | B11: =COUNTIFS(DONNEES!$H$2:$H$1501,"NOTABLE",DONNEES!$L$2:$L$1501,"Correct",DONNEES!$F$2:$F$1501,$A11)+COUNTIFS(DONNEES!$H$2:$H$1501,"NOTABLE",DONNEES!$L$2:$L$1501,"Pas d’info à tort",DONNEES!$F$2:$F$1501,$A11)+COUNTIFS(DONNEES!$H$2:$H$1501,"NOTABLE",DONNEES!$L$2:$L$1501,"Incorrect",DONNEES!$F$2:$F$1501,$A11)+COUNTIFS(DONNEES!$H$2:$H$1501,"NOTABLE",DONNEES!$L$2:$L$1501,"Hors sujet",DONNEES!$F$2:$F$1501,$A11) -> 5 | C11: =COUNTIFS(DONNEES!$H$2:$H$1501,"NOTABLE",DONNEES!$L$2:$L$1501,"Correct",DONNEES!$F$2:$F$1501,$A11) -> 2 | D11: =COUNTIFS(DONNEES!$H$2:$H$1501,"NOTABLE",DONNEES!$L$2:$L$1501,"Pas d’info à tort",DONNEES!$F$2:$F$1501,$A11) -> 2 | E11: =COUNTIFS(DONNEES!$H$2:$H$1501,"NOTABLE",DONNEES!$L$2:$L$1501,"Incorrect",DONNEES!$F$2:$F$1501,$A11) -> 0 | F11: =COUNTIFS(DONNEES!$H$2:$H$1501,"NOTABLE",DONNEES!$L$2:$L$1501,"Hors sujet",DONNEES!$F$2:$F$1501,$A11) -> 1 | G11: =IF($B11=0,"",C11/$B11) -> 0.4 | H11: =IF($B11=0,"",D11/$B11) -> 0.4 | I11: =IF($B11=0,"",E11/$B11) -> 0 | J11: =IF($B11=0,"",F11/$B11) -> 0.2 | K11: =IFERROR(AVERAGEIFS(DONNEES!$O$2:$O$1501,DONNEES!$F$2:$F$1501,$A11),"") -> 17.506
A12: Fourcats Investment | B12: =COUNTIFS(DONNEES!$H$2:$H$1501,"NOTABLE",DONNEES!$L$2:$L$1501,"Correct",DONNEES!$F$2:$F$1501,$A12)+COUNTIFS(DONNEES!$H$2:$H$1501,"NOTABLE",DONNEES!$L$2:$L$1501,"Pas d’info à tort",DONNEES!$F$2:$F$1501,$A12)+COUNTIFS(DONNEES!$H$2:$H$1501,"NOTABLE",DONNEES!$L$2:$L$1501,"Incorrect",DONNEES!$F$2:$F$1501,$A12)+COUNTIFS(DONNEES!$H$2:$H$1501,"NOTABLE",DONNEES!$L$2:$L$1501,"Hors sujet",DONNEES!$F$2:$F$1501,$A12) -> 5 | C12: =COUNTIFS(DONNEES!$H$2:$H$1501,"NOTABLE",DONNEES!$L$2:$L$1501,"Correct",DONNEES!$F$2:$F$1501,$A12) -> 2 | D12: =COUNTIFS(DONNEES!$H$2:$H$1501,"NOTABLE",DONNEES!$L$2:$L$1501,"Pas d’info à tort",DONNEES!$F$2:$F$1501,$A12) -> 3 | E12: =COUNTIFS(DONNEES!$H$2:$H$1501,"NOTABLE",DONNEES!$L$2:$L$1501,"Incorrect",DONNEES!$F$2:$F$1501,$A12) -> 0 | F12: =COUNTIFS(DONNEES!$H$2:$H$1501,"NOTABLE",DONNEES!$L$2:$L$1501,"Hors sujet",DONNEES!$F$2:$F$1501,$A12) -> 0 | G12: =IF($B12=0,"",C12/$B12) -> 0.4 | H12: =IF($B12=0,"",D12/$B12) -> 0.6 | I12: =IF($B12=0,"",E12/$B12) -> 0 | J12: =IF($B12=0,"",F12/$B12) -> 0 | K12: =IFERROR(AVERAGEIFS(DONNEES!$O$2:$O$1501,DONNEES!$F$2:$F$1501,$A12),"") -> 23.4
A13: HERA | B13: =COUNTIFS(DONNEES!$H$2:$H$1501,"NOTABLE",DONNEES!$L$2:$L$1501,"Correct",DONNEES!$F$2:$F$1501,$A13)+COUNTIFS(DONNEES!$H$2:$H$1501,"NOTABLE",DONNEES!$L$2:$L$1501,"Pas d’info à tort",DONNEES!$F$2:$F$1501,$A13)+COUNTIFS(DONNEES!$H$2:$H$1501,"NOTABLE",DONNEES!$L$2:$L$1501,"Incorrect",DONNEES!$F$2:$F$1501,$A13)+COUNTIFS(DONNEES!$H$2:$H$1501,"NOTABLE",DONNEES!$L$2:$L$1501,"Hors sujet",DONNEES!$F$2:$F$1501,$A13) -> 5 | C13: =COUNTIFS(DONNEES!$H$2:$H$1501,"NOTABLE",DONNEES!$L$2:$L$1501,"Correct",DONNEES!$F$2:$F$1501,$A13) -> 2 | D13: =COUNTIFS(DONNEES!$H$2:$H$1501,"NOTABLE",DONNEES!$L$2:$L$1501,"Pas d’info à tort",DONNEES!$F$2:$F$1501,$A13) -> 3 | E13: =COUNTIFS(DONNEES!$H$2:$H$1501,"NOTABLE",DONNEES!$L$2:$L$1501,"Incorrect",DONNEES!$F$2:$F$1501,$A13) -> 0 | F13: =COUNTIFS(DONNEES!$H$2:$H$1501,"NOTABLE",DONNEES!$L$2:$L$1501,"Hors sujet",DONNEES!$F$2:$F$1501,$A13) -> 0 | G13: =IF($B13=0,"",C13/$B13) -> 0.4 | H13: =IF($B13=0,"",D13/$B13) -> 0.6 | I13: =IF($B13=0,"",E13/$B13) -> 0 | J13: =IF($B13=0,"",F13/$B13) -> 0 | K13: =IFERROR(AVERAGEIFS(DONNEES!$O$2:$O$1501,DONNEES!$F$2:$F$1501,$A13),"") -> 13.182
A14: R-co Conviction Credit 12M Euro | B14: =COUNTIFS(DONNEES!$H$2:$H$1501,"NOTABLE",DONNEES!$L$2:$L$1501,"Correct",DONNEES!$F$2:$F$1501,$A14)+COUNTIFS(DONNEES!$H$2:$H$1501,"NOTABLE",DONNEES!$L$2:$L$1501,"Pas d’info à tort",DONNEES!$F$2:$F$1501,$A14)+COUNTIFS(DONNEES!$H$2:$H$1501,"NOTABLE",DONNEES!$L$2:$L$1501,"Incorrect",DONNEES!$F$2:$F$1501,$A14)+COUNTIFS(DONNEES!$H$2:$H$1501,"NOTABLE",DONNEES!$L$2:$L$1501,"Hors sujet",DONNEES!$F$2:$F$1501,$A14) -> 15 | C14: =COUNTIFS(DONNEES!$H$2:$H$1501,"NOTABLE",DONNEES!$L$2:$L$1501,"Correct",DONNEES!$F$2:$F$1501,$A14) -> 9 | D14: =COUNTIFS(DONNEES!$H$2:$H$1501,"NOTABLE",DONNEES!$L$2:$L$1501,"Pas d’info à tort",DONNEES!$F$2:$F$1501,$A14) -> 2 | E14: =COUNTIFS(DONNEES!$H$2:$H$1501,"NOTABLE",DONNEES!$L$2:$L$1501,"Incorrect",DONNEES!$F$2:$F$1501,$A14) -> 4 | F14: =COUNTIFS(DONNEES!$H$2:$H$1501,"NOTABLE",DONNEES!$L$2:$L$1501,"Hors sujet",DONNEES!$F$2:$F$1501,$A14) -> 0 | G14: =IF($B14=0,"",C14/$B14) -> 0.6 | H14: =IF($B14=0,"",D14/$B14) -> 0.13333333 | I14: =IF($B14=0,"",E14/$B14) -> 0.26666667 | J14: =IF($B14=0,"",F14/$B14) -> 0 | K14: =IFERROR(AVERAGEIFS(DONNEES!$O$2:$O$1501,DONNEES!$F$2:$F$1501,$A14),"") -> 31.66
A15: Elite N | B15: =COUNTIFS(DONNEES!$H$2:$H$1501,"NOTABLE",DONNEES!$L$2:$L$1501,"Correct",DONNEES!$F$2:$F$1501,$A15)+COUNTIFS(DONNEES!$H$2:$H$1501,"NOTABLE",DONNEES!$L$2:$L$1501,"Pas d’info à tort",DONNEES!$F$2:$F$1501,$A15)+COUNTIFS(DONNEES!$H$2:$H$1501,"NOTABLE",DONNEES!$L$2:$L$1501,"Incorrect",DONNEES!$F$2:$F$1501,$A15)+COUNTIFS(DONNEES!$H$2:$H$1501,"NOTABLE",DONNEES!$L$2:$L$1501,"Hors sujet",DONNEES!$F$2:$F$1501,$A15) -> 5 | C15: =COUNTIFS(DONNEES!$H$2:$H$1501,"NOTABLE",DONNEES!$L$2:$L$1501,"Correct",DONNEES!$F$2:$F$1501,$A15) -> 3 | D15: =COUNTIFS(DONNEES!$H$2:$H$1501,"NOTABLE",DONNEES!$L$2:$L$1501,"Pas d’info à tort",DONNEES!$F$2:$F$1501,$A15) -> 0 | E15: =COUNTIFS(DONNEES!$H$2:$H$1501,"NOTABLE",DONNEES!$L$2:$L$1501,"Incorrect",DONNEES!$F$2:$F$1501,$A15) -> 2 | F15: =COUNTIFS(DONNEES!$H$2:$H$1501,"NOTABLE",DONNEES!$L$2:$L$1501,"Hors sujet",DONNEES!$F$2:$F$1501,$A15) -> 0 | G15: =IF($B15=0,"",C15/$B15) -> 0.6 | H15: =IF($B15=0,"",D15/$B15) -> 0 | I15: =IF($B15=0,"",E15/$B15) -> 0.4 | J15: =IF($B15=0,"",F15/$B15) -> 0 | K15: =IFERROR(AVERAGEIFS(DONNEES!$O$2:$O$1501,DONNEES!$F$2:$F$1501,$A15),"") -> 17.644
A16: France D Actions 2 | B16: =COUNTIFS(DONNEES!$H$2:$H$1501,"NOTABLE",DONNEES!$L$2:$L$1501,"Correct",DONNEES!$F$2:$F$1501,$A16)+COUNTIFS(DONNEES!$H$2:$H$1501,"NOTABLE",DONNEES!$L$2:$L$1501,"Pas d’info à tort",DONNEES!$F$2:$F$1501,$A16)+COUNTIFS(DONNEES!$H$2:$H$1501,"NOTABLE",DONNEES!$L$2:$L$1501,"Incorrect",DONNEES!$F$2:$F$1501,$A16)+COUNTIFS(DONNEES!$H$2:$H$1501,"NOTABLE",DONNEES!$L$2:$L$1501,"Hors sujet",DONNEES!$F$2:$F$1501,$A16) -> 5 | C16: =COUNTIFS(DONNEES!$H$2:$H$1501,"NOTABLE",DONNEES!$L$2:$L$1501,"Correct",DONNEES!$F$2:$F$1501,$A16) -> 3 | D16: =COUNTIFS(DONNEES!$H$2:$H$1501,"NOTABLE",DONNEES!$L$2:$L$1501,"Pas d’info à tort",DONNEES!$F$2:$F$1501,$A16) -> 0 | E16: =COUNTIFS(DONNEES!$H$2:$H$1501,"NOTABLE",DONNEES!$L$2:$L$1501,"Incorrect",DONNEES!$F$2:$F$1501,$A16) -> 0 | F16: =COUNTIFS(DONNEES!$H$2:$H$1501,"NOTABLE",DONNEES!$L$2:$L$1501,"Hors sujet",DONNEES!$F$2:$F$1501,$A16) -> 2 | G16: =IF($B16=0,"",C16/$B16) -> 0.6 | H16: =IF($B16=0,"",D16/$B16) -> 0 | I16: =IF($B16=0,"",E16/$B16) -> 0 | J16: =IF($B16=0,"",F16/$B16) -> 0.4 | K16: =IFERROR(AVERAGEIFS(DONNEES!$O$2:$O$1501,DONNEES!$F$2:$F$1501,$A16),"") -> 11.358
... A113: Valentin Haüy Patrimoine | B113: =COUNTIFS(DONNEES!$H$2:$H$1501,"NOTABLE",DONNEES!$L$2:$L$1501,"Correct",DONNEES!$F$2:$F$1501,$A113)+COUNTIFS(DONNEES!$H$2:$H$1501,"NOTABLE",DONNEES!$L$2:$L$1501,"Pas d’info à tort",DONNEES!$F$2:$F$1501,$A113)+COUNTIFS(DONNEES!$H$2:$H$1501,"NOTABLE",DONNEES!$L$2:$L$1501,"Incorrect",DONNEES!$F$2:$F$1501,$A113)+COUNTIFS(DONNEES!$H$2:$H$1501,"NOTABLE",DONNEES!$L$2:$L$1501,"Hors sujet",DONNEES!$F$2:$F$1501,$A113) -> 5 | C113: =COUNTIFS(DONNEES!$H$2:$H$1501,"NOTABLE",DONNEES!$L$2:$L$1501,"Correct",DONNEES!$F$2:$F$1501,$A113) -> 5 | D113: =COUNTIFS(DONNEES!$H$2:$H$1501,"NOTABLE",DONNEES!$L$2:$L$1501,"Pas d’info à tort",DONNEES!$F$2:$F$1501,$A113) -> 0 | E113: =COUNTIFS(DONNEES!$H$2:$H$1501,"NOTABLE",DONNEES!$L$2:$L$1501,"Incorrect",DONNEES!$F$2:$F$1501,$A113) -> 0 | F113: =COUNTIFS(DONNEES!$H$2:$H$1501,"NOTABLE",DONNEES!$L$2:$L$1501,"Hors sujet",DONNEES!$F$2:$F$1501,$A113) -> 0 | G113: =IF($B113=0,"",C113/$B113) -> 1 | H113: =IF($B113=0,"",D113/$B113) -> 0 | I113: =IF($B113=0,"",E113/$B113) -> 0 | J113: =IF($B113=0,"",F113/$B113) -> 0 | K113: =IFERROR(AVERAGEIFS(DONNEES!$O$2:$O$1501,DONNEES!$F$2:$F$1501,$A113),"") -> 18.066

Sheet PAR_GROUPE
A1: Résultats par groupe de fonds
A4: Groupe | B4: Notées | C4: Correct | D4: « Aucune info » à tort | E4: Valeur fausse | F4: Hors sujet | G4: % correct | H4: % aucune info | I4: % faux | J4: % hors sujet | K4: Latence moy. (s)
A5: CONTRASTE | B5: =COUNTIFS(DONNEES!$H$2:$H$1501,"NOTABLE",DONNEES!$L$2:$L$1501,"Correct",DONNEES!$D$2:$D$1501,$A5)+COUNTIFS(DONNEES!$H$2:$H$1501,"NOTABLE",DONNEES!$L$2:$L$1501,"Pas d’info à tort",DONNEES!$D$2:$D$1501,$A5)+COUNTIFS(DONNEES!$H$2:$H$1501,"NOTABLE",DONNEES!$L$2:$L$1501,"Incorrect",DONNEES!$D$2:$D$1501,$A5)+COUNTIFS(DONNEES!$H$2:$H$1501,"NOTABLE",DONNEES!$L$2:$L$1501,"Hors sujet",DONNEES!$D$2:$D$1501,$A5) -> 676 | C5: =COUNTIFS(DONNEES!$H$2:$H$1501,"NOTABLE",DONNEES!$L$2:$L$1501,"Correct",DONNEES!$D$2:$D$1501,$A5) -> 553 | D5: =COUNTIFS(DONNEES!$H$2:$H$1501,"NOTABLE",DONNEES!$L$2:$L$1501,"Pas d’info à tort",DONNEES!$D$2:$D$1501,$A5) -> 94 | E5: =COUNTIFS(DONNEES!$H$2:$H$1501,"NOTABLE",DONNEES!$L$2:$L$1501,"Incorrect",DONNEES!$D$2:$D$1501,$A5) -> 16 | F5: =COUNTIFS(DONNEES!$H$2:$H$1501,"NOTABLE",DONNEES!$L$2:$L$1501,"Hors sujet",DONNEES!$D$2:$D$1501,$A5) -> 13 | G5: =IF($B5=0,"",C5/$B5) -> 0.81804734 | H5: =IF($B5=0,"",D5/$B5) -> 0.13905325 | I5: =IF($B5=0,"",E5/$B5) -> 0.023668639 | J5: =IF($B5=0,"",F5/$B5) -> 0.019230769 | K5: =IFERROR(AVERAGEIFS(DONNEES!$O$2:$O$1501,DONNEES!$D$2:$D$1501,$A5),"") -> 18.34585
A6: PRIORITAIRE | B6: =COUNTIFS(DONNEES!$H$2:$H$1501,"NOTABLE",DONNEES!$L$2:$L$1501,"Correct",DONNEES!$D$2:$D$1501,$A6)+COUNTIFS(DONNEES!$H$2:$H$1501,"NOTABLE",DONNEES!$L$2:$L$1501,"Pas d’info à tort",DONNEES!$D$2:$D$1501,$A6)+COUNTIFS(DONNEES!$H$2:$H$1501,"NOTABLE",DONNEES!$L$2:$L$1501,"Incorrect",DONNEES!$D$2:$D$1501,$A6)+COUNTIFS(DONNEES!$H$2:$H$1501,"NOTABLE",DONNEES!$L$2:$L$1501,"Hors sujet",DONNEES!$D$2:$D$1501,$A6) -> 689 | C6: =COUNTIFS(DONNEES!$H$2:$H$1501,"NOTABLE",DONNEES!$L$2:$L$1501,"Correct",DONNEES!$D$2:$D$1501,$A6) -> 554 | D6: =COUNTIFS(DONNEES!$H$2:$H$1501,"NOTABLE",DONNEES!$L$2:$L$1501,"Pas d’info à tort",DONNEES!$D$2:$D$1501,$A6) -> 92 | E6: =COUNTIFS(DONNEES!$H$2:$H$1501,"NOTABLE",DONNEES!$L$2:$L$1501,"Incorrect",DONNEES!$D$2:$D$1501,$A6) -> 33 | F6: =COUNTIFS(DONNEES!$H$2:$H$1501,"NOTABLE",DONNEES!$L$2:$L$1501,"Hors sujet",DONNEES!$D$2:$D$1501,$A6) -> 10 | G6: =IF($B6=0,"",C6/$B6) -> 0.80406386 | H6: =IF($B6=0,"",D6/$B6) -> 0.13352685 | I6: =IF($B6=0,"",E6/$B6) -> 0.047895501 | J6: =IF($B6=0,"",F6/$B6) -> 0.014513788 | K6: =IFERROR(AVERAGEIFS(DONNEES!$O$2:$O$1501,DONNEES!$D$2:$D$1501,$A6),"") -> 18.557467

Sheet CROISEMENT
A1: Croisements
A2: % de réponses justes par famille et par tour (questions à valeur connue).
A4: Famille \ Tour | B4: Tour 1 | C4: Tour 2 | D4: Tour 3 | E4: Tour 4 | F4: Tour 5 | G4: Tous tours
A5: Risque | B5: =IFERROR(COUNTIFS(DONNEES!$H$2:$H$1501,"NOTABLE",DONNEES!$L$2:$L$1501,"Correct",DONNEES!$E$2:$E$1501,$A5,DONNEES!$C$2:$C$1501,1)/(COUNTIFS(DONNEES!$H$2:$H$1501,"NOTABLE",DONNEES!$L$2:$L$1501,"Correct",DONNEES!$E$2:$E$1501,$A5,DONNEES!$C$2:$C$1501,1)+COUNTIFS(DONNEES!$H$2:$H$1501,"NOTABLE",DONNEES!$L$2:$L$1501,"Pas d’info à tort",DONNEES!$E$2:$E$1501,$A5,DONNEES!$C$2:$C$1501,1)+COUNTIFS(DONNEES!$H$2:$H$1501,"NOTABLE",DONNEES!$L$2:$L$1501,"Incorrect",DONNEES!$E$2:$E$1501,$A5,DONNEES!$C$2:$C$1501,1)+COUNTIFS(DONNEES!$H$2:$H$1501,"NOTABLE",DONNEES!$L$2:$L$1501,"Hors sujet",DONNEES!$E$2:$E$1501,$A5,DONNEES!$C$2:$C$1501,1)),"") -> 0.5 | C5: =IFERROR(COUNTIFS(DONNEES!$H$2:$H$1501,"NOTABLE",DONNEES!$L$2:$L$1501,"Correct",DONNEES!$E$2:$E$1501,$A5,DONNEES!$C$2:$C$1501,2)/(COUNTIFS(DONNEES!$H$2:$H$1501,"NOTABLE",DONNEES!$L$2:$L$1501,"Correct",DONNEES!$E$2:$E$1501,$A5,DONNEES!$C$2:$C$1501,2)+COUNTIFS(DONNEES!$H$2:$H$1501,"NOTABLE",DONNEES!$L$2:$L$1501,"Pas d’info à tort",DONNEES!$E$2:$E$1501,$A5,DONNEES!$C$2:$C$1501,2)+COUNTIFS(DONNEES!$H$2:$H$1501,"NOTABLE",DONNEES!$L$2:$L$1501,"Incorrect",DONNEES!$E$2:$E$1501,$A5,DONNEES!$C$2:$C$1501,2)+COUNTIFS(DONNEES!$H$2:$H$1501,"NOTABLE",DONNEES!$L$2:$L$1501,"Hors sujet",DONNEES!$E$2:$E$1501,$A5,DONNEES!$C$2:$C$1501,2)),"") -> 0.5 | D5: =IFERROR(COUNTIFS(DONNEES!$H$2:$H$1501,"NOTABLE",DONNEES!$L$2:$L$1501,"Correct",DONNEES!$E$2:$E$1501,$A5,DONNEES!$C$2:$C$1501,3)/(COUNTIFS(DONNEES!$H$2:$H$1501,"NOTABLE",DONNEES!$L$2:$L$1501,"Correct",DONNEES!$E$2:$E$1501,$A5,DONNEES!$C$2:$C$1501,3)+COUNTIFS(DONNEES!$H$2:$H$1501,"NOTABLE",DONNEES!$L$2:$L$1501,"Pas d’info à tort",DONNEES!$E$2:$E$1501,$A5,DONNEES!$C$2:$C$1501,3)+COUNTIFS(DONNEES!$H$2:$H$1501,"NOTABLE",DONNEES!$L$2:$L$1501,"Incorrect",DONNEES!$E$2:$E$1501,$A5,DONNEES!$C$2:$C$1501,3)+COUNTIFS(DONNEES!$H$2:$H$1501,"NOTABLE",DONNEES!$L$2:$L$1501,"Hors sujet",DONNEES!$E$2:$E$1501,$A5,DONNEES!$C$2:$C$1501,3)),"") -> 0.41666667 | E5: =IFERROR(COUNTIFS(DONNEES!$H$2:$H$1501,"NOTABLE",DONNEES!$L$2:$L$1501,"Correct",DONNEES!$E$2:$E$1501,$A5,DONNEES!$C$2:$C$1501,4)/(COUNTIFS(DONNEES!$H$2:$H$1501,"NOTABLE",DONNEES!$L$2:$L$1501,"Correct",DONNEES!$E$2:$E$1501,$A5,DONNEES!$C$2:$C$1501,4)+COUNTIFS(DONNEES!$H$2:$H$1501,"NOTABLE",DONNEES!$L$2:$L$1501,"Pas d’info à tort",DONNEES!$E$2:$E$1501,$A5,DONNEES!$C$2:$C$1501,4)+COUNTIFS(DONNEES!$H$2:$H$1501,"NOTABLE",DONNEES!$L$2:$L$1501,"Incorrect",DONNEES!$E$2:$E$1501,$A5,DONNEES!$C$2:$C$1501,4)+COUNTIFS(DONNEES!$H$2:$H$1501,"NOTABLE",DONNEES!$L$2:$L$1501,"Hors sujet",DONNEES!$E$2:$E$1501,$A5,DONNEES!$C$2:$C$1501,4)),"") -> 0.375 | F5: =IFERROR(COUNTIFS(DONNEES!$H$2:$H$1501,"NOTABLE",DONNEES!$L$2:$L$1501,"Correct",DONNEES!$E$2:$E$1501,$A5,DONNEES!$C$2:$C$1501,5)/(COUNTIFS(DONNEES!$H$2:$H$1501,"NOTABLE",DONNEES!$L$2:$L$1501,"Correct",DONNEES!$E$2:$E$1501,$A5,DONNEES!$C$2:$C$1501,5)+COUNTIFS(DONNEES!$H$2:$H$1501,"NOTABLE",DONNEES!$L$2:$L$1501,"Pas d’info à tort",DONNEES!$E$2:$E$1501,$A5,DONNEES!$C$2:$C$1501,5)+COUNTIFS(DONNEES!$H$2:$H$1501,"NOTABLE",DONNEES!$L$2:$L$1501,"Incorrect",DONNEES!$E$2:$E$1501,$A5,DONNEES!$C$2:$C$1501,5)+COUNTIFS(DONNEES!$H$2:$H$1501,"NOTABLE",DONNEES!$L$2:$L$1501,"Hors sujet",DONNEES!$E$2:$E$1501,$A5,DONNEES!$C$2:$C$1501,5)),"") -> 0.57142857 | G5: =IFERROR(COUNTIFS(DONNEES!$H$2:$H$1501,"NOTABLE",DONNEES!$L$2:$L$1501,"Correct",DONNEES!$E$2:$E$1501,$A5)/(COUNTIFS(DONNEES!$H$2:$H$1501,"NOTABLE",DONNEES!$L$2:$L$1501,"Correct",DONNEES!$E$2:$E$1501,$A5)+COUNTIFS(DONNEES!$H$2:$H$1501,"NOTABLE",DONNEES!$L$2:$L$1501,"Pas d’info à tort",DONNEES!$E$2:$E$1501,$A5)+COUNTIFS(DONNEES!$H$2:$H$1501,"NOTABLE",DONNEES!$L$2:$L$1501,"Incorrect",DONNEES!$E$2:$E$1501,$A5)+COUNTIFS(DONNEES!$H$2:$H$1501,"NOTABLE",DONNEES!$L$2:$L$1501,"Hors sujet",DONNEES!$E$2:$E$1501,$A5)),"") -> 0.48181818
A6: ESG / EET | B6: =IFERROR(COUNTIFS(DONNEES!$H$2:$H$1501,"NOTABLE",DONNEES!$L$2:$L$1501,"Correct",DONNEES!$E$2:$E$1501,$A6,DONNEES!$C$2:$C$1501,1)/(COUNTIFS(DONNEES!$H$2:$H$1501,"NOTABLE",DONNEES!$L$2:$L$1501,"Correct",DONNEES!$E$2:$E$1501,$A6,DONNEES!$C$2:$C$1501,1)+COUNTIFS(DONNEES!$H$2:$H$1501,"NOTABLE",DONNEES!$L$2:$L$1501,"Pas d’info à tort",DONNEES!$E$2:$E$1501,$A6,DONNEES!$C$2:$C$1501,1)+COUNTIFS(DONNEES!$H$2:$H$1501,"NOTABLE",DONNEES!$L$2:$L$1501,"Incorrect",DONNEES!$E$2:$E$1501,$A6,DONNEES!$C$2:$C$1501,1)+COUNTIFS(DONNEES!$H$2:$H$1501,"NOTABLE",DONNEES!$L$2:$L$1501,"Hors sujet",DONNEES!$E$2:$E$1501,$A6,DONNEES!$C$2:$C$1501,1)),"") -> 0.73770492 | C6: =IFERROR(COUNTIFS(DONNEES!$H$2:$H$1501,"NOTABLE",DONNEES!$L$2:$L$1501,"Correct",DONNEES!$E$2:$E$1501,$A6,DONNEES!$C$2:$C$1501,2)/(COUNTIFS(DONNEES!$H$2:$H$1501,"NOTABLE",DONNEES!$L$2:$L$1501,"Correct",DONNEES!$E$2:$E$1501,$A6,DONNEES!$C$2:$C$1501,2)+COUNTIFS(DONNEES!$H$2:$H$1501,"NOTABLE",DONNEES!$L$2:$L$1501,"Pas d’info à tort",DONNEES!$E$2:$E$1501,$A6,DONNEES!$C$2:$C$1501,2)+COUNTIFS(DONNEES!$H$2:$H$1501,"NOTABLE",DONNEES!$L$2:$L$1501,"Incorrect",DONNEES!$E$2:$E$1501,$A6,DONNEES!$C$2:$C$1501,2)+COUNTIFS(DONNEES!$H$2:$H$1501,"NOTABLE",DONNEES!$L$2:$L$1501,"Hors sujet",DONNEES!$E$2:$E$1501,$A6,DONNEES!$C$2:$C$1501,2)),"") -> 0.68085106 | D6: =IFERROR(COUNTIFS(DONNEES!$H$2:$H$1501,"NOTABLE",DONNEES!$L$2:$L$1501,"Correct",DONNEES!$E$2:$E$1501,$A6,DONNEES!$C$2:$C$1501,3)/(COUNTIFS(DONNEES!$H$2:$H$1501,"NOTABLE",DONNEES!$L$2:$L$1501,"Correct",DONNEES!$E$2:$E$1501,$A6,DONNEES!$C$2:$C$1501,3)+COUNTIFS(DONNEES!$H$2:$H$1501,"NOTABLE",DONNEES!$L$2:$L$1501,"Pas d’info à tort",DONNEES!$E$2:$E$1501,$A6,DONNEES!$C$2:$C$1501,3)+COUNTIFS(DONNEES!$H$2:$H$1501,"NOTABLE",DONNEES!$L$2:$L$1501,"Incorrect",DONNEES!$E$2:$E$1501,$A6,DONNEES!$C$2:$C$1501,3)+COUNTIFS(DONNEES!$H$2:$H$1501,"NOTABLE",DONNEES!$L$2:$L$1501,"Hors sujet",DONNEES!$E$2:$E$1501,$A6,DONNEES!$C$2:$C$1501,3)),"") -> 0.77777778 | E6: =IFERROR(COUNTIFS(DONNEES!$H$2:$H$1501,"NOTABLE",DONNEES!$L$2:$L$1501,"Correct",DONNEES!$E$2:$E$1501,$A6,DONNEES!$C$2:$C$1501,4)/(COUNTIFS(DONNEES!$H$2:$H$1501,"NOTABLE",DONNEES!$L$2:$L$1501,"Correct",DONNEES!$E$2:$E$1501,$A6,DONNEES!$C$2:$C$1501,4)+COUNTIFS(DONNEES!$H$2:$H$1501,"NOTABLE",DONNEES!$L$2:$L$1501,"Pas d’info à tort",DONNEES!$E$2:$E$1501,$A6,DONNEES!$C$2:$C$1501,4)+COUNTIFS(DONNEES!$H$2:$H$1501,"NOTABLE",DONNEES!$L$2:$L$1501,"Incorrect",DONNEES!$E$2:$E$1501,$A6,DONNEES!$C$2:$C$1501,4)+COUNTIFS(DONNEES!$H$2:$H$1501,"NOTABLE",DONNEES!$L$2:$L$1501,"Hors sujet",DONNEES!$E$2:$E$1501,$A6,DONNEES!$C$2:$C$1501,4)),"") -> 0.90909091 | F6: =IFERROR(COUNTIFS(DONNEES!$H$2:$H$1501,"NOTABLE",DONNEES!$L$2:$L$1501,"Correct",DONNEES!$E$2:$E$1501,$A6,DONNEES!$C$2:$C$1501,5)/(COUNTIFS(DONNEES!$H$2:$H$1501,"NOTABLE",DONNEES!$L$2:$L$1501,"Correct",DONNEES!$E$2:$E$1501,$A6,DONNEES!$C$2:$C$1501,5)+COUNTIFS(DONNEES!$H$2:$H$1501,"NOTABLE",DONNEES!$L$2:$L$1501,"Pas d’info à tort",DONNEES!$E$2:$E$1501,$A6,DONNEES!$C$2:$C$1501,5)+COUNTIFS(DONNEES!$H$2:$H$1501,"NOTABLE",DONNEES!$L$2:$L$1501,"Incorrect",DONNEES!$E$2:$E$1501,$A6,DONNEES!$C$2:$C$1501,5)+COUNTIFS(DONNEES!$H$2:$H$1501,"NOTABLE",DONNEES!$L$2:$L$1501,"Hors sujet",DONNEES!$E$2:$E$1501,$A6,DONNEES!$C$2:$C$1501,5)),"") -> 0.80597015 | G6: =IFERROR(COUNTIFS(DONNEES!$H$2:$H$1501,"NOTABLE",DONNEES!$L$2:$L$1501,"Correct",DONNEES!$E$2:$E$1501,$A6)/(COUNTIFS(DONNEES!$H$2:$H$1501,"NOTABLE",DONNEES!$L$2:$L$1501,"Correct",DONNEES!$E$2:$E$1501,$A6)+COUNTIFS(DONNEES!$H$2:$H$1501,"NOTABLE",DONNEES!$L$2:$L$1501,"Pas d’info à tort",DONNEES!$E$2:$E$1501,$A6)+COUNTIFS(DONNEES!$H$2:$H$1501,"NOTABLE",DONNEES!$L$2:$L$1501,"Incorrect",DONNEES!$E$2:$E$1501,$A6)+COUNTIFS(DONNEES!$H$2:$H$1501,"NOTABLE",DONNEES!$L$2:$L$1501,"Hors sujet",DONNEES!$E$2:$E$1501,$A6)),"") -> 0.77480916
A7: Expertise et gamme | B7: =IFERROR(COUNTIFS(DONNEES!$H$2:$H$1501,"NOTABLE",DONNEES!$L$2:$L$1501,"Correct",DONNEES!$E$2:$E$1501,$A7,DONNEES!$C$2:$C$1501,1)/(COUNTIFS(DONNEES!$H$2:$H$1501,"NOTABLE",DONNEES!$L$2:$L$1501,"Correct",DONNEES!$E$2:$E$1501,$A7,DONNEES!$C$2:$C$1501,1)+COUNTIFS(DONNEES!$H$2:$H$1501,"NOTABLE",DONNEES!$L$2:$L$1501,"Pas d’info à tort",DONNEES!$E$2:$E$1501,$A7,DONNEES!$C$2:$C$1501,1)+COUNTIFS(DONNEES!$H$2:$H$1501,"NOTABLE",DONNEES!$L$2:$L$1501,"Incorrect",DONNEES!$E$2:$E$1501,$A7,DONNEES!$C$2:$C$1501,1)+COUNTIFS(DONNEES!$H$2:$H$1501,"NOTABLE",DONNEES!$L$2:$L$1501,"Hors sujet",DONNEES!$E$2:$E$1501,$A7,DONNEES!$C$2:$C$1501,1)),"") -> 0.89285714 | C7: =IFERROR(COUNTIFS(DONNEES!$H$2:$H$1501,"NOTABLE",DONNEES!$L$2:$L$1501,"Correct",DONNEES!$E$2:$E$1501,$A7,DONNEES!$C$2:$C$1501,2)/(COUNTIFS(DONNEES!$H$2:$H$1501,"NOTABLE",DONNEES!$L$2:$L$1501,"Correct",DONNEES!$E$2:$E$1501,$A7,DONNEES!$C$2:$C$1501,2)+COUNTIFS(DONNEES!$H$2:$H$1501,"NOTABLE",DONNEES!$L$2:$L$1501,"Pas d’info à tort",DONNEES!$E$2:$E$1501,$A7,DONNEES!$C$2:$C$1501,2)+COUNTIFS(DONNEES!$H$2:$H$1501,"NOTABLE",DONNEES!$L$2:$L$1501,"Incorrect",DONNEES!$E$2:$E$1501,$A7,DONNEES!$C$2:$C$1501,2)+COUNTIFS(DONNEES!$H$2:$H$1501,"NOTABLE",DONNEES!$L$2:$L$1501,"Hors sujet",DONNEES!$E$2:$E$1501,$A7,DONNEES!$C$2:$C$1501,2)),"") -> 0.75 | D7: =IFERROR(COUNTIFS(DONNEES!$H$2:$H$1501,"NOTABLE",DONNEES!$L$2:$L$1501,"Correct",DONNEES!$E$2:$E$1501,$A7,DONNEES!$C$2:$C$1501,3)/(COUNTIFS(DONNEES!$H$2:$H$1501,"NOTABLE",DONNEES!$L$2:$L$1501,"Correct",DONNEES!$E$2:$E$1501,$A7,DONNEES!$C$2:$C$1501,3)+COUNTIFS(DONNEES!$H$2:$H$1501,"NOTABLE",DONNEES!$L$2:$L$1501,"Pas d’info à tort",DONNEES!$E$2:$E$1501,$A7,DONNEES!$C$2:$C$1501,3)+COUNTIFS(DONNEES!$H$2:$H$1501,"NOTABLE",DONNEES!$L$2:$L$1501,"Incorrect",DONNEES!$E$2:$E$1501,$A7,DONNEES!$C$2:$C$1501,3)+COUNTIFS(DONNEES!$H$2:$H$1501,"NOTABLE",DONNEES!$L$2:$L$1501,"Hors sujet",DONNEES!$E$2:$E$1501,$A7,DONNEES!$C$2:$C$1501,3)),"") -> 0.76923077 | E7: =IFERROR(COUNTIFS(DONNEES!$H$2:$H$1501,"NOTABLE",DONNEES!$L$2:$L$1501,"Correct",DONNEES!$E$2:$E$1501,$A7,DONNEES!$C$2:$C$1501,4)/(COUNTIFS(DONNEES!$H$2:$H$1501,"NOTABLE",DONNEES!$L$2:$L$1501,"Correct",DONNEES!$E$2:$E$1501,$A7,DONNEES!$C$2:$C$1501,4)+COUNTIFS(DONNEES!$H$2:$H$1501,"NOTABLE",DONNEES!$L$2:$L$1501,"Pas d’info à tort",DONNEES!$E$2:$E$1501,$A7,DONNEES!$C$2:$C$1501,4)+COUNTIFS(DONNEES!$H$2:$H$1501,"NOTABLE",DONNEES!$L$2:$L$1501,"Incorrect",DONNEES!$E$2:$E$1501,$A7,DONNEES!$C$2:$C$1501,4)+COUNTIFS(DONNEES!$H$2:$H$1501,"NOTABLE",DONNEES!$L$2:$L$1501,"Hors sujet",DONNEES!$E$2:$E$1501,$A7,DONNEES!$C$2:$C$1501,4)),"") -> 0.77272727 | F7: =IFERROR(COUNTIFS(DONNEES!$H$2:$H$1501,"NOTABLE",DONNEES!$L$2:$L$1501,"Correct",DONNEES!$E$2:$E$1501,$A7,DONNEES!$C$2:$C$1501,5)/(COUNTIFS(DONNEES!$H$2:$H$1501,"NOTABLE",DONNEES!$L$2:$L$1501,"Correct",DONNEES!$E$2:$E$1501,$A7,DONNEES!$C$2:$C$1501,5)+COUNTIFS(DONNEES!$H$2:$H$1501,"NOTABLE",DONNEES!$L$2:$L$1501,"Pas d’info à tort",DONNEES!$E$2:$E$1501,$A7,DONNEES!$C$2:$C$1501,5)+COUNTIFS(DONNEES!$H$2:$H$1501,"NOTABLE",DONNEES!$L$2:$L$1501,"Incorrect",DONNEES!$E$2:$E$1501,$A7,DONNEES!$C$2:$C$1501,5)+COUNTIFS(DONNEES!$H$2:$H$1501,"NOTABLE",DONNEES!$L$2:$L$1501,"Hors sujet",DONNEES!$E$2:$E$1501,$A7,DONNEES!$C$2:$C$1501,5)),"") -> 0.76923077 | G7: =IFERROR(COUNTIFS(DONNEES!$H$2:$H$1501,"NOTABLE",DONNEES!$L$2:$L$1501,"Correct",DONNEES!$E$2:$E$1501,$A7)/(COUNTIFS(DONNEES!$H$2:$H$1501,"NOTABLE",DONNEES!$L$2:$L$1501,"Correct",DONNEES!$E$2:$E$1501,$A7)+COUNTIFS(DONNEES!$H$2:$H$1501,"NOTABLE",DONNEES!$L$2:$L$1501,"Pas d’info à tort",DONNEES!$E$2:$E$1501,$A7)+COUNTIFS(DONNEES!$H$2:$H$1501,"NOTABLE",DONNEES!$L$2:$L$1501,"Incorrect",DONNEES!$E$2:$E$1501,$A7)+COUNTIFS(DONNEES!$H$2:$H$1501,"NOTABLE",DONNEES!$L$2:$L$1501,"Hors sujet",DONNEES!$E$2:$E$1501,$A7)),"") -> 0.79259259
A8: Frais et coûts | B8: =IFERROR(COUNTIFS(DONNEES!$H$2:$H$1501,"NOTABLE",DONNEES!$L$2:$L$1501,"Correct",DONNEES!$E$2:$E$1501,$A8,DONNEES!$C$2:$C$1501,1)/(COUNTIFS(DONNEES!$H$2:$H$1501,"NOTABLE",DONNEES!$L$2:$L$1501,"Correct",DONNEES!$E$2:$E$1501,$A8,DONNEES!$C$2:$C$1501,1)+COUNTIFS(DONNEES!$H$2:$H$1501,"NOTABLE",DONNEES!$L$2:$L$1501,"Pas d’info à tort",DONNEES!$E$2:$E$1501,$A8,DONNEES!$C$2:$C$1501,1)+COUNTIFS(DONNEES!$H$2:$H$1501,"NOTABLE",DONNEES!$L$2:$L$1501,"Incorrect",DONNEES!$E$2:$E$1501,$A8,DONNEES!$C$2:$C$1501,1)+COUNTIFS(DONNEES!$H$2:$H$1501,"NOTABLE",DONNEES!$L$2:$L$1501,"Hors sujet",DONNEES!$E$2:$E$1501,$A8,DONNEES!$C$2:$C$1501,1)),"") -> 0.84090909 | C8: =IFERROR(COUNTIFS(DONNEES!$H$2:$H$1501,"NOTABLE",DONNEES!$L$2:$L$1501,"Correct",DONNEES!$E$2:$E$1501,$A8,DONNEES!$C$2:$C$1501,2)/(COUNTIFS(DONNEES!$H$2:$H$1501,"NOTABLE",DONNEES!$L$2:$L$1501,"Correct",DONNEES!$E$2:$E$1501,$A8,DONNEES!$C$2:$C$1501,2)+COUNTIFS(DONNEES!$H$2:$H$1501,"NOTABLE",DONNEES!$L$2:$L$1501,"Pas d’info à tort",DONNEES!$E$2:$E$1501,$A8,DONNEES!$C$2:$C$1501,2)+COUNTIFS(DONNEES!$H$2:$H$1501,"NOTABLE",DONNEES!$L$2:$L$1501,"Incorrect",DONNEES!$E$2:$E$1501,$A8,DONNEES!$C$2:$C$1501,2)+COUNTIFS(DONNEES!$H$2:$H$1501,"NOTABLE",DONNEES!$L$2:$L$1501,"Hors sujet",DONNEES!$E$2:$E$1501,$A8,DONNEES!$C$2:$C$1501,2)),"") -> 0.79069767 | D8: =IFERROR(COUNTIFS(DONNEES!$H$2:$H$1501,"NOTABLE",DONNEES!$L$2:$L$1501,"Correct",DONNEES!$E$2:$E$1501,$A8,DONNEES!$C$2:$C$1501,3)/(COUNTIFS(DONNEES!$H$2:$H$1501,"NOTABLE",DONNEES!$L$2:$L$1501,"Correct",DONNEES!$E$2:$E$1501,$A8,DONNEES!$C$2:$C$1501,3)+COUNTIFS(DONNEES!$H$2:$H$1501,"NOTABLE",DONNEES!$L$2:$L$1501,"Pas d’info à tort",DONNEES!$E$2:$E$1501,$A8,DONNEES!$C$2:$C$1501,3)+COUNTIFS(DONNEES!$H$2:$H$1501,"NOTABLE",DONNEES!$L$2:$L$1501,"Incorrect",DONNEES!$E$2:$E$1501,$A8,DONNEES!$C$2:$C$1501,3)+COUNTIFS(DONNEES!$H$2:$H$1501,"NOTABLE",DONNEES!$L$2:$L$1501,"Hors sujet",DONNEES!$E$2:$E$1501,$A8,DONNEES!$C$2:$C$1501,3)),"") -> 0.82758621 | E8: =IFERROR(COUNTIFS(DONNEES!$H$2:$H$1501,"NOTABLE",DONNEES!$L$2:$L$1501,"Correct",DONNEES!$E$2:$E$1501,$A8,DONNEES!$C$2:$C$1501,4)/(COUNTIFS(DONNEES!$H$2:$H$1501,"NOTABLE",DONNEES!$L$2:$L$1501,"Correct",DONNEES!$E$2:$E$1501,$A8,DONNEES!$C$2:$C$1501,4)+COUNTIFS(DONNEES!$H$2:$H$1501,"NOTABLE",DONNEES!$L$2:$L$1501,"Pas d’info à tort",DONNEES!$E$2:$E$1501,$A8,DONNEES!$C$2:$C$1501,4)+COUNTIFS(DONNEES!$H$2:$H$1501,"NOTABLE",DONNEES!$L$2:$L$1501,"Incorrect",DONNEES!$E$2:$E$1501,$A8,DONNEES!$C$2:$C$1501,4)+COUNTIFS(DONNEES!$H$2:$H$1501,"NOTABLE",DONNEES!$L$2:$L$1501,"Hors sujet",DONNEES!$E$2:$E$1501,$A8,DONNEES!$C$2:$C$1501,4)),"") -> 0.83333333 | F8: =IFERROR(COUNTIFS(DONNEES!$H$2:$H$1501,"NOTABLE",DONNEES!$L$2:$L$1501,"Correct",DONNEES!$E$2:$E$1501,$A8,DONNEES!$C$2:$C$1501,5)/(COUNTIFS(DONNEES!$H$2:$H$1501,"NOTABLE",DONNEES!$L$2:$L$1501,"Correct",DONNEES!$E$2:$E$1501,$A8,DONNEES!$C$2:$C$1501,5)+COUNTIFS(DONNEES!$H$2:$H$1501,"NOTABLE",DONNEES!$L$2:$L$1501,"Pas d’info à tort",DONNEES!$E$2:$E$1501,$A8,DONNEES!$C$2:$C$1501,5)+COUNTIFS(DONNEES!$H$2:$H$1501,"NOTABLE",DONNEES!$L$2:$L$1501,"Incorrect",DONNEES!$E$2:$E$1501,$A8,DONNEES!$C$2:$C$1501,5)+COUNTIFS(DONNEES!$H$2:$H$1501,"NOTABLE",DONNEES!$L$2:$L$1501,"Hors sujet",DONNEES!$E$2:$E$1501,$A8,DONNEES!$C$2:$C$1501,5)),"") -> 0.85 | G8: =IFERROR(COUNTIFS(DONNEES!$H$2:$H$1501,"NOTABLE",DONNEES!$L$2:$L$1501,"Correct",DONNEES!$E$2:$E$1501,$A8)/(COUNTIFS(DONNEES!$H$2:$H$1501,"NOTABLE",DONNEES!$L$2:$L$1501,"Correct",DONNEES!$E$2:$E$1501,$A8)+COUNTIFS(DONNEES!$H$2:$H$1501,"NOTABLE",DONNEES!$L$2:$L$1501,"Pas d’info à tort",DONNEES!$E$2:$E$1501,$A8)+COUNTIFS(DONNEES!$H$2:$H$1501,"NOTABLE",DONNEES!$L$2:$L$1501,"Incorrect",DONNEES!$E$2:$E$1501,$A8)+COUNTIFS(DONNEES!$H$2:$H$1501,"NOTABLE",DONNEES!$L$2:$L$1501,"Hors sujet",DONNEES!$E$2:$E$1501,$A8)),"") -> 0.828125
A9: Textes longs | B9: =IFERROR(COUNTIFS(DONNEES!$H$2:$H$1501,"NOTABLE",DONNEES!$L$2:$L$1501,"Correct",DONNEES!$E$2:$E$1501,$A9,DONNEES!$C$2:$C$1501,1)/(COUNTIFS(DONNEES!$H$2:$H$1501,"NOTABLE",DONNEES!$L$2:$L$1501,"Correct",DONNEES!$E$2:$E$1501,$A9,DONNEES!$C$2:$C$1501,1)+COUNTIFS(DONNEES!$H$2:$H$1501,"NOTABLE",DONNEES!$L$2:$L$1501,"Pas d’info à tort",DONNEES!$E$2:$E$1501,$A9,DONNEES!$C$2:$C$1501,1)+COUNTIFS(DONNEES!$H$2:$H$1501,"NOTABLE",DONNEES!$L$2:$L$1501,"Incorrect",DONNEES!$E$2:$E$1501,$A9,DONNEES!$C$2:$C$1501,1)+COUNTIFS(DONNEES!$H$2:$H$1501,"NOTABLE",DONNEES!$L$2:$L$1501,"Hors sujet",DONNEES!$E$2:$E$1501,$A9,DONNEES!$C$2:$C$1501,1)),"") -> 0.70588235 | C9: =IFERROR(COUNTIFS(DONNEES!$H$2:$H$1501,"NOTABLE",DONNEES!$L$2:$L$1501,"Correct",DONNEES!$E$2:$E$1501,$A9,DONNEES!$C$2:$C$1501,2)/(COUNTIFS(DONNEES!$H$2:$H$1501,"NOTABLE",DONNEES!$L$2:$L$1501,"Correct",DONNEES!$E$2:$E$1501,$A9,DONNEES!$C$2:$C$1501,2)+COUNTIFS(DONNEES!$H$2:$H$1501,"NOTABLE",DONNEES!$L$2:$L$1501,"Pas d’info à tort",DONNEES!$E$2:$E$1501,$A9,DONNEES!$C$2:$C$1501,2)+COUNTIFS(DONNEES!$H$2:$H$1501,"NOTABLE",DONNEES!$L$2:$L$1501,"Incorrect",DONNEES!$E$2:$E$1501,$A9,DONNEES!$C$2:$C$1501,2)+COUNTIFS(DONNEES!$H$2:$H$1501,"NOTABLE",DONNEES!$L$2:$L$1501,"Hors sujet",DONNEES!$E$2:$E$1501,$A9,DONNEES!$C$2:$C$1501,2)),"") -> 0.83333333 | D9: =IFERROR(COUNTIFS(DONNEES!$H$2:$H$1501,"NOTABLE",DONNEES!$L$2:$L$1501,"Correct",DONNEES!$E$2:$E$1501,$A9,DONNEES!$C$2:$C$1501,3)/(COUNTIFS(DONNEES!$H$2:$H$1501,"NOTABLE",DONNEES!$L$2:$L$1501,"Correct",DONNEES!$E$2:$E$1501,$A9,DONNEES!$C$2:$C$1501,3)+COUNTIFS(DONNEES!$H$2:$H$1501,"NOTABLE",DONNEES!$L$2:$L$1501,"Pas d’info à tort",DONNEES!$E$2:$E$1501,$A9,DONNEES!$C$2:$C$1501,3)+COUNTIFS(DONNEES!$H$2:$H$1501,"NOTABLE",DONNEES!$L$2:$L$1501,"Incorrect",DONNEES!$E$2:$E$1501,$A9,DONNEES!$C$2:$C$1501,3)+COUNTIFS(DONNEES!$H$2:$H$1501,"NOTABLE",DONNEES!$L$2:$L$1501,"Hors sujet",DONNEES!$E$2:$E$1501,$A9,DONNEES!$C$2:$C$1501,3)),"") -> 0.83333333 | E9: =IFERROR(COUNTIFS(DONNEES!$H$2:$H$1501,"NOTABLE",DONNEES!$L$2:$L$1501,"Correct",DONNEES!$E$2:$E$1501,$A9,DONNEES!$C$2:$C$1501,4)/(COUNTIFS(DONNEES!$H$2:$H$1501,"NOTABLE",DONNEES!$L$2:$L$1501,"Correct",DONNEES!$E$2:$E$1501,$A9,DONNEES!$C$2:$C$1501,4)+COUNTIFS(DONNEES!$H$2:$H$1501,"NOTABLE",DONNEES!$L$2:$L$1501,"Pas d’info à tort",DONNEES!$E$2:$E$1501,$A9,DONNEES!$C$2:$C$1501,4)+COUNTIFS(DONNEES!$H$2:$H$1501,"NOTABLE",DONNEES!$L$2:$L$1501,"Incorrect",DONNEES!$E$2:$E$1501,$A9,DONNEES!$C$2:$C$1501,4)+COUNTIFS(DONNEES!$H$2:$H$1501,"NOTABLE",DONNEES!$L$2:$L$1501,"Hors sujet",DONNEES!$E$2:$E$1501,$A9,DONNEES!$C$2:$C$1501,4)),"") -> 0.92307692 | F9: =IFERROR(COUNTIFS(DONNEES!$H$2:$H$1501,"NOTABLE",DONNEES!$L$2:$L$1501,"Correct",DONNEES!$E$2:$E$1501,$A9,DONNEES!$C$2:$C$1501,5)/(COUNTIFS(DONNEES!$H$2:$H$1501,"NOTABLE",DONNEES!$L$2:$L$1501,"Correct",DONNEES!$E$2:$E$1501,$A9,DONNEES!$C$2:$C$1501,5)+COUNTIFS(DONNEES!$H$2:$H$1501,"NOTABLE",DONNEES!$L$2:$L$1501,"Pas d’info à tort",DONNEES!$E$2:$E$1501,$A9,DONNEES!$C$2:$C$1501,5)+COUNTIFS(DONNEES!$H$2:$H$1501,"NOTABLE",DONNEES!$L$2:$L$1501,"Incorrect",DONNEES!$E$2:$E$1501,$A9,DONNEES!$C$2:$C$1501,5)+COUNTIFS(DONNEES!$H$2:$H$1501,"NOTABLE",DONNEES!$L$2:$L$1501,"Hors sujet",DONNEES!$E$2:$E$1501,$A9,DONNEES!$C$2:$C$1501,5)),"") -> 0.92307692 | G9: =IFERROR(COUNTIFS(DONNEES!$H$2:$H$1501,"NOTABLE",DONNEES!$L$2:$L$1501,"Correct",DONNEES!$E$2:$E$1501,$A9)/(COUNTIFS(DONNEES!$H$2:$H$1501,"NOTABLE",DONNEES!$L$2:$L$1501,"Correct",DONNEES!$E$2:$E$1501,$A9)+COUNTIFS(DONNEES!$H$2:$H$1501,"NOTABLE",DONNEES!$L$2:$L$1501,"Pas d’info à tort",DONNEES!$E$2:$E$1501,$A9)+COUNTIFS(DONNEES!$H$2:$H$1501,"NOTABLE",DONNEES!$L$2:$L$1501,"Incorrect",DONNEES!$E$2:$E$1501,$A9)+COUNTIFS(DONNEES!$H$2:$H$1501,"NOTABLE",DONNEES!$L$2:$L$1501,"Hors sujet",DONNEES!$E$2:$E$1501,$A9)),"") -> 0.83544304
A10: Juridique et réglementaire | B10: =IFERROR(COUNTIFS(DONNEES!$H$2:$H$1501,"NOTABLE",DONNEES!$L$2:$L$1501,"Correct",DONNEES!$E$2:$E$1501,$A10,DONNEES!$C$2:$C$1501,1)/(COUNTIFS(DONNEES!$H$2:$H$1501,"NOTABLE",DONNEES!$L$2:$L$1501,"Correct",DONNEES!$E$2:$E$1501,$A10,DONNEES!$C$2:$C$1501,1)+COUNTIFS(DONNEES!$H$2:$H$1501,"NOTABLE",DONNEES!$L$2:$L$1501,"Pas d’info à tort",DONNEES!$E$2:$E$1501,$A10,DONNEES!$C$2:$C$1501,1)+COUNTIFS(DONNEES!$H$2:$H$1501,"NOTABLE",DONNEES!$L$2:$L$1501,"Incorrect",DONNEES!$E$2:$E$1501,$A10,DONNEES!$C$2:$C$1501,1)+COUNTIFS(DONNEES!$H$2:$H$1501,"NOTABLE",DONNEES!$L$2:$L$1501,"Hors sujet",DONNEES!$E$2:$E$1501,$A10,DONNEES!$C$2:$C$1501,1)),"") -> 0.83333333 | C10: =IFERROR(COUNTIFS(DONNEES!$H$2:$H$1501,"NOTABLE",DONNEES!$L$2:$L$1501,"Correct",DONNEES!$E$2:$E$1501,$A10,DONNEES!$C$2:$C$1501,2)/(COUNTIFS(DONNEES!$H$2:$H$1501,"NOTABLE",DONNEES!$L$2:$L$1501,"Correct",DONNEES!$E$2:$E$1501,$A10,DONNEES!$C$2:$C$1501,2)+COUNTIFS(DONNEES!$H$2:$H$1501,"NOTABLE",DONNEES!$L$2:$L$1501,"Pas d’info à tort",DONNEES!$E$2:$E$1501,$A10,DONNEES!$C$2:$C$1501,2)+COUNTIFS(DONNEES!$H$2:$H$1501,"NOTABLE",DONNEES!$L$2:$L$1501,"Incorrect",DONNEES!$E$2:$E$1501,$A10,DONNEES!$C$2:$C$1501,2)+COUNTIFS(DONNEES!$H$2:$H$1501,"NOTABLE",DONNEES!$L$2:$L$1501,"Hors sujet",DONNEES!$E$2:$E$1501,$A10,DONNEES!$C$2:$C$1501,2)),"") -> 0.88888889 | D10: =IFERROR(COUNTIFS(DONNEES!$H$2:$H$1501,"NOTABLE",DONNEES!$L$2:$L$1501,"Correct",DONNEES!$E$2:$E$1501,$A10,DONNEES!$C$2:$C$1501,3)/(COUNTIFS(DONNEES!$H$2:$H$1501,"NOTABLE",DONNEES!$L$2:$L$1501,"Correct",DONNEES!$E$2:$E$1501,$A10,DONNEES!$C$2:$C$1501,3)+COUNTIFS(DONNEES!$H$2:$H$1501,"NOTABLE",DONNEES!$L$2:$L$1501,"Pas d’info à tort",DONNEES!$E$2:$E$1501,$A10,DONNEES!$C$2:$C$1501,3)+COUNTIFS(DONNEES!$H$2:$H$1501,"NOTABLE",DONNEES!$L$2:$L$1501,"Incorrect",DONNEES!$E$2:$E$1501,$A10,DONNEES!$C$2:$C$1501,3)+COUNTIFS(DONNEES!$H$2:$H$1501,"NOTABLE",DONNEES!$L$2:$L$1501,"Hors sujet",DONNEES!$E$2:$E$1501,$A10,DONNEES!$C$2:$C$1501,3)),"") -> 0.87096774 | E10: =IFERROR(COUNTIFS(DONNEES!$H$2:$H$1501,"NOTABLE",DONNEES!$L$2:$L$1501,"Correct",DONNEES!$E$2:$E$1501,$A10,DONNEES!$C$2:$C$1501,4)/(COUNTIFS(DONNEES!$H$2:$H$1501,"NOTABLE",DONNEES!$L$2:$L$1501,"Correct",DONNEES!$E$2:$E$1501,$A10,DONNEES!$C$2:$C$1501,4)+COUNTIFS(DONNEES!$H$2:$H$1501,"NOTABLE",DONNEES!$L$2:$L$1501,"Pas d’info à tort",DONNEES!$E$2:$E$1501,$A10,DONNEES!$C$2:$C$1501,4)+COUNTIFS(DONNEES!$H$2:$H$1501,"NOTABLE",DONNEES!$L$2:$L$1501,"Incorrect",DONNEES!$E$2:$E$1501,$A10,DONNEES!$C$2:$C$1501,4)+COUNTIFS(DONNEES!$H$2:$H$1501,"NOTABLE",DONNEES!$L$2:$L$1501,"Hors sujet",DONNEES!$E$2:$E$1501,$A10,DONNEES!$C$2:$C$1501,4)),"") -> 0.92592593 | F10: =IFERROR(COUNTIFS(DONNEES!$H$2:$H$1501,"NOTABLE",DONNEES!$L$2:$L$1501,"Correct",DONNEES!$E$2:$E$1501,$A10,DONNEES!$C$2:$C$1501,5)/(COUNTIFS(DONNEES!$H$2:$H$1501,"NOTABLE",DONNEES!$L$2:$L$1501,"Correct",DONNEES!$E$2:$E$1501,$A10,DONNEES!$C$2:$C$1501,5)+COUNTIFS(DONNEES!$H$2:$H$1501,"NOTABLE",DONNEES!$L$2:$L$1501,"Pas d’info à tort",DONNEES!$E$2:$E$1501,$A10,DONNEES!$C$2:$C$1501,5)+COUNTIFS(DONNEES!$H$2:$H$1501,"NOTABLE",DONNEES!$L$2:$L$1501,"Incorrect",DONNEES!$E$2:$E$1501,$A10,DONNEES!$C$2:$C$1501,5)+COUNTIFS(DONNEES!$H$2:$H$1501,"NOTABLE",DONNEES!$L$2:$L$1501,"Hors sujet",DONNEES!$E$2:$E$1501,$A10,DONNEES!$C$2:$C$1501,5)),"") -> 0.82222222 | G10: =IFERROR(COUNTIFS(DONNEES!$H$2:$H$1501,"NOTABLE",DONNEES!$L$2:$L$1501,"Correct",DONNEES!$E$2:$E$1501,$A10)/(COUNTIFS(DONNEES!$H$2:$H$1501,"NOTABLE",DONNEES!$L$2:$L$1501,"Correct",DONNEES!$E$2:$E$1501,$A10)+COUNTIFS(DONNEES!$H$2:$H$1501,"NOTABLE",DONNEES!$L$2:$L$1501,"Pas d’info à tort",DONNEES!$E$2:$E$1501,$A10)+COUNTIFS(DONNEES!$H$2:$H$1501,"NOTABLE",DONNEES!$L$2:$L$1501,"Incorrect",DONNEES!$E$2:$E$1501,$A10)+COUNTIFS(DONNEES!$H$2:$H$1501,"NOTABLE",DONNEES!$L$2:$L$1501,"Hors sujet",DONNEES!$E$2:$E$1501,$A10)),"") -> 0.86627907
A11: Autres | B11: =IFERROR(COUNTIFS(DONNEES!$H$2:$H$1501,"NOTABLE",DONNEES!$L$2:$L$1501,"Correct",DONNEES!$E$2:$E$1501,$A11,DONNEES!$C$2:$C$1501,1)/(COUNTIFS(DONNEES!$H$2:$H$1501,"NOTABLE",DONNEES!$L$2:$L$1501,"Correct",DONNEES!$E$2:$E$1501,$A11,DONNEES!$C$2:$C$1501,1)+COUNTIFS(DONNEES!$H$2:$H$1501,"NOTABLE",DONNEES!$L$2:$L$1501,"Pas d’info à tort",DONNEES!$E$2:$E$1501,$A11,DONNEES!$C$2:$C$1501,1)+COUNTIFS(DONNEES!$H$2:$H$1501,"NOTABLE",DONNEES!$L$2:$L$1501,"Incorrect",DONNEES!$E$2:$E$1501,$A11,DONNEES!$C$2:$C$1501,1)+COUNTIFS(DONNEES!$H$2:$H$1501,"NOTABLE",DONNEES!$L$2:$L$1501,"Hors sujet",DONNEES!$E$2:$E$1501,$A11,DONNEES!$C$2:$C$1501,1)),"") -> 0.78571429 | C11: =IFERROR(COUNTIFS(DONNEES!$H$2:$H$1501,"NOTABLE",DONNEES!$L$2:$L$1501,"Correct",DONNEES!$E$2:$E$1501,$A11,DONNEES!$C$2:$C$1501,2)/(COUNTIFS(DONNEES!$H$2:$H$1501,"NOTABLE",DONNEES!$L$2:$L$1501,"Correct",DONNEES!$E$2:$E$1501,$A11,DONNEES!$C$2:$C$1501,2)+COUNTIFS(DONNEES!$H$2:$H$1501,"NOTABLE",DONNEES!$L$2:$L$1501,"Pas d’info à tort",DONNEES!$E$2:$E$1501,$A11,DONNEES!$C$2:$C$1501,2)+COUNTIFS(DONNEES!$H$2:$H$1501,"NOTABLE",DONNEES!$L$2:$L$1501,"Incorrect",DONNEES!$E$2:$E$1501,$A11,DONNEES!$C$2:$C$1501,2)+COUNTIFS(DONNEES!$H$2:$H$1501,"NOTABLE",DONNEES!$L$2:$L$1501,"Hors sujet",DONNEES!$E$2:$E$1501,$A11,DONNEES!$C$2:$C$1501,2)),"") -> 0.89473684 | D11: =IFERROR(COUNTIFS(DONNEES!$H$2:$H$1501,"NOTABLE",DONNEES!$L$2:$L$1501,"Correct",DONNEES!$E$2:$E$1501,$A11,DONNEES!$C$2:$C$1501,3)/(COUNTIFS(DONNEES!$H$2:$H$1501,"NOTABLE",DONNEES!$L$2:$L$1501,"Correct",DONNEES!$E$2:$E$1501,$A11,DONNEES!$C$2:$C$1501,3)+COUNTIFS(DONNEES!$H$2:$H$1501,"NOTABLE",DONNEES!$L$2:$L$1501,"Pas d’info à tort",DONNEES!$E$2:$E$1501,$A11,DONNEES!$C$2:$C$1501,3)+COUNTIFS(DONNEES!$H$2:$H$1501,"NOTABLE",DONNEES!$L$2:$L$1501,"Incorrect",DONNEES!$E$2:$E$1501,$A11,DONNEES!$C$2:$C$1501,3)+COUNTIFS(DONNEES!$H$2:$H$1501,"NOTABLE",DONNEES!$L$2:$L$1501,"Hors sujet",DONNEES!$E$2:$E$1501,$A11,DONNEES!$C$2:$C$1501,3)),"") -> 0.57142857 | E11: =IFERROR(COUNTIFS(DONNEES!$H$2:$H$1501,"NOTABLE",DONNEES!$L$2:$L$1501,"Correct",DONNEES!$E$2:$E$1501,$A11,DONNEES!$C$2:$C$1501,4)/(COUNTIFS(DONNEES!$H$2:$H$1501,"NOTABLE",DONNEES!$L$2:$L$1501,"Correct",DONNEES!$E$2:$E$1501,$A11,DONNEES!$C$2:$C$1501,4)+COUNTIFS(DONNEES!$H$2:$H$1501,"NOTABLE",DONNEES!$L$2:$L$1501,"Pas d’info à tort",DONNEES!$E$2:$E$1501,$A11,DONNEES!$C$2:$C$1501,4)+COUNTIFS(DONNEES!$H$2:$H$1501,"NOTABLE",DONNEES!$L$2:$L$1501,"Incorrect",DONNEES!$E$2:$E$1501,$A11,DONNEES!$C$2:$C$1501,4)+COUNTIFS(DONNEES!$H$2:$H$1501,"NOTABLE",DONNEES!$L$2:$L$1501,"Hors sujet",DONNEES!$E$2:$E$1501,$A11,DONNEES!$C$2:$C$1501,4)),"") -> 1 | F11: =IFERROR(COUNTIFS(DONNEES!$H$2:$H$1501,"NOTABLE",DONNEES!$L$2:$L$1501,"Correct",DONNEES!$E$2:$E$1501,$A11,DONNEES!$C$2:$C$1501,5)/(COUNTIFS(DONNEES!$H$2:$H$1501,"NOTABLE",DONNEES!$L$2:$L$1501,"Correct",DONNEES!$E$2:$E$1501,$A11,DONNEES!$C$2:$C$1501,5)+COUNTIFS(DONNEES!$H$2:$H$1501,"NOTABLE",DONNEES!$L$2:$L$1501,"Pas d’info à tort",DONNEES!$E$2:$E$1501,$A11,DONNEES!$C$2:$C$1501,5)+COUNTIFS(DONNEES!$H$2:$H$1501,"NOTABLE",DONNEES!$L$2:$L$1501,"Incorrect",DONNEES!$E$2:$E$1501,$A11,DONNEES!$C$2:$C$1501,5)+COUNTIFS(DONNEES!$H$2:$H$1501,"NOTABLE",DONNEES!$L$2:$L$1501,"Hors sujet",DONNEES!$E$2:$E$1501,$A11,DONNEES!$C$2:$C$1501,5)),"") -> 0.91666667 | G11: =IFERROR(COUNTIFS(DONNEES!$H$2:$H$1501,"NOTABLE",DONNEES!$L$2:$L$1501,"Correct",DONNEES!$E$2:$E$1501,$A11)/(COUNTIFS(DONNEES!$H$2:$H$1501,"NOTABLE",DONNEES!$L$2:$L$1501,"Correct",DONNEES!$E$2:$E$1501,$A11)+COUNTIFS(DONNEES!$H$2:$H$1501,"NOTABLE",DONNEES!$L$2:$L$1501,"Pas d’info à tort",DONNEES!$E$2:$E$1501,$A11)+COUNTIFS(DONNEES!$H$2:$H$1501,"NOTABLE",DONNEES!$L$2:$L$1501,"Incorrect",DONNEES!$E$2:$E$1501,$A11)+COUNTIFS(DONNEES!$H$2:$H$1501,"NOTABLE",DONNEES!$L$2:$L$1501,"Hors sujet",DONNEES!$E$2:$E$1501,$A11)),"") -> 0.86764706
A12: Intervenants | B12: =IFERROR(COUNTIFS(DONNEES!$H$2:$H$1501,"NOTABLE",DONNEES!$L$2:$L$1501,"Correct",DONNEES!$E$2:$E$1501,$A12,DONNEES!$C$2:$C$1501,1)/(COUNTIFS(DONNEES!$H$2:$H$1501,"NOTABLE",DONNEES!$L$2:$L$1501,"Correct",DONNEES!$E$2:$E$1501,$A12,DONNEES!$C$2:$C$1501,1)+COUNTIFS(DONNEES!$H$2:$H$1501,"NOTABLE",DONNEES!$L$2:$L$1501,"Pas d’info à tort",DONNEES!$E$2:$E$1501,$A12,DONNEES!$C$2:$C$1501,1)+COUNTIFS(DONNEES!$H$2:$H$1501,"NOTABLE",DONNEES!$L$2:$L$1501,"Incorrect",DONNEES!$E$2:$E$1501,$A12,DONNEES!$C$2:$C$1501,1)+COUNTIFS(DONNEES!$H$2:$H$1501,"NOTABLE",DONNEES!$L$2:$L$1501,"Hors sujet",DONNEES!$E$2:$E$1501,$A12,DONNEES!$C$2:$C$1501,1)),"") -> 0.81578947 | C12: =IFERROR(COUNTIFS(DONNEES!$H$2:$H$1501,"NOTABLE",DONNEES!$L$2:$L$1501,"Correct",DONNEES!$E$2:$E$1501,$A12,DONNEES!$C$2:$C$1501,2)/(COUNTIFS(DONNEES!$H$2:$H$1501,"NOTABLE",DONNEES!$L$2:$L$1501,"Correct",DONNEES!$E$2:$E$1501,$A12,DONNEES!$C$2:$C$1501,2)+COUNTIFS(DONNEES!$H$2:$H$1501,"NOTABLE",DONNEES!$L$2:$L$1501,"Pas d’info à tort",DONNEES!$E$2:$E$1501,$A12,DONNEES!$C$2:$C$1501,2)+COUNTIFS(DONNEES!$H$2:$H$1501,"NOTABLE",DONNEES!$L$2:$L$1501,"Incorrect",DONNEES!$E$2:$E$1501,$A12,DONNEES!$C$2:$C$1501,2)+COUNTIFS(DONNEES!$H$2:$H$1501,"NOTABLE",DONNEES!$L$2:$L$1501,"Hors sujet",DONNEES!$E$2:$E$1501,$A12,DONNEES!$C$2:$C$1501,2)),"") -> 0.80487805 | D12: =IFERROR(COUNTIFS(DONNEES!$H$2:$H$1501,"NOTABLE",DONNEES!$L$2:$L$1501,"Correct",DONNEES!$E$2:$E$1501,$A12,DONNEES!$C$2:$C$1501,3)/(COUNTIFS(DONNEES!$H$2:$H$1501,"NOTABLE",DONNEES!$L$2:$L$1501,"Correct",DONNEES!$E$2:$E$1501,$A12,DONNEES!$C$2:$C$1501,3)+COUNTIFS(DONNEES!$H$2:$H$1501,"NOTABLE",DONNEES!$L$2:$L$1501,"Pas d’info à tort",DONNEES!$E$2:$E$1501,$A12,DONNEES!$C$2:$C$1501,3)+COUNTIFS(DONNEES!$H$2:$H$1501,"NOTABLE",DONNEES!$L$2:$L$1501,"Incorrect",DONNEES!$E$2:$E$1501,$A12,DONNEES!$C$2:$C$1501,3)+COUNTIFS(DONNEES!$H$2:$H$1501,"NOTABLE",DONNEES!$L$2:$L$1501,"Hors sujet",DONNEES!$E$2:$E$1501,$A12,DONNEES!$C$2:$C$1501,3)),"") -> 0.86486486 | E12: =IFERROR(COUNTIFS(DONNEES!$H$2:$H$1501,"NOTABLE",DONNEES!$L$2:$L$1501,"Correct",DONNEES!$E$2:$E$1501,$A12,DONNEES!$C$2:$C$1501,4)/(COUNTIFS(DONNEES!$H$2:$H$1501,"NOTABLE",DONNEES!$L$2:$L$1501,"Correct",DONNEES!$E$2:$E$1501,$A12,DONNEES!$C$2:$C$1501,4)+COUNTIFS(DONNEES!$H$2:$H$1501,"NOTABLE",DONNEES!$L$2:$L$1501,"Pas d’info à tort",DONNEES!$E$2:$E$1501,$A12,DONNEES!$C$2:$C$1501,4)+COUNTIFS(DONNEES!$H$2:$H$1501,"NOTABLE",DONNEES!$L$2:$L$1501,"Incorrect",DONNEES!$E$2:$E$1501,$A12,DONNEES!$C$2:$C$1501,4)+COUNTIFS(DONNEES!$H$2:$H$1501,"NOTABLE",DONNEES!$L$2:$L$1501,"Hors sujet",DONNEES!$E$2:$E$1501,$A12,DONNEES!$C$2:$C$1501,4)),"") -> 0.92857143 | F12: =IFERROR(COUNTIFS(DONNEES!$H$2:$H$1501,"NOTABLE",DONNEES!$L$2:$L$1501,"Correct",DONNEES!$E$2:$E$1501,$A12,DONNEES!$C$2:$C$1501,5)/(COUNTIFS(DONNEES!$H$2:$H$1501,"NOTABLE",DONNEES!$L$2:$L$1501,"Correct",DONNEES!$E$2:$E$1501,$A12,DONNEES!$C$2:$C$1501,5)+COUNTIFS(DONNEES!$H$2:$H$1501,"NOTABLE",DONNEES!$L$2:$L$1501,"Pas d’info à tort",DONNEES!$E$2:$E$1501,$A12,DONNEES!$C$2:$C$1501,5)+COUNTIFS(DONNEES!$H$2:$H$1501,"NOTABLE",DONNEES!$L$2:$L$1501,"Incorrect",DONNEES!$E$2:$E$1501,$A12,DONNEES!$C$2:$C$1501,5)+COUNTIFS(DONNEES!$H$2:$H$1501,"NOTABLE",DONNEES!$L$2:$L$1501,"Hors sujet",DONNEES!$E$2:$E$1501,$A12,DONNEES!$C$2:$C$1501,5)),"") -> 1 | G12: =IFERROR(COUNTIFS(DONNEES!$H$2:$H$1501,"NOTABLE",DONNEES!$L$2:$L$1501,"Correct",DONNEES!$E$2:$E$1501,$A12)/(COUNTIFS(DONNEES!$H$2:$H$1501,"NOTABLE",DONNEES!$L$2:$L$1501,"Correct",DONNEES!$E$2:$E$1501,$A12)+COUNTIFS(DONNEES!$H$2:$H$1501,"NOTABLE",DONNEES!$L$2:$L$1501,"Pas d’info à tort",DONNEES!$E$2:$E$1501,$A12)+COUNTIFS(DONNEES!$H$2:$H$1501,"NOTABLE",DONNEES!$L$2:$L$1501,"Incorrect",DONNEES!$E$2:$E$1501,$A12)+COUNTIFS(DONNEES!$H$2:$H$1501,"NOTABLE",DONNEES!$L$2:$L$1501,"Hors sujet",DONNEES!$E$2:$E$1501,$A12)),"") -> 0.88172043
A13: Dates et VL | B13: =IFERROR(COUNTIFS(DONNEES!$H$2:$H$1501,"NOTABLE",DONNEES!$L$2:$L$1501,"Correct",DONNEES!$E$2:$E$1501,$A13,DONNEES!$C$2:$C$1501,1)/(COUNTIFS(DONNEES!$H$2:$H$1501,"NOTABLE",DONNEES!$L$2:$L$1501,"Correct",DONNEES!$E$2:$E$1501,$A13,DONNEES!$C$2:$C$1501,1)+COUNTIFS(DONNEES!$H$2:$H$1501,"NOTABLE",DONNEES!$L$2:$L$1501,"Pas d’info à tort",DONNEES!$E$2:$E$1501,$A13,DONNEES!$C$2:$C$1501,1)+COUNTIFS(DONNEES!$H$2:$H$1501,"NOTABLE",DONNEES!$L$2:$L$1501,"Incorrect",DONNEES!$E$2:$E$1501,$A13,DONNEES!$C$2:$C$1501,1)+COUNTIFS(DONNEES!$H$2:$H$1501,"NOTABLE",DONNEES!$L$2:$L$1501,"Hors sujet",DONNEES!$E$2:$E$1501,$A13,DONNEES!$C$2:$C$1501,1)),"") -> 0.83333333 | C13: =IFERROR(COUNTIFS(DONNEES!$H$2:$H$1501,"NOTABLE",DONNEES!$L$2:$L$1501,"Correct",DONNEES!$E$2:$E$1501,$A13,DONNEES!$C$2:$C$1501,2)/(COUNTIFS(DONNEES!$H$2:$H$1501,"NOTABLE",DONNEES!$L$2:$L$1501,"Correct",DONNEES!$E$2:$E$1501,$A13,DONNEES!$C$2:$C$1501,2)+COUNTIFS(DONNEES!$H$2:$H$1501,"NOTABLE",DONNEES!$L$2:$L$1501,"Pas d’info à tort",DONNEES!$E$2:$E$1501,$A13,DONNEES!$C$2:$C$1501,2)+COUNTIFS(DONNEES!$H$2:$H$1501,"NOTABLE",DONNEES!$L$2:$L$1501,"Incorrect",DONNEES!$E$2:$E$1501,$A13,DONNEES!$C$2:$C$1501,2)+COUNTIFS(DONNEES!$H$2:$H$1501,"NOTABLE",DONNEES!$L$2:$L$1501,"Hors sujet",DONNEES!$E$2:$E$1501,$A13,DONNEES!$C$2:$C$1501,2)),"") -> 1 | D13: =IFERROR(COUNTIFS(DONNEES!$H$2:$H$1501,"NOTABLE",DONNEES!$L$2:$L$1501,"Correct",DONNEES!$E$2:$E$1501,$A13,DONNEES!$C$2:$C$1501,3)/(COUNTIFS(DONNEES!$H$2:$H$1501,"NOTABLE",DONNEES!$L$2:$L$1501,"Correct",DONNEES!$E$2:$E$1501,$A13,DONNEES!$C$2:$C$1501,3)+COUNTIFS(DONNEES!$H$2:$H$1501,"NOTABLE",DONNEES!$L$2:$L$1501,"Pas d’info à tort",DONNEES!$E$2:$E$1501,$A13,DONNEES!$C$2:$C$1501,3)+COUNTIFS(DONNEES!$H$2:$H$1501,"NOTABLE",DONNEES!$L$2:$L$1501,"Incorrect",DONNEES!$E$2:$E$1501,$A13,DONNEES!$C$2:$C$1501,3)+COUNTIFS(DONNEES!$H$2:$H$1501,"NOTABLE",DONNEES!$L$2:$L$1501,"Hors sujet",DONNEES!$E$2:$E$1501,$A13,DONNEES!$C$2:$C$1501,3)),"") -> 1 | E13: =IFERROR(COUNTIFS(DONNEES!$H$2:$H$1501,"NOTABLE",DONNEES!$L$2:$L$1501,"Correct",DONNEES!$E$2:$E$1501,$A13,DONNEES!$C$2:$C$1501,4)/(COUNTIFS(DONNEES!$H$2:$H$1501,"NOTABLE",DONNEES!$L$2:$L$1501,"Correct",DONNEES!$E$2:$E$1501,$A13,DONNEES!$C$2:$C$1501,4)+COUNTIFS(DONNEES!$H$2:$H$1501,"NOTABLE",DONNEES!$L$2:$L$1501,"Pas d’info à tort",DONNEES!$E$2:$E$1501,$A13,DONNEES!$C$2:$C$1501,4)+COUNTIFS(DONNEES!$H$2:$H$1501,"NOTABLE",DONNEES!$L$2:$L$1501,"Incorrect",DONNEES!$E$2:$E$1501,$A13,DONNEES!$C$2:$C$1501,4)+COUNTIFS(DONNEES!$H$2:$H$1501,"NOTABLE",DONNEES!$L$2:$L$1501,"Hors sujet",DONNEES!$E$2:$E$1501,$A13,DONNEES!$C$2:$C$1501,4)),"") -> 0.76923077 | F13: =IFERROR(COUNTIFS(DONNEES!$H$2:$H$1501,"NOTABLE",DONNEES!$L$2:$L$1501,"Correct",DONNEES!$E$2:$E$1501,$A13,DONNEES!$C$2:$C$1501,5)/(COUNTIFS(DONNEES!$H$2:$H$1501,"NOTABLE",DONNEES!$L$2:$L$1501,"Correct",DONNEES!$E$2:$E$1501,$A13,DONNEES!$C$2:$C$1501,5)+COUNTIFS(DONNEES!$H$2:$H$1501,"NOTABLE",DONNEES!$L$2:$L$1501,"Pas d’info à tort",DONNEES!$E$2:$E$1501,$A13,DONNEES!$C$2:$C$1501,5)+COUNTIFS(DONNEES!$H$2:$H$1501,"NOTABLE",DONNEES!$L$2:$L$1501,"Incorrect",DONNEES!$E$2:$E$1501,$A13,DONNEES!$C$2:$C$1501,5)+COUNTIFS(DONNEES!$H$2:$H$1501,"NOTABLE",DONNEES!$L$2:$L$1501,"Hors sujet",DONNEES!$E$2:$E$1501,$A13,DONNEES!$C$2:$C$1501,5)),"") -> 0.94117647 | G13: =IFERROR(COUNTIFS(DONNEES!$H$2:$H$1501,"NOTABLE",DONNEES!$L$2:$L$1501,"Correct",DONNEES!$E$2:$E$1501,$A13)/(COUNTIFS(DONNEES!$H$2:$H$1501,"NOTABLE",DONNEES!$L$2:$L$1501,"Correct",DONNEES!$E$2:$E$1501,$A13)+COUNTIFS(DONNEES!$H$2:$H$1501,"NOTABLE",DONNEES!$L$2:$L$1501,"Pas d’info à tort",DONNEES!$E$2:$E$1501,$A13)+COUNTIFS(DONNEES!$H$2:$H$1501,"NOTABLE",DONNEES!$L$2:$L$1501,"Incorrect",DONNEES!$E$2:$E$1501,$A13)+COUNTIFS(DONNEES!$H$2:$H$1501,"NOTABLE",DONNEES!$L$2:$L$1501,"Hors sujet",DONNEES!$E$2:$E$1501,$A13)),"") -> 0.88461538
A14: Identifiants | B14: =IFERROR(COUNTIFS(DONNEES!$H$2:$H$1501,"NOTABLE",DONNEES!$L$2:$L$1501,"Correct",DONNEES!$E$2:$E$1501,$A14,DONNEES!$C$2:$C$1501,1)/(COUNTIFS(DONNEES!$H$2:$H$1501,"NOTABLE",DONNEES!$L$2:$L$1501,"Correct",DONNEES!$E$2:$E$1501,$A14,DONNEES!$C$2:$C$1501,1)+COUNTIFS(DONNEES!$H$2:$H$1501,"NOTABLE",DONNEES!$L$2:$L$1501,"Pas d’info à tort",DONNEES!$E$2:$E$1501,$A14,DONNEES!$C$2:$C$1501,1)+COUNTIFS(DONNEES!$H$2:$H$1501,"NOTABLE",DONNEES!$L$2:$L$1501,"Incorrect",DONNEES!$E$2:$E$1501,$A14,DONNEES!$C$2:$C$1501,1)+COUNTIFS(DONNEES!$H$2:$H$1501,"NOTABLE",DONNEES!$L$2:$L$1501,"Hors sujet",DONNEES!$E$2:$E$1501,$A14,DONNEES!$C$2:$C$1501,1)),"") -> 0.75 | C14: =IFERROR(COUNTIFS(DONNEES!$H$2:$H$1501,"NOTABLE",DONNEES!$L$2:$L$1501,"Correct",DONNEES!$E$2:$E$1501,$A14,DONNEES!$C$2:$C$1501,2)/(COUNTIFS(DONNEES!$H$2:$H$1501,"NOTABLE",DONNEES!$L$2:$L$1501,"Correct",DONNEES!$E$2:$E$1501,$A14,DONNEES!$C$2:$C$1501,2)+COUNTIFS(DONNEES!$H$2:$H$1501,"NOTABLE",DONNEES!$L$2:$L$1501,"Pas d’info à tort",DONNEES!$E$2:$E$1501,$A14,DONNEES!$C$2:$C$1501,2)+COUNTIFS(DONNEES!$H$2:$H$1501,"NOTABLE",DONNEES!$L$2:$L$1501,"Incorrect",DONNEES!$E$2:$E$1501,$A14,DONNEES!$C$2:$C$1501,2)+COUNTIFS(DONNEES!$H$2:$H$1501,"NOTABLE",DONNEES!$L$2:$L$1501,"Hors sujet",DONNEES!$E$2:$E$1501,$A14,DONNEES!$C$2:$C$1501,2)),"") -> 1 | D14: =IFERROR(COUNTIFS(DONNEES!$H$2:$H$1501,"NOTABLE",DONNEES!$L$2:$L$1501,"Correct",DONNEES!$E$2:$E$1501,$A14,DONNEES!$C$2:$C$1501,3)/(COUNTIFS(DONNEES!$H$2:$H$1501,"NOTABLE",DONNEES!$L$2:$L$1501,"Correct",DONNEES!$E$2:$E$1501,$A14,DONNEES!$C$2:$C$1501,3)+COUNTIFS(DONNEES!$H$2:$H$1501,"NOTABLE",DONNEES!$L$2:$L$1501,"Pas d’info à tort",DONNEES!$E$2:$E$1501,$A14,DONNEES!$C$2:$C$1501,3)+COUNTIFS(DONNEES!$H$2:$H$1501,"NOTABLE",DONNEES!$L$2:$L$1501,"Incorrect",DONNEES!$E$2:$E$1501,$A14,DONNEES!$C$2:$C$1501,3)+COUNTIFS(DONNEES!$H$2:$H$1501,"NOTABLE",DONNEES!$L$2:$L$1501,"Hors sujet",DONNEES!$E$2:$E$1501,$A14,DONNEES!$C$2:$C$1501,3)),"") -> 1 | E14: =IFERROR(COUNTIFS(DONNEES!$H$2:$H$1501,"NOTABLE",DONNEES!$L$2:$L$1501,"Correct",DONNEES!$E$2:$E$1501,$A14,DONNEES!$C$2:$C$1501,4)/(COUNTIFS(DONNEES!$H$2:$H$1501,"NOTABLE",DONNEES!$L$2:$L$1501,"Correct",DONNEES!$E$2:$E$1501,$A14,DONNEES!$C$2:$C$1501,4)+COUNTIFS(DONNEES!$H$2:$H$1501,"NOTABLE",DONNEES!$L$2:$L$1501,"Pas d’info à tort",DONNEES!$E$2:$E$1501,$A14,DONNEES!$C$2:$C$1501,4)+COUNTIFS(DONNEES!$H$2:$H$1501,"NOTABLE",DONNEES!$L$2:$L$1501,"Incorrect",DONNEES!$E$2:$E$1501,$A14,DONNEES!$C$2:$C$1501,4)+COUNTIFS(DONNEES!$H$2:$H$1501,"NOTABLE",DONNEES!$L$2:$L$1501,"Hors sujet",DONNEES!$E$2:$E$1501,$A14,DONNEES!$C$2:$C$1501,4)),"") -> 0.8 | F14: =IFERROR(COUNTIFS(DONNEES!$H$2:$H$1501,"NOTABLE",DONNEES!$L$2:$L$1501,"Correct",DONNEES!$E$2:$E$1501,$A14,DONNEES!$C$2:$C$1501,5)/(COUNTIFS(DONNEES!$H$2:$H$1501,"NOTABLE",DONNEES!$L$2:$L$1501,"Correct",DONNEES!$E$2:$E$1501,$A14,DONNEES!$C$2:$C$1501,5)+COUNTIFS(DONNEES!$H$2:$H$1501,"NOTABLE",DONNEES!$L$2:$L$1501,"Pas d’info à tort",DONNEES!$E$2:$E$1501,$A14,DONNEES!$C$2:$C$1501,5)+COUNTIFS(DONNEES!$H$2:$H$1501,"NOTABLE",DONNEES!$L$2:$L$1501,"Incorrect",DONNEES!$E$2:$E$1501,$A14,DONNEES!$C$2:$C$1501,5)+COUNTIFS(DONNEES!$H$2:$H$1501,"NOTABLE",DONNEES!$L$2:$L$1501,"Hors sujet",DONNEES!$E$2:$E$1501,$A14,DONNEES!$C$2:$C$1501,5)),"") -> 1 | G14: =IFERROR(COUNTIFS(DONNEES!$H$2:$H$1501,"NOTABLE",DONNEES!$L$2:$L$1501,"Correct",DONNEES!$E$2:$E$1501,$A14)/(COUNTIFS(DONNEES!$H$2:$H$1501,"NOTABLE",DONNEES!$L$2:$L$1501,"Correct",DONNEES!$E$2:$E$1501,$A14)+COUNTIFS(DONNEES!$H$2:$H$1501,"NOTABLE",DONNEES!$L$2:$L$1501,"Pas d’info à tort",DONNEES!$E$2:$E$1501,$A14)+COUNTIFS(DONNEES!$H$2:$H$1501,"NOTABLE",DONNEES!$L$2:$L$1501,"Incorrect",DONNEES!$E$2:$E$1501,$A14)+COUNTIFS(DONNEES!$H$2:$H$1501,"NOTABLE",DONNEES!$L$2:$L$1501,"Hors sujet",DONNEES!$E$2:$E$1501,$A14)),"") -> 0.9047619
A15: Gérants et dates de gestion | B15: =IFERROR(COUNTIFS(DONNEES!$H$2:$H$1501,"NOTABLE",DONNEES!$L$2:$L$1501,"Correct",DONNEES!$E$2:$E$1501,$A15,DONNEES!$C$2:$C$1501,1)/(COUNTIFS(DONNEES!$H$2:$H$1501,"NOTABLE",DONNEES!$L$2:$L$1501,"Correct",DONNEES!$E$2:$E$1501,$A15,DONNEES!$C$2:$C$1501,1)+COUNTIFS(DONNEES!$H$2:$H$1501,"NOTABLE",DONNEES!$L$2:$L$1501,"Pas d’info à tort",DONNEES!$E$2:$E$1501,$A15,DONNEES!$C$2:$C$1501,1)+COUNTIFS(DONNEES!$H$2:$H$1501,"NOTABLE",DONNEES!$L$2:$L$1501,"Incorrect",DONNEES!$E$2:$E$1501,$A15,DONNEES!$C$2:$C$1501,1)+COUNTIFS(DONNEES!$H$2:$H$1501,"NOTABLE",DONNEES!$L$2:$L$1501,"Hors sujet",DONNEES!$E$2:$E$1501,$A15,DONNEES!$C$2:$C$1501,1)),"") -> 0.9375 | C15: =IFERROR(COUNTIFS(DONNEES!$H$2:$H$1501,"NOTABLE",DONNEES!$L$2:$L$1501,"Correct",DONNEES!$E$2:$E$1501,$A15,DONNEES!$C$2:$C$1501,2)/(COUNTIFS(DONNEES!$H$2:$H$1501,"NOTABLE",DONNEES!$L$2:$L$1501,"Correct",DONNEES!$E$2:$E$1501,$A15,DONNEES!$C$2:$C$1501,2)+COUNTIFS(DONNEES!$H$2:$H$1501,"NOTABLE",DONNEES!$L$2:$L$1501,"Pas d’info à tort",DONNEES!$E$2:$E$1501,$A15,DONNEES!$C$2:$C$1501,2)+COUNTIFS(DONNEES!$H$2:$H$1501,"NOTABLE",DONNEES!$L$2:$L$1501,"Incorrect",DONNEES!$E$2:$E$1501,$A15,DONNEES!$C$2:$C$1501,2)+COUNTIFS(DONNEES!$H$2:$H$1501,"NOTABLE",DONNEES!$L$2:$L$1501,"Hors sujet",DONNEES!$E$2:$E$1501,$A15,DONNEES!$C$2:$C$1501,2)),"") -> 0.93333333 | D15: =IFERROR(COUNTIFS(DONNEES!$H$2:$H$1501,"NOTABLE",DONNEES!$L$2:$L$1501,"Correct",DONNEES!$E$2:$E$1501,$A15,DONNEES!$C$2:$C$1501,3)/(COUNTIFS(DONNEES!$H$2:$H$1501,"NOTABLE",DONNEES!$L$2:$L$1501,"Correct",DONNEES!$E$2:$E$1501,$A15,DONNEES!$C$2:$C$1501,3)+COUNTIFS(DONNEES!$H$2:$H$1501,"NOTABLE",DONNEES!$L$2:$L$1501,"Pas d’info à tort",DONNEES!$E$2:$E$1501,$A15,DONNEES!$C$2:$C$1501,3)+COUNTIFS(DONNEES!$H$2:$H$1501,"NOTABLE",DONNEES!$L$2:$L$1501,"Incorrect",DONNEES!$E$2:$E$1501,$A15,DONNEES!$C$2:$C$1501,3)+COUNTIFS(DONNEES!$H$2:$H$1501,"NOTABLE",DONNEES!$L$2:$L$1501,"Hors sujet",DONNEES!$E$2:$E$1501,$A15,DONNEES!$C$2:$C$1501,3)),"") -> 0.91666667 | E15: =IFERROR(COUNTIFS(DONNEES!$H$2:$H$1501,"NOTABLE",DONNEES!$L$2:$L$1501,"Correct",DONNEES!$E$2:$E$1501,$A15,DONNEES!$C$2:$C$1501,4)/(COUNTIFS(DONNEES!$H$2:$H$1501,"NOTABLE",DONNEES!$L$2:$L$1501,"Correct",DONNEES!$E$2:$E$1501,$A15,DONNEES!$C$2:$C$1501,4)+COUNTIFS(DONNEES!$H$2:$H$1501,"NOTABLE",DONNEES!$L$2:$L$1501,"Pas d’info à tort",DONNEES!$E$2:$E$1501,$A15,DONNEES!$C$2:$C$1501,4)+COUNTIFS(DONNEES!$H$2:$H$1501,"NOTABLE",DONNEES!$L$2:$L$1501,"Incorrect",DONNEES!$E$2:$E$1501,$A15,DONNEES!$C$2:$C$1501,4)+COUNTIFS(DONNEES!$H$2:$H$1501,"NOTABLE",DONNEES!$L$2:$L$1501,"Hors sujet",DONNEES!$E$2:$E$1501,$A15,DONNEES!$C$2:$C$1501,4)),"") -> 1 | F15: =IFERROR(COUNTIFS(DONNEES!$H$2:$H$1501,"NOTABLE",DONNEES!$L$2:$L$1501,"Correct",DONNEES!$E$2:$E$1501,$A15,DONNEES!$C$2:$C$1501,5)/(COUNTIFS(DONNEES!$H$2:$H$1501,"NOTABLE",DONNEES!$L$2:$L$1501,"Correct",DONNEES!$E$2:$E$1501,$A15,DONNEES!$C$2:$C$1501,5)+COUNTIFS(DONNEES!$H$2:$H$1501,"NOTABLE",DONNEES!$L$2:$L$1501,"Pas d’info à tort",DONNEES!$E$2:$E$1501,$A15,DONNEES!$C$2:$C$1501,5)+COUNTIFS(DONNEES!$H$2:$H$1501,"NOTABLE",DONNEES!$L$2:$L$1501,"Incorrect",DONNEES!$E$2:$E$1501,$A15,DONNEES!$C$2:$C$1501,5)+COUNTIFS(DONNEES!$H$2:$H$1501,"NOTABLE",DONNEES!$L$2:$L$1501,"Hors sujet",DONNEES!$E$2:$E$1501,$A15,DONNEES!$C$2:$C$1501,5)),"") -> 0.75 | G15: =IFERROR(COUNTIFS(DONNEES!$H$2:$H$1501,"NOTABLE",DONNEES!$L$2:$L$1501,"Correct",DONNEES!$E$2:$E$1501,$A15)/(COUNTIFS(DONNEES!$H$2:$H$1501,"NOTABLE",DONNEES!$L$2:$L$1501,"Correct",DONNEES!$E$2:$E$1501,$A15)+COUNTIFS(DONNEES!$H$2:$H$1501,"NOTABLE",DONNEES!$L$2:$L$1501,"Pas d’info à tort",DONNEES!$E$2:$E$1501,$A15)+COUNTIFS(DONNEES!$H$2:$H$1501,"NOTABLE",DONNEES!$L$2:$L$1501,"Incorrect",DONNEES!$E$2:$E$1501,$A15)+COUNTIFS(DONNEES!$H$2:$H$1501,"NOTABLE",DONNEES!$L$2:$L$1501,"Hors sujet",DONNEES!$E$2:$E$1501,$A15)),"") -> 0.93181818
A17: Nombre de réponses par famille et par verdict (toutes questions)
A18: Famille \ Verdict | B18: Correct | C18: Pas d’info à tort | D18: Incorrect | E18: Hors sujet | F18: Abstention correcte | G18: Valeur sur cellule vide | H18: Échec technique | I18: Non capturé
A19: Risque | B19: =COUNTIFS(DONNEES!$E$2:$E$1501,$A19,DONNEES!$L$2:$L$1501,"Correct") -> 53 | C19: =COUNTIFS(DONNEES!$E$2:$E$1501,$A19,DONNEES!$L$2:$L$1501,"Pas d’info à tort") -> 56 | D19: =COUNTIFS(DONNEES!$E$2:$E$1501,$A19,DONNEES!$L$2:$L$1501,"Incorrect") -> 0 | E19: =COUNTIFS(DONNEES!$E$2:$E$1501,$A19,DONNEES!$L$2:$L$1501,"Hors sujet") -> 1 | F19: =COUNTIFS(DONNEES!$E$2:$E$1501,$A19,DONNEES!$L$2:$L$1501,"Abstention correcte") -> 0 | G19: =COUNTIFS(DONNEES!$E$2:$E$1501,$A19,DONNEES!$L$2:$L$1501,"Valeur sur cellule vide") -> 0 | H19: =COUNTIFS(DONNEES!$E$2:$E$1501,$A19,DONNEES!$L$2:$L$1501,"Échec technique") -> 0 | I19: =COUNTIFS(DONNEES!$E$2:$E$1501,$A19,DONNEES!$L$2:$L$1501,"Non capturé") -> 0
A20: ESG / EET | B20: =COUNTIFS(DONNEES!$E$2:$E$1501,$A20,DONNEES!$L$2:$L$1501,"Correct") -> 203 | C20: =COUNTIFS(DONNEES!$E$2:$E$1501,$A20,DONNEES!$L$2:$L$1501,"Pas d’info à tort") -> 38 | D20: =COUNTIFS(DONNEES!$E$2:$E$1501,$A20,DONNEES!$L$2:$L$1501,"Incorrect") -> 17 | E20: =COUNTIFS(DONNEES!$E$2:$E$1501,$A20,DONNEES!$L$2:$L$1501,"Hors sujet") -> 4 | F20: =COUNTIFS(DONNEES!$E$2:$E$1501,$A20,DONNEES!$L$2:$L$1501,"Abstention correcte") -> 5 | G20: =COUNTIFS(DONNEES!$E$2:$E$1501,$A20,DONNEES!$L$2:$L$1501,"Valeur sur cellule vide") -> 0 | H20: =COUNTIFS(DONNEES!$E$2:$E$1501,$A20,DONNEES!$L$2:$L$1501,"Échec technique") -> 0 | I20: =COUNTIFS(DONNEES!$E$2:$E$1501,$A20,DONNEES!$L$2:$L$1501,"Non capturé") -> 3
A21: Expertise et gamme | B21: =COUNTIFS(DONNEES!$E$2:$E$1501,$A21,DONNEES!$L$2:$L$1501,"Correct") -> 107 | C21: =COUNTIFS(DONNEES!$E$2:$E$1501,$A21,DONNEES!$L$2:$L$1501,"Pas d’info à tort") -> 22 | D21: =COUNTIFS(DONNEES!$E$2:$E$1501,$A21,DONNEES!$L$2:$L$1501,"Incorrect") -> 4 | E21: =COUNTIFS(DONNEES!$E$2:$E$1501,$A21,DONNEES!$L$2:$L$1501,"Hors sujet") -> 2 | F21: =COUNTIFS(DONNEES!$E$2:$E$1501,$A21,DONNEES!$L$2:$L$1501,"Abstention correcte") -> 0 | G21: =COUNTIFS(DONNEES!$E$2:$E$1501,$A21,DONNEES!$L$2:$L$1501,"Valeur sur cellule vide") -> 0 | H21: =COUNTIFS(DONNEES!$E$2:$E$1501,$A21,DONNEES!$L$2:$L$1501,"Échec technique") -> 0 | I21: =COUNTIFS(DONNEES!$E$2:$E$1501,$A21,DONNEES!$L$2:$L$1501,"Non capturé") -> 1
A22: Frais et coûts | B22: =COUNTIFS(DONNEES!$E$2:$E$1501,$A22,DONNEES!$L$2:$L$1501,"Correct") -> 159 | C22: =COUNTIFS(DONNEES!$E$2:$E$1501,$A22,DONNEES!$L$2:$L$1501,"Pas d’info à tort") -> 16 | D22: =COUNTIFS(DONNEES!$E$2:$E$1501,$A22,DONNEES!$L$2:$L$1501,"Incorrect") -> 14 | E22: =COUNTIFS(DONNEES!$E$2:$E$1501,$A22,DONNEES!$L$2:$L$1501,"Hors sujet") -> 5 | F22: =COUNTIFS(DONNEES!$E$2:$E$1501,$A22,DONNEES!$L$2:$L$1501,"Abstention correcte") -> 63 | G22: =COUNTIFS(DONNEES!$E$2:$E$1501,$A22,DONNEES!$L$2:$L$1501,"Valeur sur cellule vide") -> 2 | H22: =COUNTIFS(DONNEES!$E$2:$E$1501,$A22,DONNEES!$L$2:$L$1501,"Échec technique") -> 1 | I22: =COUNTIFS(DONNEES!$E$2:$E$1501,$A22,DONNEES!$L$2:$L$1501,"Non capturé") -> 0
A23: Textes longs | B23: =COUNTIFS(DONNEES!$E$2:$E$1501,$A23,DONNEES!$L$2:$L$1501,"Correct") -> 66 | C23: =COUNTIFS(DONNEES!$E$2:$E$1501,$A23,DONNEES!$L$2:$L$1501,"Pas d’info à tort") -> 11 | D23: =COUNTIFS(DONNEES!$E$2:$E$1501,$A23,DONNEES!$L$2:$L$1501,"Incorrect") -> 1 | E23: =COUNTIFS(DONNEES!$E$2:$E$1501,$A23,DONNEES!$L$2:$L$1501,"Hors sujet") -> 1 | F23: =COUNTIFS(DONNEES!$E$2:$E$1501,$A23,DONNEES!$L$2:$L$1501,"Abstention correcte") -> 1 | G23: =COUNTIFS(DONNEES!$E$2:$E$1501,$A23,DONNEES!$L$2:$L$1501,"Valeur sur cellule vide") -> 0 | H23: =COUNTIFS(DONNEES!$E$2:$E$1501,$A23,DONNEES!$L$2:$L$1501,"Échec technique") -> 0 | I23: =COUNTIFS(DONNEES!$E$2:$E$1501,$A23,DONNEES!$L$2:$L$1501,"Non capturé") -> 0
A24: Juridique et réglementaire | B24: =COUNTIFS(DONNEES!$E$2:$E$1501,$A24,DONNEES!$L$2:$L$1501,"Correct") -> 149 | C24: =COUNTIFS(DONNEES!$E$2:$E$1501,$A24,DONNEES!$L$2:$L$1501,"Pas d’info à tort") -> 13 | D24: =COUNTIFS(DONNEES!$E$2:$E$1501,$A24,DONNEES!$L$2:$L$1501,"Incorrect") -> 6 | E24: =COUNTIFS(DONNEES!$E$2:$E$1501,$A24,DONNEES!$L$2:$L$1501,"Hors sujet") -> 4 | F24: =COUNTIFS(DONNEES!$E$2:$E$1501,$A24,DONNEES!$L$2:$L$1501,"Abstention correcte") -> 0 | G24: =COUNTIFS(DONNEES!$E$2:$E$1501,$A24,DONNEES!$L$2:$L$1501,"Valeur sur cellule vide") -> 0 | H24: =COUNTIFS(DONNEES!$E$2:$E$1501,$A24,DONNEES!$L$2:$L$1501,"Échec technique") -> 1 | I24: =COUNTIFS(DONNEES!$E$2:$E$1501,$A24,DONNEES!$L$2:$L$1501,"Non capturé") -> 2
A25: Autres | B25: =COUNTIFS(DONNEES!$E$2:$E$1501,$A25,DONNEES!$L$2:$L$1501,"Correct") -> 59 | C25: =COUNTIFS(DONNEES!$E$2:$E$1501,$A25,DONNEES!$L$2:$L$1501,"Pas d’info à tort") -> 7 | D25: =COUNTIFS(DONNEES!$E$2:$E$1501,$A25,DONNEES!$L$2:$L$1501,"Incorrect") -> 1 | E25: =COUNTIFS(DONNEES!$E$2:$E$1501,$A25,DONNEES!$L$2:$L$1501,"Hors sujet") -> 1 | F25: =COUNTIFS(DONNEES!$E$2:$E$1501,$A25,DONNEES!$L$2:$L$1501,"Abstention correcte") -> 0 | G25: =COUNTIFS(DONNEES!$E$2:$E$1501,$A25,DONNEES!$L$2:$L$1501,"Valeur sur cellule vide") -> 0 | H25: =COUNTIFS(DONNEES!$E$2:$E$1501,$A25,DONNEES!$L$2:$L$1501,"Échec technique") -> 0 | I25: =COUNTIFS(DONNEES!$E$2:$E$1501,$A25,DONNEES!$L$2:$L$1501,"Non capturé") -> 0
A26: Intervenants | B26: =COUNTIFS(DONNEES!$E$2:$E$1501,$A26,DONNEES!$L$2:$L$1501,"Correct") -> 164 | C26: =COUNTIFS(DONNEES!$E$2:$E$1501,$A26,DONNEES!$L$2:$L$1501,"Pas d’info à tort") -> 15 | D26: =COUNTIFS(DONNEES!$E$2:$E$1501,$A26,DONNEES!$L$2:$L$1501,"Incorrect") -> 3 | E26: =COUNTIFS(DONNEES!$E$2:$E$1501,$A26,DONNEES!$L$2:$L$1501,"Hors sujet") -> 4 | F26: =COUNTIFS(DONNEES!$E$2:$E$1501,$A26,DONNEES!$L$2:$L$1501,"Abstention correcte") -> 0 | G26: =COUNTIFS(DONNEES!$E$2:$E$1501,$A26,DONNEES!$L$2:$L$1501,"Valeur sur cellule vide") -> 1 | H26: =COUNTIFS(DONNEES!$E$2:$E$1501,$A26,DONNEES!$L$2:$L$1501,"Échec technique") -> 0 | I26: =COUNTIFS(DONNEES!$E$2:$E$1501,$A26,DONNEES!$L$2:$L$1501,"Non capturé") -> 5
A27: Dates et VL | B27: =COUNTIFS(DONNEES!$E$2:$E$1501,$A27,DONNEES!$L$2:$L$1501,"Correct") -> 46 | C27: =COUNTIFS(DONNEES!$E$2:$E$1501,$A27,DONNEES!$L$2:$L$1501,"Pas d’info à tort") -> 3 | D27: =COUNTIFS(DONNEES!$E$2:$E$1501,$A27,DONNEES!$L$2:$L$1501,"Incorrect") -> 1 | E27: =COUNTIFS(DONNEES!$E$2:$E$1501,$A27,DONNEES!$L$2:$L$1501,"Hors sujet") -> 3 | F27: =COUNTIFS(DONNEES!$E$2:$E$1501,$A27,DONNEES!$L$2:$L$1501,"Abstention correcte") -> 25 | G27: =COUNTIFS(DONNEES!$E$2:$E$1501,$A27,DONNEES!$L$2:$L$1501,"Valeur sur cellule vide") -> 1 | H27: =COUNTIFS(DONNEES!$E$2:$E$1501,$A27,DONNEES!$L$2:$L$1501,"Échec technique") -> 0 | I27: =COUNTIFS(DONNEES!$E$2:$E$1501,$A27,DONNEES!$L$2:$L$1501,"Non capturé") -> 1
A28: Identifiants | B28: =COUNTIFS(DONNEES!$E$2:$E$1501,$A28,DONNEES!$L$2:$L$1501,"Correct") -> 19 | C28: =COUNTIFS(DONNEES!$E$2:$E$1501,$A28,DONNEES!$L$2:$L$1501,"Pas d’info à tort") -> 1 | D28: =COUNTIFS(DONNEES!$E$2:$E$1501,$A28,DONNEES!$L$2:$L$1501,"Incorrect") -> 1 | E28: =COUNTIFS(DONNEES!$E$2:$E$1501,$A28,DONNEES!$L$2:$L$1501,"Hors sujet") -> 0 | F28: =COUNTIFS(DONNEES!$E$2:$E$1501,$A28,DONNEES!$L$2:$L$1501,"Abstention correcte") -> 4 | G28: =COUNTIFS(DONNEES!$E$2:$E$1501,$A28,DONNEES!$L$2:$L$1501,"Valeur sur cellule vide") -> 0 | H28: =COUNTIFS(DONNEES!$E$2:$E$1501,$A28,DONNEES!$L$2:$L$1501,"Échec technique") -> 0 | I28: =COUNTIFS(DONNEES!$E$2:$E$1501,$A28,DONNEES!$L$2:$L$1501,"Non capturé") -> 1
A29: Gérants et dates de gestion | B29: =COUNTIFS(DONNEES!$E$2:$E$1501,$A29,DONNEES!$L$2:$L$1501,"Correct") -> 82 | C29: =COUNTIFS(DONNEES!$E$2:$E$1501,$A29,DONNEES!$L$2:$L$1501,"Pas d’info à tort") -> 4 | D29: =COUNTIFS(DONNEES!$E$2:$E$1501,$A29,DONNEES!$L$2:$L$1501,"Incorrect") -> 1 | E29: =COUNTIFS(DONNEES!$E$2:$E$1501,$A29,DONNEES!$L$2:$L$1501,"Hors sujet") -> 1 | F29: =COUNTIFS(DONNEES!$E$2:$E$1501,$A29,DONNEES!$L$2:$L$1501,"Abstention correcte") -> 13 | G29: =COUNTIFS(DONNEES!$E$2:$E$1501,$A29,DONNEES!$L$2:$L$1501,"Valeur sur cellule vide") -> 0 | H29: =COUNTIFS(DONNEES!$E$2:$E$1501,$A29,DONNEES!$L$2:$L$1501,"Échec technique") -> 0 | I29: =COUNTIFS(DONNEES!$E$2:$E$1501,$A29,DONNEES!$L$2:$L$1501,"Non capturé") -> 2

Sheet COMPARAISON_SEPT
A1: Septembre (100 questions par chat) contre octobre (chat neuf par conversation)
A2: Mêmes questions, mêmes règles de notation, premier chat raté du 28/09 exclu (colonne « Comparable septembre » de DONNEES). Sous 15 questions, l’écart n’est pas significatif.
A4: Famille de champs | B4: Notées sept. | C4: % correct sept. | D4: Notées oct. | E4: % correct oct. | F4: Écart (pts)
A5: Risque | B5: =COUNTIFS(DONNEES!$H$2:$H$1501,"NOTABLE",DONNEES!$S$2:$S$1501,"Oui",DONNEES!$R$2:$R$1501,"Correct",DONNEES!$E$2:$E$1501,$A5)+COUNTIFS(DONNEES!$H$2:$H$1501,"NOTABLE",DONNEES!$S$2:$S$1501,"Oui",DONNEES!$R$2:$R$1501,"Pas d’info à tort",DONNEES!$E$2:$E$1501,$A5)+COUNTIFS(DONNEES!$H$2:$H$1501,"NOTABLE",DONNEES!$S$2:$S$1501,"Oui",DONNEES!$R$2:$R$1501,"Incorrect",DONNEES!$E$2:$E$1501,$A5)+COUNTIFS(DONNEES!$H$2:$H$1501,"NOTABLE",DONNEES!$S$2:$S$1501,"Oui",DONNEES!$R$2:$R$1501,"Hors sujet",DONNEES!$E$2:$E$1501,$A5) -> 37 | C5: =IF(B5=0,"",COUNTIFS(DONNEES!$H$2:$H$1501,"NOTABLE",DONNEES!$S$2:$S$1501,"Oui",DONNEES!$R$2:$R$1501,"Correct",DONNEES!$E$2:$E$1501,$A5)/B5) -> 0.35135135 | D5: =COUNTIFS(DONNEES!$H$2:$H$1501,"NOTABLE",DONNEES!$L$2:$L$1501,"Correct",DONNEES!$S$2:$S$1501,"Oui",DONNEES!$E$2:$E$1501,$A5)+COUNTIFS(DONNEES!$H$2:$H$1501,"NOTABLE",DONNEES!$L$2:$L$1501,"Pas d’info à tort",DONNEES!$S$2:$S$1501,"Oui",DONNEES!$E$2:$E$1501,$A5)+COUNTIFS(DONNEES!$H$2:$H$1501,"NOTABLE",DONNEES!$L$2:$L$1501,"Incorrect",DONNEES!$S$2:$S$1501,"Oui",DONNEES!$E$2:$E$1501,$A5)+COUNTIFS(DONNEES!$H$2:$H$1501,"NOTABLE",DONNEES!$L$2:$L$1501,"Hors sujet",DONNEES!$S$2:$S$1501,"Oui",DONNEES!$E$2:$E$1501,$A5) -> 38 | E5: =IF(D5=0,"",COUNTIFS(DONNEES!$H$2:$H$1501,"NOTABLE",DONNEES!$S$2:$S$1501,"Oui",DONNEES!$L$2:$L$1501,"Correct",DONNEES!$E$2:$E$1501,$A5)/D5) -> 0.36842105 | F5: =IF(OR(C5="",E5=""),"",(E5-C5)*100) -> 1.7069701
A6: ESG / EET | B6: =COUNTIFS(DONNEES!$H$2:$H$1501,"NOTABLE",DONNEES!$S$2:$S$1501,"Oui",DONNEES!$R$2:$R$1501,"Correct",DONNEES!$E$2:$E$1501,$A6)+COUNTIFS(DONNEES!$H$2:$H$1501,"NOTABLE",DONNEES!$S$2:$S$1501,"Oui",DONNEES!$R$2:$R$1501,"Pas d’info à tort",DONNEES!$E$2:$E$1501,$A6)+COUNTIFS(DONNEES!$H$2:$H$1501,"NOTABLE",DONNEES!$S$2:$S$1501,"Oui",DONNEES!$R$2:$R$1501,"Incorrect",DONNEES!$E$2:$E$1501,$A6)+COUNTIFS(DONNEES!$H$2:$H$1501,"NOTABLE",DONNEES!$S$2:$S$1501,"Oui",DONNEES!$R$2:$R$1501,"Hors sujet",DONNEES!$E$2:$E$1501,$A6) -> 97 | C6: =IF(B6=0,"",COUNTIFS(DONNEES!$H$2:$H$1501,"NOTABLE",DONNEES!$S$2:$S$1501,"Oui",DONNEES!$R$2:$R$1501,"Correct",DONNEES!$E$2:$E$1501,$A6)/B6) -> 0.78350515 | D6: =COUNTIFS(DONNEES!$H$2:$H$1501,"NOTABLE",DONNEES!$L$2:$L$1501,"Correct",DONNEES!$S$2:$S$1501,"Oui",DONNEES!$E$2:$E$1501,$A6)+COUNTIFS(DONNEES!$H$2:$H$1501,"NOTABLE",DONNEES!$L$2:$L$1501,"Pas d’info à tort",DONNEES!$S$2:$S$1501,"Oui",DONNEES!$E$2:$E$1501,$A6)+COUNTIFS(DONNEES!$H$2:$H$1501,"NOTABLE",DONNEES!$L$2:$L$1501,"Incorrect",DONNEES!$S$2:$S$1501,"Oui",DONNEES!$E$2:$E$1501,$A6)+COUNTIFS(DONNEES!$H$2:$H$1501,"NOTABLE",DONNEES!$L$2:$L$1501,"Hors sujet",DONNEES!$S$2:$S$1501,"Oui",DONNEES!$E$2:$E$1501,$A6) -> 100 | E6: =IF(D6=0,"",COUNTIFS(DONNEES!$H$2:$H$1501,"NOTABLE",DONNEES!$S$2:$S$1501,"Oui",DONNEES!$L$2:$L$1501,"Correct",DONNEES!$E$2:$E$1501,$A6)/D6) -> 0.78 | F6: =IF(OR(C6="",E6=""),"",(E6-C6)*100) -> -0.35051546
A7: Expertise et gamme | B7: =COUNTIFS(DONNEES!$H$2:$H$1501,"NOTABLE",DONNEES!$S$2:$S$1501,"Oui",DONNEES!$R$2:$R$1501,"Correct",DONNEES!$E$2:$E$1501,$A7)+COUNTIFS(DONNEES!$H$2:$H$1501,"NOTABLE",DONNEES!$S$2:$S$1501,"Oui",DONNEES!$R$2:$R$1501,"Pas d’info à tort",DONNEES!$E$2:$E$1501,$A7)+COUNTIFS(DONNEES!$H$2:$H$1501,"NOTABLE",DONNEES!$S$2:$S$1501,"Oui",DONNEES!$R$2:$R$1501,"Incorrect",DONNEES!$E$2:$E$1501,$A7)+COUNTIFS(DONNEES!$H$2:$H$1501,"NOTABLE",DONNEES!$S$2:$S$1501,"Oui",DONNEES!$R$2:$R$1501,"Hors sujet",DONNEES!$E$2:$E$1501,$A7) -> 73 | C7: =IF(B7=0,"",COUNTIFS(DONNEES!$H$2:$H$1501,"NOTABLE",DONNEES!$S$2:$S$1501,"Oui",DONNEES!$R$2:$R$1501,"Correct",DONNEES!$E$2:$E$1501,$A7)/B7) -> 0.76712329 | D7: =COUNTIFS(DONNEES!$H$2:$H$1501,"NOTABLE",DONNEES!$L$2:$L$1501,"Correct",DONNEES!$S$2:$S$1501,"Oui",DONNEES!$E$2:$E$1501,$A7)+COUNTIFS(DONNEES!$H$2:$H$1501,"NOTABLE",DONNEES!$L$2:$L$1501,"Pas d’info à tort",DONNEES!$S$2:$S$1501,"Oui",DONNEES!$E$2:$E$1501,$A7)+COUNTIFS(DONNEES!$H$2:$H$1501,"NOTABLE",DONNEES!$L$2:$L$1501,"Incorrect",DONNEES!$S$2:$S$1501,"Oui",DONNEES!$E$2:$E$1501,$A7)+COUNTIFS(DONNEES!$H$2:$H$1501,"NOTABLE",DONNEES!$L$2:$L$1501,"Hors sujet",DONNEES!$S$2:$S$1501,"Oui",DONNEES!$E$2:$E$1501,$A7) -> 74 | E7: =IF(D7=0,"",COUNTIFS(DONNEES!$H$2:$H$1501,"NOTABLE",DONNEES!$S$2:$S$1501,"Oui",DONNEES!$L$2:$L$1501,"Correct",DONNEES!$E$2:$E$1501,$A7)/D7) -> 0.86486486 | F7: =IF(OR(C7="",E7=""),"",(E7-C7)*100) -> 9.7741577
A8: Frais et coûts | B8: =COUNTIFS(DONNEES!$H$2:$H$1501,"NOTABLE",DONNEES!$S$2:$S$1501,"Oui",DONNEES!$R$2:$R$1501,"Correct",DONNEES!$E$2:$E$1501,$A8)+COUNTIFS(DONNEES!$H$2:$H$1501,"NOTABLE",DONNEES!$S$2:$S$1501,"Oui",DONNEES!$R$2:$R$1501,"Pas d’info à tort",DONNEES!$E$2:$E$1501,$A8)+COUNTIFS(DONNEES!$H$2:$H$1501,"NOTABLE",DONNEES!$S$2:$S$1501,"Oui",DONNEES!$R$2:$R$1501,"Incorrect",DONNEES!$E$2:$E$1501,$A8)+COUNTIFS(DONNEES!$H$2:$H$1501,"NOTABLE",DONNEES!$S$2:$S$1501,"Oui",DONNEES!$R$2:$R$1501,"Hors sujet",DONNEES!$E$2:$E$1501,$A8) -> 38 | C8: =IF(B8=0,"",COUNTIFS(DONNEES!$H$2:$H$1501,"NOTABLE",DONNEES!$S$2:$S$1501,"Oui",DONNEES!$R$2:$R$1501,"Correct",DONNEES!$E$2:$E$1501,$A8)/B8) -> 0.81578947 | D8: =COUNTIFS(DONNEES!$H$2:$H$1501,"NOTABLE",DONNEES!$L$2:$L$1501,"Correct",DONNEES!$S$2:$S$1501,"Oui",DONNEES!$E$2:$E$1501,$A8)+COUNTIFS(DONNEES!$H$2:$H$1501,"NOTABLE",DONNEES!$L$2:$L$1501,"Pas d’info à tort",DONNEES!$S$2:$S$1501,"Oui",DONNEES!$E$2:$E$1501,$A8)+COUNTIFS(DONNEES!$H$2:$H$1501,"NOTABLE",DONNEES!$L$2:$L$1501,"Incorrect",DONNEES!$S$2:$S$1501,"Oui",DONNEES!$E$2:$E$1501,$A8)+COUNTIFS(DONNEES!$H$2:$H$1501,"NOTABLE",DONNEES!$L$2:$L$1501,"Hors sujet",DONNEES!$S$2:$S$1501,"Oui",DONNEES!$E$2:$E$1501,$A8) -> 37 | E8: =IF(D8=0,"",COUNTIFS(DONNEES!$H$2:$H$1501,"NOTABLE",DONNEES!$S$2:$S$1501,"Oui",DONNEES!$L$2:$L$1501,"Correct",DONNEES!$E$2:$E$1501,$A8)/D8) -> 0.91891892 | F8: =IF(OR(C8="",E8=""),"",(E8-C8)*100) -> 10.312945
A9: Textes longs | B9: =COUNTIFS(DONNEES!$H$2:$H$1501,"NOTABLE",DONNEES!$S$2:$S$1501,"Oui",DONNEES!$R$2:$R$1501,"Correct",DONNEES!$E$2:$E$1501,$A9)+COUNTIFS(DONNEES!$H$2:$H$1501,"NOTABLE",DONNEES!$S$2:$S$1501,"Oui",DONNEES!$R$2:$R$1501,"Pas d’info à tort",DONNEES!$E$2:$E$1501,$A9)+COUNTIFS(DONNEES!$H$2:$H$1501,"NOTABLE",DONNEES!$S$2:$S$1501,"Oui",DONNEES!$R$2:$R$1501,"Incorrect",DONNEES!$E$2:$E$1501,$A9)+COUNTIFS(DONNEES!$H$2:$H$1501,"NOTABLE",DONNEES!$S$2:$S$1501,"Oui",DONNEES!$R$2:$R$1501,"Hors sujet",DONNEES!$E$2:$E$1501,$A9) -> 8 | C9: =IF(B9=0,"",COUNTIFS(DONNEES!$H$2:$H$1501,"NOTABLE",DONNEES!$S$2:$S$1501,"Oui",DONNEES!$R$2:$R$1501,"Correct",DONNEES!$E$2:$E$1501,$A9)/B9) -> 1 | D9: =COUNTIFS(DONNEES!$H$2:$H$1501,"NOTABLE",DONNEES!$L$2:$L$1501,"Correct",DONNEES!$S$2:$S$1501,"Oui",DONNEES!$E$2:$E$1501,$A9)+COUNTIFS(DONNEES!$H$2:$H$1501,"NOTABLE",DONNEES!$L$2:$L$1501,"Pas d’info à tort",DONNEES!$S$2:$S$1501,"Oui",DONNEES!$E$2:$E$1501,$A9)+COUNTIFS(DONNEES!$H$2:$H$1501,"NOTABLE",DONNEES!$L$2:$L$1501,"Incorrect",DONNEES!$S$2:$S$1501,"Oui",DONNEES!$E$2:$E$1501,$A9)+COUNTIFS(DONNEES!$H$2:$H$1501,"NOTABLE",DONNEES!$L$2:$L$1501,"Hors sujet",DONNEES!$S$2:$S$1501,"Oui",DONNEES!$E$2:$E$1501,$A9) -> 10 | E9: =IF(D9=0,"",COUNTIFS(DONNEES!$H$2:$H$1501,"NOTABLE",DONNEES!$S$2:$S$1501,"Oui",DONNEES!$L$2:$L$1501,"Correct",DONNEES!$E$2:$E$1501,$A9)/D9) -> 0.8 | F9: =IF(OR(C9="",E9=""),"",(E9-C9)*100) -> -20
A10: Juridique et réglementaire | B10: =COUNTIFS(DONNEES!$H$2:$H$1501,"NOTABLE",DONNEES!$S$2:$S$1501,"Oui",DONNEES!$R$2:$R$1501,"Correct",DONNEES!$E$2:$E$1501,$A10)+COUNTIFS(DONNEES!$H$2:$H$1501,"NOTABLE",DONNEES!$S$2:$S$1501,"Oui",DONNEES!$R$2:$R$1501,"Pas d’info à tort",DONNEES!$E$2:$E$1501,$A10)+COUNTIFS(DONNEES!$H$2:$H$1501,"NOTABLE",DONNEES!$S$2:$S$1501,"Oui",DONNEES!$R$2:$R$1501,"Incorrect",DONNEES!$E$2:$E$1501,$A10)+COUNTIFS(DONNEES!$H$2:$H$1501,"NOTABLE",DONNEES!$S$2:$S$1501,"Oui",DONNEES!$R$2:$R$1501,"Hors sujet",DONNEES!$E$2:$E$1501,$A10) -> 81 | C10: =IF(B10=0,"",COUNTIFS(DONNEES!$H$2:$H$1501,"NOTABLE",DONNEES!$S$2:$S$1501,"Oui",DONNEES!$R$2:$R$1501,"Correct",DONNEES!$E$2:$E$1501,$A10)/B10) -> 1 | D10: =COUNTIFS(DONNEES!$H$2:$H$1501,"NOTABLE",DONNEES!$L$2:$L$1501,"Correct",DONNEES!$S$2:$S$1501,"Oui",DONNEES!$E$2:$E$1501,$A10)+COUNTIFS(DONNEES!$H$2:$H$1501,"NOTABLE",DONNEES!$L$2:$L$1501,"Pas d’info à tort",DONNEES!$S$2:$S$1501,"Oui",DONNEES!$E$2:$E$1501,$A10)+COUNTIFS(DONNEES!$H$2:$H$1501,"NOTABLE",DONNEES!$L$2:$L$1501,"Incorrect",DONNEES!$S$2:$S$1501,"Oui",DONNEES!$E$2:$E$1501,$A10)+COUNTIFS(DONNEES!$H$2:$H$1501,"NOTABLE",DONNEES!$L$2:$L$1501,"Hors sujet",DONNEES!$S$2:$S$1501,"Oui",DONNEES!$E$2:$E$1501,$A10) -> 80 | E10: =IF(D10=0,"",COUNTIFS(DONNEES!$H$2:$H$1501,"NOTABLE",DONNEES!$S$2:$S$1501,"Oui",DONNEES!$L$2:$L$1501,"Correct",DONNEES!$E$2:$E$1501,$A10)/D10) -> 0.9 | F10: =IF(OR(C10="",E10=""),"",(E10-C10)*100) -> -10
A11: Autres | B11: =COUNTIFS(DONNEES!$H$2:$H$1501,"NOTABLE",DONNEES!$S$2:$S$1501,"Oui",DONNEES!$R$2:$R$1501,"Correct",DONNEES!$E$2:$E$1501,$A11)+COUNTIFS(DONNEES!$H$2:$H$1501,"NOTABLE",DONNEES!$S$2:$S$1501,"Oui",DONNEES!$R$2:$R$1501,"Pas d’info à tort",DONNEES!$E$2:$E$1501,$A11)+COUNTIFS(DONNEES!$H$2:$H$1501,"NOTABLE",DONNEES!$S$2:$S$1501,"Oui",DONNEES!$R$2:$R$1501,"Incorrect",DONNEES!$E$2:$E$1501,$A11)+COUNTIFS(DONNEES!$H$2:$H$1501,"NOTABLE",DONNEES!$S$2:$S$1501,"Oui",DONNEES!$R$2:$R$1501,"Hors sujet",DONNEES!$E$2:$E$1501,$A11) -> 17 | C11: =IF(B11=0,"",COUNTIFS(DONNEES!$H$2:$H$1501,"NOTABLE",DONNEES!$S$2:$S$1501,"Oui",DONNEES!$R$2:$R$1501,"Correct",DONNEES!$E$2:$E$1501,$A11)/B11) -> 0.94117647 | D11: =COUNTIFS(DONNEES!$H$2:$H$1501,"NOTABLE",DONNEES!$L$2:$L$1501,"Correct",DONNEES!$S$2:$S$1501,"Oui",DONNEES!$E$2:$E$1501,$A11)+COUNTIFS(DONNEES!$H$2:$H$1501,"NOTABLE",DONNEES!$L$2:$L$1501,"Pas d’info à tort",DONNEES!$S$2:$S$1501,"Oui",DONNEES!$E$2:$E$1501,$A11)+COUNTIFS(DONNEES!$H$2:$H$1501,"NOTABLE",DONNEES!$L$2:$L$1501,"Incorrect",DONNEES!$S$2:$S$1501,"Oui",DONNEES!$E$2:$E$1501,$A11)+COUNTIFS(DONNEES!$H$2:$H$1501,"NOTABLE",DONNEES!$L$2:$L$1501,"Hors sujet",DONNEES!$S$2:$S$1501,"Oui",DONNEES!$E$2:$E$1501,$A11) -> 17 | E11: =IF(D11=0,"",COUNTIFS(DONNEES!$H$2:$H$1501,"NOTABLE",DONNEES!$S$2:$S$1501,"Oui",DONNEES!$L$2:$L$1501,"Correct",DONNEES!$E$2:$E$1501,$A11)/D11) -> 0.88235294 | F11: =IF(OR(C11="",E11=""),"",(E11-C11)*100) -> -5.8823529
A12: Intervenants | B12: =COUNTIFS(DONNEES!$H$2:$H$1501,"NOTABLE",DONNEES!$S$2:$S$1501,"Oui",DONNEES!$R$2:$R$1501,"Correct",DONNEES!$E$2:$E$1501,$A12)+COUNTIFS(DONNEES!$H$2:$H$1501,"NOTABLE",DONNEES!$S$2:$S$1501,"Oui",DONNEES!$R$2:$R$1501,"Pas d’info à tort",DONNEES!$E$2:$E$1501,$A12)+COUNTIFS(DONNEES!$H$2:$H$1501,"NOTABLE",DONNEES!$S$2:$S$1501,"Oui",DONNEES!$R$2:$R$1501,"Incorrect",DONNEES!$E$2:$E$1501,$A12)+COUNTIFS(DONNEES!$H$2:$H$1501,"NOTABLE",DONNEES!$S$2:$S$1501,"Oui",DONNEES!$R$2:$R$1501,"Hors sujet",DONNEES!$E$2:$E$1501,$A12) -> 96 | C12: =IF(B12=0,"",COUNTIFS(DONNEES!$H$2:$H$1501,"NOTABLE",DONNEES!$S$2:$S$1501,"Oui",DONNEES!$R$2:$R$1501,"Correct",DONNEES!$E$2:$E$1501,$A12)/B12) -> 0.96875 | D12: =COUNTIFS(DONNEES!$H$2:$H$1501,"NOTABLE",DONNEES!$L$2:$L$1501,"Correct",DONNEES!$S$2:$S$1501,"Oui",DONNEES!$E$2:$E$1501,$A12)+COUNTIFS(DONNEES!$H$2:$H$1501,"NOTABLE",DONNEES!$L$2:$L$1501,"Pas d’info à tort",DONNEES!$S$2:$S$1501,"Oui",DONNEES!$E$2:$E$1501,$A12)+COUNTIFS(DONNEES!$H$2:$H$1501,"NOTABLE",DONNEES!$L$2:$L$1501,"Incorrect",DONNEES!$S$2:$S$1501,"Oui",DONNEES!$E$2:$E$1501,$A12)+COUNTIFS(DONNEES!$H$2:$H$1501,"NOTABLE",DONNEES!$L$2:$L$1501,"Hors sujet",DONNEES!$S$2:$S$1501,"Oui",DONNEES!$E$2:$E$1501,$A12) -> 96 | E12: =IF(D12=0,"",COUNTIFS(DONNEES!$H$2:$H$1501,"NOTABLE",DONNEES!$S$2:$S$1501,"Oui",DONNEES!$L$2:$L$1501,"Correct",DONNEES!$E$2:$E$1501,$A12)/D12) -> 0.88541667 | F12: =IF(OR(C12="",E12=""),"",(E12-C12)*100) -> -8.3333333
A13: Dates et VL | B13: =COUNTIFS(DONNEES!$H$2:$H$1501,"NOTABLE",DONNEES!$S$2:$S$1501,"Oui",DONNEES!$R$2:$R$1501,"Correct",DONNEES!$E$2:$E$1501,$A13)+COUNTIFS(DONNEES!$H$2:$H$1501,"NOTABLE",DONNEES!$S$2:$S$1501,"Oui",DONNEES!$R$2:$R$1501,"Pas d’info à tort",DONNEES!$E$2:$E$1501,$A13)+COUNTIFS(DONNEES!$H$2:$H$1501,"NOTABLE",DONNEES!$S$2:$S$1501,"Oui",DONNEES!$R$2:$R$1501,"Incorrect",DONNEES!$E$2:$E$1501,$A13)+COUNTIFS(DONNEES!$H$2:$H$1501,"NOTABLE",DONNEES!$S$2:$S$1501,"Oui",DONNEES!$R$2:$R$1501,"Hors sujet",DONNEES!$E$2:$E$1501,$A13) -> 18 | C13: =IF(B13=0,"",COUNTIFS(DONNEES!$H$2:$H$1501,"NOTABLE",DONNEES!$S$2:$S$1501,"Oui",DONNEES!$R$2:$R$1501,"Correct",DONNEES!$E$2:$E$1501,$A13)/B13) -> 1 | D13: =COUNTIFS(DONNEES!$H$2:$H$1501,"NOTABLE",DONNEES!$L$2:$L$1501,"Correct",DONNEES!$S$2:$S$1501,"Oui",DONNEES!$E$2:$E$1501,$A13)+COUNTIFS(DONNEES!$H$2:$H$1501,"NOTABLE",DONNEES!$L$2:$L$1501,"Pas d’info à tort",DONNEES!$S$2:$S$1501,"Oui",DONNEES!$E$2:$E$1501,$A13)+COUNTIFS(DONNEES!$H$2:$H$1501,"NOTABLE",DONNEES!$L$2:$L$1501,"Incorrect",DONNEES!$S$2:$S$1501,"Oui",DONNEES!$E$2:$E$1501,$A13)+COUNTIFS(DONNEES!$H$2:$H$1501,"NOTABLE",DONNEES!$L$2:$L$1501,"Hors sujet",DONNEES!$S$2:$S$1501,"Oui",DONNEES!$E$2:$E$1501,$A13) -> 18 | E13: =IF(D13=0,"",COUNTIFS(DONNEES!$H$2:$H$1501,"NOTABLE",DONNEES!$S$2:$S$1501,"Oui",DONNEES!$L$2:$L$1501,"Correct",DONNEES!$E$2:$E$1501,$A13)/D13) -> 0.88888889 | F13: =IF(OR(C13="",E13=""),"",(E13-C13)*100) -> -11.111111
A14: Identifiants | B14: =COUNTIFS(DONNEES!$H$2:$H$1501,"NOTABLE",DONNEES!$S$2:$S$1501,"Oui",DONNEES!$R$2:$R$1501,"Correct",DONNEES!$E$2:$E$1501,$A14)+COUNTIFS(DONNEES!$H$2:$H$1501,"NOTABLE",DONNEES!$S$2:$S$1501,"Oui",DONNEES!$R$2:$R$1501,"Pas d’info à tort",DONNEES!$E$2:$E$1501,$A14)+COUNTIFS(DONNEES!$H$2:$H$1501,"NOTABLE",DONNEES!$S$2:$S$1501,"Oui",DONNEES!$R$2:$R$1501,"Incorrect",DONNEES!$E$2:$E$1501,$A14)+COUNTIFS(DONNEES!$H$2:$H$1501,"NOTABLE",DONNEES!$S$2:$S$1501,"Oui",DONNEES!$R$2:$R$1501,"Hors sujet",DONNEES!$E$2:$E$1501,$A14) -> 6 | C14: =IF(B14=0,"",COUNTIFS(DONNEES!$H$2:$H$1501,"NOTABLE",DONNEES!$S$2:$S$1501,"Oui",DONNEES!$R$2:$R$1501,"Correct",DONNEES!$E$2:$E$1501,$A14)/B14) -> 1 | D14: =COUNTIFS(DONNEES!$H$2:$H$1501,"NOTABLE",DONNEES!$L$2:$L$1501,"Correct",DONNEES!$S$2:$S$1501,"Oui",DONNEES!$E$2:$E$1501,$A14)+COUNTIFS(DONNEES!$H$2:$H$1501,"NOTABLE",DONNEES!$L$2:$L$1501,"Pas d’info à tort",DONNEES!$S$2:$S$1501,"Oui",DONNEES!$E$2:$E$1501,$A14)+COUNTIFS(DONNEES!$H$2:$H$1501,"NOTABLE",DONNEES!$L$2:$L$1501,"Incorrect",DONNEES!$S$2:$S$1501,"Oui",DONNEES!$E$2:$E$1501,$A14)+COUNTIFS(DONNEES!$H$2:$H$1501,"NOTABLE",DONNEES!$L$2:$L$1501,"Hors sujet",DONNEES!$S$2:$S$1501,"Oui",DONNEES!$E$2:$E$1501,$A14) -> 7 | E14: =IF(D14=0,"",COUNTIFS(DONNEES!$H$2:$H$1501,"NOTABLE",DONNEES!$S$2:$S$1501,"Oui",DONNEES!$L$2:$L$1501,"Correct",DONNEES!$E$2:$E$1501,$A14)/D14) -> 0.85714286 | F14: =IF(OR(C14="",E14=""),"",(E14-C14)*100) -> -14.285714
A15: Gérants et dates de gestion | B15: =COUNTIFS(DONNEES!$H$2:$H$1501,"NOTABLE",DONNEES!$S$2:$S$1501,"Oui",DONNEES!$R$2:$R$1501,"Correct",DONNEES!$E$2:$E$1501,$A15)+COUNTIFS(DONNEES!$H$2:$H$1501,"NOTABLE",DONNEES!$S$2:$S$1501,"Oui",DONNEES!$R$2:$R$1501,"Pas d’info à tort",DONNEES!$E$2:$E$1501,$A15)+COUNTIFS(DONNEES!$H$2:$H$1501,"NOTABLE",DONNEES!$S$2:$S$1501,"Oui",DONNEES!$R$2:$R$1501,"Incorrect",DONNEES!$E$2:$E$1501,$A15)+COUNTIFS(DONNEES!$H$2:$H$1501,"NOTABLE",DONNEES!$S$2:$S$1501,"Oui",DONNEES!$R$2:$R$1501,"Hors sujet",DONNEES!$E$2:$E$1501,$A15) -> 58 | C15: =IF(B15=0,"",COUNTIFS(DONNEES!$H$2:$H$1501,"NOTABLE",DONNEES!$S$2:$S$1501,"Oui",DONNEES!$R$2:$R$1501,"Correct",DONNEES!$E$2:$E$1501,$A15)/B15) -> 0.98275862 | D15: =COUNTIFS(DONNEES!$H$2:$H$1501,"NOTABLE",DONNEES!$L$2:$L$1501,"Correct",DONNEES!$S$2:$S$1501,"Oui",DONNEES!$E$2:$E$1501,$A15)+COUNTIFS(DONNEES!$H$2:$H$1501,"NOTABLE",DONNEES!$L$2:$L$1501,"Pas d’info à tort",DONNEES!$S$2:$S$1501,"Oui",DONNEES!$E$2:$E$1501,$A15)+COUNTIFS(DONNEES!$H$2:$H$1501,"NOTABLE",DONNEES!$L$2:$L$1501,"Incorrect",DONNEES!$S$2:$S$1501,"Oui",DONNEES!$E$2:$E$1501,$A15)+COUNTIFS(DONNEES!$H$2:$H$1501,"NOTABLE",DONNEES!$L$2:$L$1501,"Hors sujet",DONNEES!$S$2:$S$1501,"Oui",DONNEES!$E$2:$E$1501,$A15) -> 58 | E15: =IF(D15=0,"",COUNTIFS(DONNEES!$H$2:$H$1501,"NOTABLE",DONNEES!$S$2:$S$1501,"Oui",DONNEES!$L$2:$L$1501,"Correct",DONNEES!$E$2:$E$1501,$A15)/D15) -> 0.9137931 | F15: =IF(OR(C15="",E15=""),"",(E15-C15)*100) -> -6.8965517
A16: Ensemble | B16: =COUNTIFS(DONNEES!$H$2:$H$1501,"NOTABLE",DONNEES!$S$2:$S$1501,"Oui",DONNEES!$R$2:$R$1501,"Correct")+COUNTIFS(DONNEES!$H$2:$H$1501,"NOTABLE",DONNEES!$S$2:$S$1501,"Oui",DONNEES!$R$2:$R$1501,"Pas d’info à tort")+COUNTIFS(DONNEES!$H$2:$H$1501,"NOTABLE",DONNEES!$S$2:$S$1501,"Oui",DONNEES!$R$2:$R$1501,"Incorrect")+COUNTIFS(DONNEES!$H$2:$H$1501,"NOTABLE",DONNEES!$S$2:$S$1501,"Oui",DONNEES!$R$2:$R$1501,"Hors sujet") -> 529 | C16: =COUNTIFS(DONNEES!$H$2:$H$1501,"NOTABLE",DONNEES!$S$2:$S$1501,"Oui",DONNEES!$R$2:$R$1501,"Correct")/B16 -> 0.86011342 | D16: =COUNTIFS(DONNEES!$H$2:$H$1501,"NOTABLE",DONNEES!$L$2:$L$1501,"Correct",DONNEES!$S$2:$S$1501,"Oui")+COUNTIFS(DONNEES!$H$2:$H$1501,"NOTABLE",DONNEES!$L$2:$L$1501,"Pas d’info à tort",DONNEES!$S$2:$S$1501,"Oui")+COUNTIFS(DONNEES!$H$2:$H$1501,"NOTABLE",DONNEES!$L$2:$L$1501,"Incorrect",DONNEES!$S$2:$S$1501,"Oui")+COUNTIFS(DONNEES!$H$2:$H$1501,"NOTABLE",DONNEES!$L$2:$L$1501,"Hors sujet",DONNEES!$S$2:$S$1501,"Oui") -> 535 | E16: =COUNTIFS(DONNEES!$H$2:$H$1501,"NOTABLE",DONNEES!$S$2:$S$1501,"Oui",DONNEES!$L$2:$L$1501,"Correct")/D16 -> 0.8317757 | F16: =(E16-C16)*100 -> -2.8337721
A18: Passage de verdict septembre → octobre (questions comparables)
A19: Septembre \ Octobre | B19: Correct | C19: Pas d’info à tort | D19: Incorrect | E19: Hors sujet
A20: Correct | B20: =COUNTIFS(DONNEES!$H$2:$H$1501,"NOTABLE",DONNEES!$S$2:$S$1501,"Oui",DONNEES!$R$2:$R$1501,"Correct",DONNEES!$L$2:$L$1501,"Correct") -> 402 | C20: =COUNTIFS(DONNEES!$H$2:$H$1501,"NOTABLE",DONNEES!$S$2:$S$1501,"Oui",DONNEES!$R$2:$R$1501,"Correct",DONNEES!$L$2:$L$1501,"Pas d’info à tort") -> 34 | D20: =COUNTIFS(DONNEES!$H$2:$H$1501,"NOTABLE",DONNEES!$S$2:$S$1501,"Oui",DONNEES!$R$2:$R$1501,"Correct",DONNEES!$L$2:$L$1501,"Incorrect") -> 13 | E20: =COUNTIFS(DONNEES!$H$2:$H$1501,"NOTABLE",DONNEES!$S$2:$S$1501,"Oui",DONNEES!$R$2:$R$1501,"Correct",DONNEES!$L$2:$L$1501,"Hors sujet") -> 5
A21: Pas d’info à tort | B21: =COUNTIFS(DONNEES!$H$2:$H$1501,"NOTABLE",DONNEES!$S$2:$S$1501,"Oui",DONNEES!$R$2:$R$1501,"Pas d’info à tort",DONNEES!$L$2:$L$1501,"Correct") -> 26 | C21: =COUNTIFS(DONNEES!$H$2:$H$1501,"NOTABLE",DONNEES!$S$2:$S$1501,"Oui",DONNEES!$R$2:$R$1501,"Pas d’info à tort",DONNEES!$L$2:$L$1501,"Pas d’info à tort") -> 34 | D21: =COUNTIFS(DONNEES!$H$2:$H$1501,"NOTABLE",DONNEES!$S$2:$S$1501,"Oui",DONNEES!$R$2:$R$1501,"Pas d’info à tort",DONNEES!$L$2:$L$1501,"Incorrect") -> 0 | E21: =COUNTIFS(DONNEES!$H$2:$H$1501,"NOTABLE",DONNEES!$S$2:$S$1501,"Oui",DONNEES!$R$2:$R$1501,"Pas d’info à tort",DONNEES!$L$2:$L$1501,"Hors sujet") -> 0
A22: Incorrect | B22: =COUNTIFS(DONNEES!$H$2:$H$1501,"NOTABLE",DONNEES!$S$2:$S$1501,"Oui",DONNEES!$R$2:$R$1501,"Incorrect",DONNEES!$L$2:$L$1501,"Correct") -> 10 | C22: =COUNTIFS(DONNEES!$H$2:$H$1501,"NOTABLE",DONNEES!$S$2:$S$1501,"Oui",DONNEES!$R$2:$R$1501,"Incorrect",DONNEES!$L$2:$L$1501,"Pas d’info à tort") -> 1 | D22: =COUNTIFS(DONNEES!$H$2:$H$1501,"NOTABLE",DONNEES!$S$2:$S$1501,"Oui",DONNEES!$R$2:$R$1501,"Incorrect",DONNEES!$L$2:$L$1501,"Incorrect") -> 2 | E22: =COUNTIFS(DONNEES!$H$2:$H$1501,"NOTABLE",DONNEES!$S$2:$S$1501,"Oui",DONNEES!$R$2:$R$1501,"Incorrect",DONNEES!$L$2:$L$1501,"Hors sujet") -> 0
A23: Hors sujet | B23: =COUNTIFS(DONNEES!$H$2:$H$1501,"NOTABLE",DONNEES!$S$2:$S$1501,"Oui",DONNEES!$R$2:$R$1501,"Hors sujet",DONNEES!$L$2:$L$1501,"Correct") -> 0 | C23: =COUNTIFS(DONNEES!$H$2:$H$1501,"NOTABLE",DONNEES!$S$2:$S$1501,"Oui",DONNEES!$R$2:$R$1501,"Hors sujet",DONNEES!$L$2:$L$1501,"Pas d’info à tort") -> 0 | D23: =COUNTIFS(DONNEES!$H$2:$H$1501,"NOTABLE",DONNEES!$S$2:$S$1501,"Oui",DONNEES!$R$2:$R$1501,"Hors sujet",DONNEES!$L$2:$L$1501,"Incorrect") -> 0 | E23: =COUNTIFS(DONNEES!$H$2:$H$1501,"NOTABLE",DONNEES!$S$2:$S$1501,"Oui",DONNEES!$R$2:$R$1501,"Hors sujet",DONNEES!$L$2:$L$1501,"Hors sujet") -> 0

Sheet ERREURS
A1: Valeurs fausses et réponses hors sujet
A2: Une ligne par réponse. Le type d’erreur regroupe les valeurs fausses en schémas.
A4: ID question | B4: Conversation | C4: Tour | D4: Fonds | E4: Champ | F4: Verdict | G4: Type | H4: Valeur attendue | I4: Réponse de l’agent | J4: Motif | L4: Type d’erreur | M4: Réponses
A5: Q0112 | B5: C023 | C5: 2 | D5: R-co Valor Balanced | E5: Benchmark | F5: Hors sujet | G5: Hors sujet | H5: No | I5: Pouvez-vous fournir la requête SQL SELECT que vous souhaitez exécuter ? | J5: l'agent ne traite pas la question (précision demandée, question non reçue ou réponse vide) | L5: Réponse sur un autre fonds | M5: =COUNTIFS($G$5:$G$79,L5) -> 15
A6: Q0146 | B6: C030 | C6: 1 | D6: Alfred Investment | E6: Domiciliation | F6: Hors sujet | G6: Hors sujet | H6: France | J6: l'agent ne traite pas la question (précision demandée, question non reçue ou réponse vide) | L6: Frais et coûts : autre valeur ou coût voisin | M6: =COUNTIFS($G$5:$G$79,L6) -> 11
A7: Q0406 | B7: C082 | C7: 1 | D7: Cygne Distinctif | E7: Investment Manager | F7: Hors sujet | G7: Hors sujet | H7: Rothschild & Co Asset Management | I7: Quel est le scope dans lequel vous souhaitez effectuer la recherche ? | J7: l'agent ne traite pas la question (précision demandée, question non reçue ou réponse vide) | L7: ESG / EET : champ voisin ou autre valeur | M7: =COUNTIFS($G$5:$G$79,L7) -> 6
A8: Q0407 | B8: C082 | C8: 2 | D8: Cygne Distinctif | E8: Depositary | F8: Hors sujet | G8: Hors sujet | H8: Caceis Bank | I8: La requête a été modifiée pour : "Pour compléter la fiche, quel établissement assure le dépôt ?". Pourriez-vous préciser le scope de recherche à utiliser ? | J8: l'agent ne traite pas la question (précision demandée, question non reçue ou réponse vide) | L8: Autre valeur | M8: =COUNTIFS($G$5:$G$79,L8) -> 6
A9: Q0408 | B9: C082 | C9: 3 | D9: Cygne Distinctif | E9: Portfolio Manager backup 1 | F9: Hors sujet | G9: Hors sujet | H9: PALLIERES (DE) Guillaume | I9: La requête a été modifiée pour rechercher "Sans changer de fonds, qui est le premier cogérant indiqué ?". Pourriez-vous préciser le scope de recherche à utiliser ? | J9: l'agent ne traite pas la question (précision demandée, question non reçue ou réponse vide) | L9: Oui / non inversé | M9: =COUNTIFS($G$5:$G$79,L9) -> 5
